Workbook

Sheet 說明
A1: 台股觀察表 · 架構範本 v2
B3: 資料由 GitHub Actions 自動更新。Raw 分頁為管線寫入區，請勿手改。
A5: v2 改了什麼
B6: Raw_Q 從 32 欄砍到 14 欄。只留下你指定的指標，以及計算這些指標所必需的原始欄位。
B7: 刪掉的是：營益率、FCF、杜邦拆解、ROIC、淨負債、有效稅率、adj_gap、PE 百分位、2年CAGR、
B8: 近4季平均加速度、EPS加速度、年度加速度 —— 這些都是我加的，不是你要的。
B9: 新增：殖利率（需要 Raw_Q 的 dps 欄）。
A11: Raw_Q 的 14 欄，每一欄都有用途
B12: ticker / period / fy / fq / period_end → 鍵值與期別對齊
B13: is_est / est_source → 區分實際與預估，避免預估污染歷史
B14: eps_basis → EPS 口徑標記：street=市場口徑；gaap=四層來源
B15: 全部失敗時的降級，PE/PEG 會失真，須注意
B16: revenue → 營收成長率、毛利率分母
B17: gross_profit → 毛利率分子
B18: eps_diluted_adj → EPS、PE、PEG、EPS成長率
B19: shares_diluted → 反推 ROE 淨利、ROE_Forward 的每股淨值
B20: total_equity → ROE 分母
B21: dps → 殖利率
B22: price_at_end → 歷史 PE、PEG_T、歷史殖利率
A24: 抓不到的東西（誠實說明）
B25: Adjusted 淨利：沒有任何 API 提供。它不是損益表項目，只存在於公司財報的 non-GAAP 對帳附註。
B26: 本表用「逐季 adjusted EPS × 稀釋股數」反推，逐季相乘再加總比用單一股數準，但仍是近似值。
B27: Adjusted EPS 本身拿得到，但不是從損益表，是從「歷史財報實際值」那類端點的 actual EPS。
B28: fy / fq：多數來源不直接提供公司自己的財年標號，要從 period_end 推算。
B29: 歷史的 Forward PE（每一年當時的前瞻本益比）：拿不到，歷史分析師共識一般不留存。
A31: 年 與 季 分在哪裡
B32: 年度層 → 「年度檢視」：每一列＝一個完整財年，由 Raw_Q 的季度資料 rollup 而來。
B33: 季度層 → 「季度檢視」：每一列＝一個財季，另有年 × 季矩陣做季節可比的閱讀。
B34: 橫向層 → 「Dashboard」：每一列＝一檔股票，用來跨標的比較與篩選。
B35: 三層共用同一份 Raw_Q，年度值永遠等於該年四季加總，不會有兩套打架的資料。
A37: 加速度只做在季度層
B38: 季度成長率(QoQ) ＝ 本季營收 ÷ 上一季營收 − 1。
B39: 加速度(pp) ＝ 本季QoQ − 上一季QoQ。字面上就是「這季成長率有沒有比上季快」。
B40: 但這一欄會被季節性主宰：旺季 QoQ 天生高、淡季天生低，每年在同一季重複同樣的震盪。
B41: 同期加速度(pp) ＝ 本季QoQ − 去年同一財季的QoQ。一樣在比季度成長率，但基準換成
B42: 去年同一季，季節性自動抵消。實務上這一欄才有訊號，建議以它為主、加速度當參考。
B43: 年度層刻意不放加速度：一年才一個點，訊號遲鈍到失去意義。
A45: 口徑
B46: EPS / PE / PEG / EPS成長 → Adjusted，與分析師預估和市場定價同口徑。
B47: ROE → 分子用 adjusted EPS 反推的淨利，分母用 GAAP 股東權益（你選的口徑）。
B48: 注意：這代表 ROE 數字會與各大財經網站（多用 GAAP 淨利）不同，這是刻意的。
A50: 顏色慣例
B51: 藍字＝你手動輸入 ｜ 黑字＝公式 ｜ 綠字＝跨分頁連結 ｜ 黃底＝資料管線寫入區，請勿手改
A53: 新增一檔股票
B54: ① Tickers 第 2~21 列往下打一列 → ② 重跑資料管線 → ③ Excel 按「資料 → 全部重新整理」

Sheet Dashboard
A1: 基本 | E1: 毛利率 | G1: ROE | J1: 成長 | N1: 預估 | O1: 估值 | S1: 殖利率 | U1: 參考
A2: Ticker | B2: 公司 | C2: 等級 | D2: 股價 | E2: 毛利率 | F2: 5年平均 | G2: ROE_TTM | H2: ROE_5年平均 | I2: ROE Forward | J2: 營收QoQ | K2: 加速度(%) | L2: 動能判讀 | M2: 同期成長率(pp) | N2: 當季EPS預估 | O2: PE_TTM | P2: PE Forward | Q2: PEG_T | R2: PEG_F | S2: 殖利率 | T2: 配息YoY | U2: 預估期別 | V2: 來源 | W2: 下次財報
A3: =IF(Calc!$A$2="","",Calc!A$2) -> 2330 | B3: =IF(Calc!$A$2="","",Calc!B$2) -> 台積電 | C3: =IF(Calc!$A$2="","",Calc!C$2) -> 核心 | D3: =IF(Calc!$A$2="","",Calc!D$2) -> 2420 | E3: =IF(Calc!$A$2="","",Calc!AA$2) -> 0.64230169 | F3: =IF(Calc!$A$2="","",Calc!AB$2) -> 0.58974357 | G3: =IF(Calc!$A$2="","",Calc!AG$2) -> 0.40630776 | H3: =IF(Calc!$A$2="","",Calc!AH$2) -> 0.3398412 | I3: =IF(Calc!$A$2="","",Calc!AI$2) -> 0.44646533 | J3: =IF(Calc!$A$2="","",Calc!T$2) -> 0.12016259 | K3: =IF(Calc!$A$2="","",Calc!W$2) -> 0.42820845 | L3: =IF(Calc!$A$2="","",Calc!X$2) -> 成長且加速 | M3: =IF(Calc!$A$2="","",Calc!Y$2) -> 0.75170257 | N3: =IF(Calc!$A$2="","",Calc!AJ$2) -> 28.19147 | O3: =IF(Calc!$A$2="","",Calc!J$2) -> 28.048215 | P3: =IF(Calc!$A$2="","",Calc!L$2) -> 17.246923 | Q3: =IF(Calc!$A$2="","",Calc!N$2) -> 0.52699199 | R3: =IF(Calc!$A$2="","",Calc!O$2) -> 0.51144944 | S3: =IF(Calc!$A$2="","",Calc!Q$2) -> 0.0090909505 | T3: =IF(Calc!$A$2="","",Calc!R$2) -> 0.29413754 | U3: =IF(Calc!$A$2="","",Calc!AK$2) -> FY2026Q3E | V3: =IF(Calc!$A$2="","",Calc!AL$2) -> consensus | W3: =IF(Calc!$A$2="","",Calc!AN$2) -> 0
A4: =IF(Calc!$A$3="","",Calc!A$3) -> 2408 | B4: =IF(Calc!$A$3="","",Calc!B$3) -> 南亞科 | C4: =IF(Calc!$A$3="","",Calc!C$3) -> 核心 | D4: =IF(Calc!$A$3="","",Calc!D$3) -> 447.5 | E4: =IF(Calc!$A$3="","",Calc!AA$3) -> 0.64909776 | F4: =IF(Calc!$A$3="","",Calc!AB$3) -> 0.41891279 | G4: =IF(Calc!$A$3="","",Calc!AG$3) -> 0.37416987 | H4: =IF(Calc!$A$3="","",Calc!AH$3) -> 0.17665407 | I4: =IF(Calc!$A$3="","",Calc!AI$3) -> 0.81411989 | J4: =IF(Calc!$A$3="","",Calc!T$3) -> 0.68169143 | K4: =IF(Calc!$A$3="","",Calc!W$3) -> 0.080093846 | L4: =IF(Calc!$A$3="","",Calc!X$3) -> 成長且加速 | M4: =IF(Calc!$A$3="","",Calc!Y$3) -> 21.728105 | N4: =IF(Calc!$A$3="","",Calc!AJ$3) -> 20.84785 | O4: =IF(Calc!$A$3="","",Calc!J$3) -> 16.482505 | P4: =IF(Calc!$A$3="","",Calc!L$3) -> 4.0717326 | Q4: =IF(Calc!$A$3="","",Calc!N$3) -> N/M | R4: =IF(Calc!$A$3="","",Calc!O$3) -> 0.072615198 | S4: =IF(Calc!$A$3="","",Calc!Q$3) -> 不配息 | T4: =IF(Calc!$A$3="","",Calc!R$3) | U4: =IF(Calc!$A$3="","",Calc!AK$3) -> FY2026Q3E | V4: =IF(Calc!$A$3="","",Calc!AL$3) -> consensus | W4: =IF(Calc!$A$3="","",Calc!AN$3) -> 0
A5: =IF(Calc!$A$4="","",Calc!A$4) -> 5289 | B5: =IF(Calc!$A$4="","",Calc!B$4) -> 宜鼎 | C5: =IF(Calc!$A$4="","",Calc!C$4) -> 觀察 | D5: =IF(Calc!$A$4="","",Calc!D$4) -> 1175 | E5: =IF(Calc!$A$4="","",Calc!AA$4) | F5: =IF(Calc!$A$4="","",Calc!AB$4) | G5: =IF(Calc!$A$4="","",Calc!AG$4) -> N/M | H5: =IF(Calc!$A$4="","",Calc!AH$4) | I5: =IF(Calc!$A$4="","",Calc!AI$4) -> N/M | J5: =IF(Calc!$A$4="","",Calc!T$4) | K5: =IF(Calc!$A$4="","",Calc!W$4) -> N/M | L5: =IF(Calc!$A$4="","",Calc!X$4) | M5: =IF(Calc!$A$4="","",Calc!Y$4) | N5: =IF(Calc!$A$4="","",Calc!AJ$4) -> 0 | O5: =IF(Calc!$A$4="","",Calc!J$4) -> N/M | P5: =IF(Calc!$A$4="","",Calc!L$4) -> 5.1579388 | Q5: =IF(Calc!$A$4="","",Calc!N$4) -> N/M | R5: =IF(Calc!$A$4="","",Calc!O$4) -> N/M | S5: =IF(Calc!$A$4="","",Calc!Q$4) -> 不配息 | T5: =IF(Calc!$A$4="","",Calc!R$4) | U5: =IF(Calc!$A$4="","",Calc!AK$4) | V5: =IF(Calc!$A$4="","",Calc!AL$4) | W5: =IF(Calc!$A$4="","",Calc!AN$4) -> 0
A6: =IF(Calc!$A$5="","",Calc!A$5) -> 2455 | B6: =IF(Calc!$A$5="","",Calc!B$5) -> 全新 | C6: =IF(Calc!$A$5="","",Calc!C$5) -> 池子 | D6: =IF(Calc!$A$5="","",Calc!D$5) -> 493 | E6: =IF(Calc!$A$5="","",Calc!AA$5) -> 0.36755835 | F6: =IF(Calc!$A$5="","",Calc!AB$5) -> 0.394733 | G6: =IF(Calc!$A$5="","",Calc!AG$5) -> 0.23348629 | H6: =IF(Calc!$A$5="","",Calc!AH$5) -> 0.1978 | I6: =IF(Calc!$A$5="","",Calc!AI$5) -> 0.28167152 | J6: =IF(Calc!$A$5="","",Calc!T$5) -> 0.0063201676 | K6: =IF(Calc!$A$5="","",Calc!W$5) -> N/M | L6: =IF(Calc!$A$5="","",Calc!X$5) -> 由負轉正 | M6: =IF(Calc!$A$5="","",Calc!Y$5) -> 10.658439 | N6: =IF(Calc!$A$5="","",Calc!AJ$5) -> 1.43429 | O6: =IF(Calc!$A$5="","",Calc!J$5) -> 119.66019 | P6: =IF(Calc!$A$5="","",Calc!L$5) -> 56.93997 | Q6: =IF(Calc!$A$5="","",Calc!N$5) -> 1.9435254 | R6: =IF(Calc!$A$5="","",Calc!O$5) -> 0.83640012 | S6: =IF(Calc!$A$5="","",Calc!Q$5) -> 0.0053155305 | T6: =IF(Calc!$A$5="","",Calc!R$5) -> -0.1855581 | U6: =IF(Calc!$A$5="","",Calc!AK$5) -> FY2026Q3E | V6: =IF(Calc!$A$5="","",Calc!AL$5) -> consensus | W6: =IF(Calc!$A$5="","",Calc!AN$5) -> 0
A7: =IF(Calc!$A$6="","",Calc!A$6) -> 3034 | B7: =IF(Calc!$A$6="","",Calc!B$6) -> 聯詠 | C7: =IF(Calc!$A$6="","",Calc!C$6) -> 池子 | D7: =IF(Calc!$A$6="","",Calc!D$6) -> 577 | E7: =IF(Calc!$A$6="","",Calc!AA$6) -> 0.3914295 | F7: =IF(Calc!$A$6="","",Calc!AB$6) -> 0.42949275 | G7: =IF(Calc!$A$6="","",Calc!AG$6) -> 0.27131661 | H7: =IF(Calc!$A$6="","",Calc!AH$6) -> 0.43282102 | I7: =IF(Calc!$A$6="","",Calc!AI$6) -> 0.29942709 | J7: =IF(Calc!$A$6="","",Calc!T$6) -> 0.23826843 | K7: =IF(Calc!$A$6="","",Calc!W$6) -> N/M | L7: =IF(Calc!$A$6="","",Calc!X$6) -> 成長且加速 | M7: =IF(Calc!$A$6="","",Calc!Y$6) -> 27.39665 | N7: =IF(Calc!$A$6="","",Calc!AJ$6) -> 9.57273 | O7: =IF(Calc!$A$6="","",Calc!J$6) -> 20.125567 | P7: =IF(Calc!$A$6="","",Calc!L$6) -> 16.436904 | Q7: =IF(Calc!$A$6="","",Calc!N$6) -> N/M | R7: =IF(Calc!$A$6="","",Calc!O$6) -> N/M | S7: =IF(Calc!$A$6="","",Calc!Q$6) -> 0.048526863 | T7: =IF(Calc!$A$6="","",Calc!R$6) -> -0.125 | U7: =IF(Calc!$A$6="","",Calc!AK$6) -> FY2026Q3E | V7: =IF(Calc!$A$6="","",Calc!AL$6) -> consensus | W7: =IF(Calc!$A$6="","",Calc!AN$6) -> 0
A8: =IF(Calc!$A$7="","",Calc!A$7) -> 3665 | B8: =IF(Calc!$A$7="","",Calc!B$7) -> 貿聯-KY | C8: =IF(Calc!$A$7="","",Calc!C$7) -> 池子 | D8: =IF(Calc!$A$7="","",Calc!D$7) -> 2015 | E8: =IF(Calc!$A$7="","",Calc!AA$7) -> 0.31084835 | F8: =IF(Calc!$A$7="","",Calc!AB$7) -> 0.27955152 | G8: =IF(Calc!$A$7="","",Calc!AG$7) -> 0.24684388 | H8: =IF(Calc!$A$7="","",Calc!AH$7) -> 0.18075913 | I8: =IF(Calc!$A$7="","",Calc!AI$7) -> 0.27356215 | J8: =IF(Calc!$A$7="","",Calc!T$7) -> 0.11587326 | K8: =IF(Calc!$A$7="","",Calc!W$7) -> 1.114977 | L8: =IF(Calc!$A$7="","",Calc!X$7) -> 成長且加速 | M8: =IF(Calc!$A$7="","",Calc!Y$7) -> 6.546982 | N8: =IF(Calc!$A$7="","",Calc!AJ$7) -> 18.74375 | O8: =IF(Calc!$A$7="","",Calc!J$7) -> 36.952136 | P8: =IF(Calc!$A$7="","",Calc!L$7) -> 17.355683 | Q8: =IF(Calc!$A$7="","",Calc!N$7) -> 0.64304145 | R8: =IF(Calc!$A$7="","",Calc!O$7) -> 0.20496858 | S8: =IF(Calc!$A$7="","",Calc!Q$7) -> 0.005213639 | T8: =IF(Calc!$A$7="","",Calc!R$7) -> 0.19642403 | U8: =IF(Calc!$A$7="","",Calc!AK$7) -> FY2026Q3E | V8: =IF(Calc!$A$7="","",Calc!AL$7) -> consensus | W8: =IF(Calc!$A$7="","",Calc!AN$7) -> 0
A9: =IF(Calc!$A$8="","",Calc!A$8) -> 5434 | B9: =IF(Calc!$A$8="","",Calc!B$8) -> 崇越 | C9: =IF(Calc!$A$8="","",Calc!C$8) -> 池子 | D9: =IF(Calc!$A$8="","",Calc!D$8) -> 576 | E9: =IF(Calc!$A$8="","",Calc!AA$8) | F9: =IF(Calc!$A$8="","",Calc!AB$8) | G9: =IF(Calc!$A$8="","",Calc!AG$8) -> N/M | H9: =IF(Calc!$A$8="","",Calc!AH$8) | I9: =IF(Calc!$A$8="","",Calc!AI$8) -> N/M | J9: =IF(Calc!$A$8="","",Calc!T$8) | K9: =IF(Calc!$A$8="","",Calc!W$8) -> N/M | L9: =IF(Calc!$A$8="","",Calc!X$8) | M9: =IF(Calc!$A$8="","",Calc!Y$8) | N9: =IF(Calc!$A$8="","",Calc!AJ$8) -> 0 | O9: =IF(Calc!$A$8="","",Calc!J$8) -> N/M | P9: =IF(Calc!$A$8="","",Calc!L$8) -> 17.303883 | Q9: =IF(Calc!$A$8="","",Calc!N$8) -> N/M | R9: =IF(Calc!$A$8="","",Calc!O$8) -> 1.5553667 | S9: =IF(Calc!$A$8="","",Calc!Q$8) -> 不配息 | T9: =IF(Calc!$A$8="","",Calc!R$8) | U9: =IF(Calc!$A$8="","",Calc!AK$8) | V9: =IF(Calc!$A$8="","",Calc!AL$8) | W9: =IF(Calc!$A$8="","",Calc!AN$8) -> 0
A10: =IF(Calc!$A$9="","",Calc!A$9) -> 2376 | B10: =IF(Calc!$A$9="","",Calc!B$9) -> 技嘉 | C10: =IF(Calc!$A$9="","",Calc!C$9) -> 池子 | D10: =IF(Calc!$A$9="","",Calc!D$9) -> 357.5 | E10: =IF(Calc!$A$9="","",Calc!AA$9) -> 0.10415901 | F10: =IF(Calc!$A$9="","",Calc!AB$9) -> 0.11858133 | G10: =IF(Calc!$A$9="","",Calc!AG$9) -> 0.30194575 | H10: =IF(Calc!$A$9="","",Calc!AH$9) -> 0.24916275 | I10: =IF(Calc!$A$9="","",Calc!AI$9) -> 0.34261066 | J10: =IF(Calc!$A$9="","",Calc!T$9) -> 0.37272128 | K10: =IF(Calc!$A$9="","",Calc!W$9) -> 1.1201407 | L10: =IF(Calc!$A$9="","",Calc!X$9) -> 成長且加速 | M10: =IF(Calc!$A$9="","",Calc!Y$9) -> -18.259603 | N10: =IF(Calc!$A$9="","",Calc!AJ$9) -> 8.21666 | O10: =IF(Calc!$A$9="","",Calc!J$9) -> 13.3845 | P10: =IF(Calc!$A$9="","",Calc!L$9) -> 9.755493 | Q10: =IF(Calc!$A$9="","",Calc!N$9) -> 0.21357968 | R10: =IF(Calc!$A$9="","",Calc!O$9) -> 1.0013259 | S10: =IF(Calc!$A$9="","",Calc!Q$9) -> 0.027972028 | T10: =IF(Calc!$A$9="","",Calc!R$9) -> 0.57283568 | U10: =IF(Calc!$A$9="","",Calc!AK$9) -> FY2026Q3E | V10: =IF(Calc!$A$9="","",Calc!AL$9) -> consensus | W10: =IF(Calc!$A$9="","",Calc!AN$9) -> 0
A11: =IF(Calc!$A$10="","",Calc!A$10) -> 2059 | B11: =IF(Calc!$A$10="","",Calc!B$10) -> 川湖 | C11: =IF(Calc!$A$10="","",Calc!C$10) -> 池子 | D11: =IF(Calc!$A$10="","",Calc!D$10) -> 9955 | E11: =IF(Calc!$A$10="","",Calc!AA$10) -> 0.80979839 | F11: =IF(Calc!$A$10="","",Calc!AB$10) -> 0.71993297 | G11: =IF(Calc!$A$10="","",Calc!AG$10) -> 0.62845438 | H11: =IF(Calc!$A$10="","",Calc!AH$10) -> 0.34114797 | I11: =IF(Calc!$A$10="","",Calc!AI$10) -> 0.99003304 | J11: =IF(Calc!$A$10="","",Calc!T$10) -> 0.98726376 | K11: =IF(Calc!$A$10="","",Calc!W$10) -> 8.760106 | L11: =IF(Calc!$A$10="","",Calc!X$10) -> 成長且加速 | M11: =IF(Calc!$A$10="","",Calc!Y$10) -> 91.783503 | N11: =IF(Calc!$A$10="","",Calc!AJ$10) -> 118.40075 | O11: =IF(Calc!$A$10="","",Calc!J$10) -> 54.881747 | P11: =IF(Calc!$A$10="","",Calc!L$10) -> 21.35513 | Q11: =IF(Calc!$A$10="","",Calc!N$10) -> 0.32565548 | R11: =IF(Calc!$A$10="","",Calc!O$10) -> 0.51336133 | S11: =IF(Calc!$A$10="","",Calc!Q$10) -> 0.0032345555 | T11: =IF(Calc!$A$10="","",Calc!R$10) -> 1.2692037 | U11: =IF(Calc!$A$10="","",Calc!AK$10) -> FY2026Q3E | V11: =IF(Calc!$A$10="","",Calc!AL$10) -> consensus | W11: =IF(Calc!$A$10="","",Calc!AN$10) -> 0
A12: =IF(Calc!$A$11="","",Calc!A$11) -> 3081 | B12: =IF(Calc!$A$11="","",Calc!B$11) -> 聯亞 | C12: =IF(Calc!$A$11="","",Calc!C$11) -> 池子 | D12: =IF(Calc!$A$11="","",Calc!D$11) -> 2545 | E12: =IF(Calc!$A$11="","",Calc!AA$11) -> 0.52719968 | F12: =IF(Calc!$A$11="","",Calc!AB$11) -> 0.35868683 | G12: =IF(Calc!$A$11="","",Calc!AG$11) -> 0.24117217 | H12: =IF(Calc!$A$11="","",Calc!AH$11) -> 0.060054396 | I12: =IF(Calc!$A$11="","",Calc!AI$11) -> 0.38448223 | J12: =IF(Calc!$A$11="","",Calc!T$11) -> 0.35027958 | K12: =IF(Calc!$A$11="","",Calc!W$11) -> -0.14100895 | L12: =IF(Calc!$A$11="","",Calc!X$11) -> 成長但減速 | M12: =IF(Calc!$A$11="","",Calc!Y$11) -> 13.335644 | N12: =IF(Calc!$A$11="","",Calc!AJ$11) -> 5.79 | O12: =IF(Calc!$A$11="","",Calc!J$11) -> 227.02944 | P12: =IF(Calc!$A$11="","",Calc!L$11) -> 72.148179 | Q12: =IF(Calc!$A$11="","",Calc!N$11) -> 0.40302495 | R12: =IF(Calc!$A$11="","",Calc!O$11) -> 0.71519807 | S12: =IF(Calc!$A$11="","",Calc!Q$11) -> 0.00019647236 | T12: =IF(Calc!$A$11="","",Calc!R$11) -> 9.7705217e-05 | U12: =IF(Calc!$A$11="","",Calc!AK$11) -> FY2026Q3E | V12: =IF(Calc!$A$11="","",Calc!AL$11) -> consensus | W12: =IF(Calc!$A$11="","",Calc!AN$11) -> 0
A13: =IF(Calc!$A$12="","",Calc!A$12) -> 3163 | B13: =IF(Calc!$A$12="","",Calc!B$12) -> 波若威 | C13: =IF(Calc!$A$12="","",Calc!C$12) -> 基本面not good | D13: =IF(Calc!$A$12="","",Calc!D$12) -> 589 | E13: =IF(Calc!$A$12="","",Calc!AA$12) -> 0.1783065 | F13: =IF(Calc!$A$12="","",Calc!AB$12) -> 0.19418807 | G13: =IF(Calc!$A$12="","",Calc!AG$12) -> 0.26521956 | H13: =IF(Calc!$A$12="","",Calc!AH$12) -> 0.18851076 | I13: =IF(Calc!$A$12="","",Calc!AI$12) -> 0 | J13: =IF(Calc!$A$12="","",Calc!T$12) -> -0.097918747 | K13: =IF(Calc!$A$12="","",Calc!W$12) -> -2.8377245 | L13: =IF(Calc!$A$12="","",Calc!X$12) -> 由正轉負 | M13: =IF(Calc!$A$12="","",Calc!Y$12) -> -12.573454 | N13: =IF(Calc!$A$12="","",Calc!AJ$12) -> 0 | O13: =IF(Calc!$A$12="","",Calc!J$12) -> 61.099585 | P13: =IF(Calc!$A$12="","",Calc!L$12) -> N/M | Q13: =IF(Calc!$A$12="","",Calc!N$12) -> 0.22923239 | R13: =IF(Calc!$A$12="","",Calc!O$12) -> N/M | S13: =IF(Calc!$A$12="","",Calc!Q$12) -> 不配息 | T13: =IF(Calc!$A$12="","",Calc!R$12) -> -1 | U13: =IF(Calc!$A$12="","",Calc!AK$12) | V13: =IF(Calc!$A$12="","",Calc!AL$12) | W13: =IF(Calc!$A$12="","",Calc!AN$12) -> 0
A14: =IF(Calc!$A$13="","",Calc!A$13) -> 3189 | B14: =IF(Calc!$A$13="","",Calc!B$13) -> 景碩 | C14: =IF(Calc!$A$13="","",Calc!C$13) -> 池子 | D14: =IF(Calc!$A$13="","",Calc!D$13) -> 1000 | E14: =IF(Calc!$A$13="","",Calc!AA$13) -> 0.22264191 | F14: =IF(Calc!$A$13="","",Calc!AB$13) -> 0.28503349 | G14: =IF(Calc!$A$13="","",Calc!AG$13) -> 0.077810324 | H14: =IF(Calc!$A$13="","",Calc!AH$13) -> 0.086417659 | I14: =IF(Calc!$A$13="","",Calc!AI$13) -> 0.14269029 | J14: =IF(Calc!$A$13="","",Calc!T$13) -> 0.12528531 | K14: =IF(Calc!$A$13="","",Calc!W$13) -> 3.614616 | L14: =IF(Calc!$A$13="","",Calc!X$13) -> 成長且加速 | M14: =IF(Calc!$A$13="","",Calc!Y$13) -> 1.5771386 | N14: =IF(Calc!$A$13="","",Calc!AJ$13) -> 3.18425 | O14: =IF(Calc!$A$13="","",Calc!J$13) -> 169.49153 | P14: =IF(Calc!$A$13="","",Calc!L$13) -> 38.255845 | Q14: =IF(Calc!$A$13="","",Calc!N$13) -> 0.43728091 | R14: =IF(Calc!$A$13="","",Calc!O$13) -> 0.25872524 | S14: =IF(Calc!$A$13="","",Calc!Q$13) -> 0.0010001719 | T14: =IF(Calc!$A$13="","",Calc!R$13) -> 6.4083089e-05 | U14: =IF(Calc!$A$13="","",Calc!AK$13) -> FY2026Q3E | V14: =IF(Calc!$A$13="","",Calc!AL$13) -> consensus | W14: =IF(Calc!$A$13="","",Calc!AN$13) -> 0
A15: =IF(Calc!$A$14="","",Calc!A$14) -> 6442 | B15: =IF(Calc!$A$14="","",Calc!B$14) -> 光聖 | C15: =IF(Calc!$A$14="","",Calc!C$14) -> 池子 | D15: =IF(Calc!$A$14="","",Calc!D$14) -> 1505 | E15: =IF(Calc!$A$14="","",Calc!AA$14) | F15: =IF(Calc!$A$14="","",Calc!AB$14) | G15: =IF(Calc!$A$14="","",Calc!AG$14) -> N/M | H15: =IF(Calc!$A$14="","",Calc!AH$14) | I15: =IF(Calc!$A$14="","",Calc!AI$14) -> N/M | J15: =IF(Calc!$A$14="","",Calc!T$14) | K15: =IF(Calc!$A$14="","",Calc!W$14) -> N/M | L15: =IF(Calc!$A$14="","",Calc!X$14) | M15: =IF(Calc!$A$14="","",Calc!Y$14) | N15: =IF(Calc!$A$14="","",Calc!AJ$14) -> 0 | O15: =IF(Calc!$A$14="","",Calc!J$14) -> N/M | P15: =IF(Calc!$A$14="","",Calc!L$14) -> 12.991702 | Q15: =IF(Calc!$A$14="","",Calc!N$14) -> N/M | R15: =IF(Calc!$A$14="","",Calc!O$14) -> 0.11849028 | S15: =IF(Calc!$A$14="","",Calc!Q$14) -> 不配息 | T15: =IF(Calc!$A$14="","",Calc!R$14) | U15: =IF(Calc!$A$14="","",Calc!AK$14) | V15: =IF(Calc!$A$14="","",Calc!AL$14) | W15: =IF(Calc!$A$14="","",Calc!AN$14) -> 0
A16: =IF(Calc!$A$15="","",Calc!A$15) -> 2303 | B16: =IF(Calc!$A$15="","",Calc!B$15) -> 聯電 | C16: =IF(Calc!$A$15="","",Calc!C$15) -> 池子 | D16: =IF(Calc!$A$15="","",Calc!D$15) -> 133 | E16: =IF(Calc!$A$15="","",Calc!AA$15) -> 0.30602652 | F16: =IF(Calc!$A$15="","",Calc!AB$15) -> 0.35518363 | G16: =IF(Calc!$A$15="","",Calc!AG$15) -> 0.21516722 | H16: =IF(Calc!$A$15="","",Calc!AH$15) -> 0.20748385 | I16: =IF(Calc!$A$15="","",Calc!AI$15) -> 0.20262443 | J16: =IF(Calc!$A$15="","",Calc!T$15) -> 0.12606528 | K16: =IF(Calc!$A$15="","",Calc!W$15) -> N/M | L16: =IF(Calc!$A$15="","",Calc!X$15) -> 由負轉正 | M16: =IF(Calc!$A$15="","",Calc!Y$15) -> 11.053268 | N16: =IF(Calc!$A$15="","",Calc!AJ$15) -> 1.4114 | O16: =IF(Calc!$A$15="","",Calc!J$15) -> 19.91018 | P16: =IF(Calc!$A$15="","",Calc!L$15) -> 18.255318 | Q16: =IF(Calc!$A$15="","",Calc!N$15) -> 0.17981558 | R16: =IF(Calc!$A$15="","",Calc!O$15) -> N/M | S16: =IF(Calc!$A$15="","",Calc!Q$15) -> 不配息 | T16: =IF(Calc!$A$15="","",Calc!R$15) -> -1 | U16: =IF(Calc!$A$15="","",Calc!AK$15) -> FY2026Q3E | V16: =IF(Calc!$A$15="","",Calc!AL$15) -> consensus | W16: =IF(Calc!$A$15="","",Calc!AN$15) -> 0
A17: =IF(Calc!$A$16="","",Calc!A$16) -> 2454 | B17: =IF(Calc!$A$16="","",Calc!B$16) -> 聯發科 | C17: =IF(Calc!$A$16="","",Calc!C$16) -> 池子 | D17: =IF(Calc!$A$16="","",Calc!D$16) -> 4250 | E17: =IF(Calc!$A$16="","",Calc!AA$16) -> 0.46284946 | F17: =IF(Calc!$A$16="","",Calc!AB$16) -> 0.48285234 | G17: =IF(Calc!$A$16="","",Calc!AG$16) -> 0.24317652 | H17: =IF(Calc!$A$16="","",Calc!AH$16) -> 0.26965686 | I17: =IF(Calc!$A$16="","",Calc!AI$16) -> 0.25896066 | J17: =IF(Calc!$A$16="","",Calc!T$16) -> 0.020329136 | K17: =IF(Calc!$A$16="","",Calc!W$16) -> N/M | L17: =IF(Calc!$A$16="","",Calc!X$16) -> 由負轉正 | M17: =IF(Calc!$A$16="","",Calc!Y$16) -> 3.9529599 | N17: =IF(Calc!$A$16="","",Calc!AJ$16) -> 15.43434 | O17: =IF(Calc!$A$16="","",Calc!J$16) -> 70.028011 | P17: =IF(Calc!$A$16="","",Calc!L$16) -> 32.200337 | Q17: =IF(Calc!$A$16="","",Calc!N$16) -> N/M | R17: =IF(Calc!$A$16="","",Calc!O$16) -> 0.27499619 | S17: =IF(Calc!$A$16="","",Calc!Q$16) -> 0.012705934 | T17: =IF(Calc!$A$16="","",Calc!R$16) -> -0.090986671 | U17: =IF(Calc!$A$16="","",Calc!AK$16) -> FY2026Q3E | V17: =IF(Calc!$A$16="","",Calc!AL$16) -> consensus | W17: =IF(Calc!$A$16="","",Calc!AN$16) -> 0
A18: =IF(Calc!$A$17="","",Calc!A$17) -> 2465 | B18: =IF(Calc!$A$17="","",Calc!B$17) -> 麗臺 | C18: =IF(Calc!$A$17="","",Calc!C$17) -> 池子 | D18: =IF(Calc!$A$17="","",Calc!D$17) -> 86 | E18: =IF(Calc!$A$17="","",Calc!AA$17) -> 0.095604955 | F18: =IF(Calc!$A$17="","",Calc!AB$17) -> 0.11861438 | G18: =IF(Calc!$A$17="","",Calc!AG$17) -> 0.26300347 | H18: =IF(Calc!$A$17="","",Calc!AH$17) -> -0.14671724 | I18: =IF(Calc!$A$17="","",Calc!AI$17) -> 0 | J18: =IF(Calc!$A$17="","",Calc!T$17) -> 0.59680357 | K18: =IF(Calc!$A$17="","",Calc!W$17) -> -0.1362974 | L18: =IF(Calc!$A$17="","",Calc!X$17) -> 成長但減速 | M18: =IF(Calc!$A$17="","",Calc!Y$17) -> 69.949307 | N18: =IF(Calc!$A$17="","",Calc!AJ$17) -> 0 | O18: =IF(Calc!$A$17="","",Calc!J$17) -> 31.851852 | P18: =IF(Calc!$A$17="","",Calc!L$17) -> N/M | Q18: =IF(Calc!$A$17="","",Calc!N$17) -> N/M | R18: =IF(Calc!$A$17="","",Calc!O$17) -> N/M | S18: =IF(Calc!$A$17="","",Calc!Q$17) -> 不配息 | T18: =IF(Calc!$A$17="","",Calc!R$17) | U18: =IF(Calc!$A$17="","",Calc!AK$17) | V18: =IF(Calc!$A$17="","",Calc!AL$17) | W18: =IF(Calc!$A$17="","",Calc!AN$17) -> 0
A19: =IF(Calc!$A$18="","",Calc!A$18) -> 4938 | B19: =IF(Calc!$A$18="","",Calc!B$18) -> 和碩 | C19: =IF(Calc!$A$18="","",Calc!C$18) -> 池子 | D19: =IF(Calc!$A$18="","",Calc!D$18) -> 102 | E19: =IF(Calc!$A$18="","",Calc!AA$18) -> 0.042808925 | F19: =IF(Calc!$A$18="","",Calc!AB$18) -> 0.039688262 | G19: =IF(Calc!$A$18="","",Calc!AG$18) -> 0.082153688 | H19: =IF(Calc!$A$18="","",Calc!AH$18) -> 0.087267436 | I19: =IF(Calc!$A$18="","",Calc!AI$18) -> 0.074873042 | J19: =IF(Calc!$A$18="","",Calc!T$18) -> 0.12430066 | K19: =IF(Calc!$A$18="","",Calc!W$18) -> N/M | L19: =IF(Calc!$A$18="","",Calc!X$18) -> 由負轉正 | M19: =IF(Calc!$A$18="","",Calc!Y$18) -> 14.301239 | N19: =IF(Calc!$A$18="","",Calc!AJ$18) -> 1.47057 | O19: =IF(Calc!$A$18="","",Calc!J$18) -> 17.22973 | P19: =IF(Calc!$A$18="","",Calc!L$18) -> 14.374757 | Q19: =IF(Calc!$A$18="","",Calc!N$18) -> 0.69949757 | R19: =IF(Calc!$A$18="","",Calc!O$18) -> 0.50462387 | S19: =IF(Calc!$A$18="","",Calc!Q$18) -> 0.039308204 | T19: =IF(Calc!$A$18="","",Calc!R$18) -> -0.10957308 | U19: =IF(Calc!$A$18="","",Calc!AK$18) -> FY2026Q3E | V19: =IF(Calc!$A$18="","",Calc!AL$18) -> consensus | W19: =IF(Calc!$A$18="","",Calc!AN$18) -> 0
A20: =IF(Calc!$A$19="","",Calc!A$19) -> 8299 | B20: =IF(Calc!$A$19="","",Calc!B$19) -> 群聯 | C20: =IF(Calc!$A$19="","",Calc!C$19) -> 池子 | D20: =IF(Calc!$A$19="","",Calc!D$19) -> 1890 | E20: =IF(Calc!$A$19="","",Calc!AA$19) | F20: =IF(Calc!$A$19="","",Calc!AB$19) | G20: =IF(Calc!$A$19="","",Calc!AG$19) -> N/M | H20: =IF(Calc!$A$19="","",Calc!AH$19) | I20: =IF(Calc!$A$19="","",Calc!AI$19) -> N/M | J20: =IF(Calc!$A$19="","",Calc!T$19) | K20: =IF(Calc!$A$19="","",Calc!W$19) -> N/M | L20: =IF(Calc!$A$19="","",Calc!X$19) | M20: =IF(Calc!$A$19="","",Calc!Y$19) | N20: =IF(Calc!$A$19="","",Calc!AJ$19) -> 0 | O20: =IF(Calc!$A$19="","",Calc!J$19) -> N/M | P20: =IF(Calc!$A$19="","",Calc!L$19) -> 6.1210298 | Q20: =IF(Calc!$A$19="","",Calc!N$19) -> N/M | R20: =IF(Calc!$A$19="","",Calc!O$19) -> N/M | S20: =IF(Calc!$A$19="","",Calc!Q$19) -> 不配息 | T20: =IF(Calc!$A$19="","",Calc!R$19) | U20: =IF(Calc!$A$19="","",Calc!AK$19) | V20: =IF(Calc!$A$19="","",Calc!AL$19) | W20: =IF(Calc!$A$19="","",Calc!AN$19) -> 0
A21: =IF(Calc!$A$20="","",Calc!A$20) -> 3105 | B21: =IF(Calc!$A$20="","",Calc!B$20) -> 穩懋 | C21: =IF(Calc!$A$20="","",Calc!C$20) -> 池子 | D21: =IF(Calc!$A$20="","",Calc!D$20) -> 501 | E21: =IF(Calc!$A$20="","",Calc!AA$20) -> 0.28350858 | F21: =IF(Calc!$A$20="","",Calc!AB$20) -> 0.26605367 | G21: =IF(Calc!$A$20="","",Calc!AG$20) -> 0.089808736 | H21: =IF(Calc!$A$20="","",Calc!AH$20) -> 0.050895171 | I21: =IF(Calc!$A$20="","",Calc!AI$20) -> 0.075454081 | J21: =IF(Calc!$A$20="","",Calc!T$20) -> 0.14535932 | K21: =IF(Calc!$A$20="","",Calc!W$20) -> N/M | L21: =IF(Calc!$A$20="","",Calc!X$20) -> 由負轉正 | M21: =IF(Calc!$A$20="","",Calc!Y$20) -> 8.8142801 | N21: =IF(Calc!$A$20="","",Calc!AJ$20) -> 2.11774 | O21: =IF(Calc!$A$20="","",Calc!J$20) -> 58.871915 | P21: =IF(Calc!$A$20="","",Calc!L$20) -> 51.536875 | Q21: =IF(Calc!$A$20="","",Calc!N$20) -> N/M | R21: =IF(Calc!$A$20="","",Calc!O$20) -> 1.6540257 | S21: =IF(Calc!$A$20="","",Calc!Q$20) -> 0.003992016 | T21: =IF(Calc!$A$20="","",Calc!R$20) -> 1 | U21: =IF(Calc!$A$20="","",Calc!AK$20) -> FY2026Q3E | V21: =IF(Calc!$A$20="","",Calc!AL$20) -> consensus | W21: =IF(Calc!$A$20="","",Calc!AN$20) -> 0
A22: =IF(Calc!$A$21="","",Calc!A$21) -> 4979 | B22: =IF(Calc!$A$21="","",Calc!B$21) -> 華星光 | C22: =IF(Calc!$A$21="","",Calc!C$21) -> 池子 | D22: =IF(Calc!$A$21="","",Calc!D$21) -> 520 | E22: =IF(Calc!$A$21="","",Calc!AA$21) -> 0.23028088 | F22: =IF(Calc!$A$21="","",Calc!AB$21) -> 0.20751202 | G22: =IF(Calc!$A$21="","",Calc!AG$21) -> 0.21984691 | H22: =IF(Calc!$A$21="","",Calc!AH$21) -> 0.16103233 | I22: =IF(Calc!$A$21="","",Calc!AI$21) -> 0.23629877 | J22: =IF(Calc!$A$21="","",Calc!T$21) -> 0.080127158 | K22: =IF(Calc!$A$21="","",Calc!W$21) -> 1.3645275 | L22: =IF(Calc!$A$21="","",Calc!X$21) -> 成長且加速 | M22: =IF(Calc!$A$21="","",Calc!Y$21) -> 6.0837736 | N22: =IF(Calc!$A$21="","",Calc!AJ$21) -> 2.18 | O22: =IF(Calc!$A$21="","",Calc!J$21) -> 84.552846 | P22: =IF(Calc!$A$21="","",Calc!L$21) -> 40.859294 | Q22: =IF(Calc!$A$21="","",Calc!N$21) -> 1.8913136 | R22: =IF(Calc!$A$21="","",Calc!O$21) -> 0.4479973 | S22: =IF(Calc!$A$21="","",Calc!Q$21) -> 0.0029704477 | T22: =IF(Calc!$A$21="","",Calc!R$21) -> 0.080159547 | U22: =IF(Calc!$A$21="","",Calc!AK$21) -> FY2026Q3E | V22: =IF(Calc!$A$21="","",Calc!AL$21) -> consensus | W22: =IF(Calc!$A$21="","",Calc!AN$21) -> 0
A23: =IF(Calc!$A$22="","",Calc!A$22) -> 3363 | B23: =IF(Calc!$A$22="","",Calc!B$22) -> 上詮 | C23: =IF(Calc!$A$22="","",Calc!C$22) -> 池子 | D23: =IF(Calc!$A$22="","",Calc!D$22) -> 531 | E23: =IF(Calc!$A$22="","",Calc!AA$22) -> 0.10389595 | F23: =IF(Calc!$A$22="","",Calc!AB$22) -> 0.16638727 | G23: =IF(Calc!$A$22="","",Calc!AG$22) -> -0.0333505 | H23: =IF(Calc!$A$22="","",Calc!AH$22) -> 0.019719722 | I23: =IF(Calc!$A$22="","",Calc!AI$22) -> -0.0086465536 | J23: =IF(Calc!$A$22="","",Calc!T$22) -> 0.12361998 | K23: =IF(Calc!$A$22="","",Calc!W$22) -> N/M | L23: =IF(Calc!$A$22="","",Calc!X$22) -> 由負轉正 | M23: =IF(Calc!$A$22="","",Calc!Y$22) -> -29.123601 | N23: =IF(Calc!$A$22="","",Calc!AJ$22) -> 0.19 | O23: =IF(Calc!$A$22="","",Calc!J$22) -> N/M | P23: =IF(Calc!$A$22="","",Calc!L$22) -> 61.873247 | Q23: =IF(Calc!$A$22="","",Calc!N$22) -> N/M | R23: =IF(Calc!$A$22="","",Calc!O$22) -> N/M | S23: =IF(Calc!$A$22="","",Calc!Q$22) -> 不配息 | T23: =IF(Calc!$A$22="","",Calc!R$22) | U23: =IF(Calc!$A$22="","",Calc!AK$22) -> FY2026Q3E | V23: =IF(Calc!$A$22="","",Calc!AL$22) -> consensus | W23: =IF(Calc!$A$22="","",Calc!AN$22) -> 0
A24: =IF(Calc!$A$23="","",Calc!A$23) -> 2344 | B24: =IF(Calc!$A$23="","",Calc!B$23) -> 華邦電 | C24: =IF(Calc!$A$23="","",Calc!C$23) -> 池子 | D24: =IF(Calc!$A$23="","",Calc!D$23) -> 161.5 | E24: =IF(Calc!$A$23="","",Calc!AA$23) -> 0.55547106 | F24: =IF(Calc!$A$23="","",Calc!AB$23) -> 0.41598347 | G24: =IF(Calc!$A$23="","",Calc!AG$23) -> 0.32271041 | H24: =IF(Calc!$A$23="","",Calc!AH$23) -> 0.11050918 | I24: =IF(Calc!$A$23="","",Calc!AI$23) -> 0.69317776 | J24: =IF(Calc!$A$23="","",Calc!T$23) -> 0.56440449 | K24: =IF(Calc!$A$23="","",Calc!W$23) -> 0.29233954 | L24: =IF(Calc!$A$23="","",Calc!X$23) -> 成長且加速 | M24: =IF(Calc!$A$23="","",Calc!Y$23) -> 51.311856 | N24: =IF(Calc!$A$23="","",Calc!AJ$23) -> 8.09903 | O24: =IF(Calc!$A$23="","",Calc!J$23) -> 17.825607 | P24: =IF(Calc!$A$23="","",Calc!L$23) -> 3.4435512 | Q24: =IF(Calc!$A$23="","",Calc!N$23) -> N/M | R24: =IF(Calc!$A$23="","",Calc!O$23) -> 0.032262139 | S24: =IF(Calc!$A$23="","",Calc!Q$23) -> 0.0030959752 | T24: =IF(Calc!$A$23="","",Calc!R$23) | U24: =IF(Calc!$A$23="","",Calc!AK$23) -> FY2026Q3E | V24: =IF(Calc!$A$23="","",Calc!AL$23) -> consensus | W24: =IF(Calc!$A$23="","",Calc!AN$23) -> 0
A25: =IF(Calc!$A$24="","",Calc!A$24) -> ↑ 藍字＝手動輸入。新增股票就在第 2~21 列往下打一列，其餘分頁全自動延伸。 | B25: =IF(Calc!$A$24="","",Calc!B$24) | C25: =IF(Calc!$A$24="","",Calc!C$24) | D25: =IF(Calc!$A$24="","",Calc!D$24) | E25: =IF(Calc!$A$24="","",Calc!AA$24) | F25: =IF(Calc!$A$24="","",Calc!AB$24) | G25: =IF(Calc!$A$24="","",Calc!AG$24) -> N/M | H25: =IF(Calc!$A$24="","",Calc!AH$24) | I25: =IF(Calc!$A$24="","",Calc!AI$24) -> N/M | J25: =IF(Calc!$A$24="","",Calc!T$24) | K25: =IF(Calc!$A$24="","",Calc!W$24) -> N/M | L25: =IF(Calc!$A$24="","",Calc!X$24) | M25: =IF(Calc!$A$24="","",Calc!Y$24) | N25: =IF(Calc!$A$24="","",Calc!AJ$24) -> 0 | O25: =IF(Calc!$A$24="","",Calc!J$24) -> N/M | P25: =IF(Calc!$A$24="","",Calc!L$24) -> N/M | Q25: =IF(Calc!$A$24="","",Calc!N$24) -> N/M | R25: =IF(Calc!$A$24="","",Calc!O$24) -> N/M | S25: =IF(Calc!$A$24="","",Calc!Q$24) -> 不配息 | T25: =IF(Calc!$A$24="","",Calc!R$24) | U25: =IF(Calc!$A$24="","",Calc!AK$24) | V25: =IF(Calc!$A$24="","",Calc!AL$24) | W25: =IF(Calc!$A$24="","",Calc!AN$24)
A26: =IF(Calc!$A$25="","",Calc!A$25) -> 3450 | B26: =IF(Calc!$A$25="","",Calc!B$25) -> 聯鈞 | C26: =IF(Calc!$A$25="","",Calc!C$25) -> 池子 | D26: =IF(Calc!$A$25="","",Calc!D$25) -> 457 | E26: =IF(Calc!$A$25="","",Calc!AA$25) -> 0.27318746 | F26: =IF(Calc!$A$25="","",Calc!AB$25) -> 0.24378557 | G26: =IF(Calc!$A$25="","",Calc!AG$25) -> 0.14018068 | H26: =IF(Calc!$A$25="","",Calc!AH$25) -> 0.088252261 | I26: =IF(Calc!$A$25="","",Calc!AI$25) -> 0.31224078 | J26: =IF(Calc!$A$25="","",Calc!T$25) -> 0.42635876 | K26: =IF(Calc!$A$25="","",Calc!W$25) -> N/M | L26: =IF(Calc!$A$25="","",Calc!X$25) -> 由負轉正 | M26: =IF(Calc!$A$25="","",Calc!Y$25) -> 75.59818 | N26: =IF(Calc!$A$25="","",Calc!AJ$25) -> 0 | O26: =IF(Calc!$A$25="","",Calc!J$25) -> 92.886179 | P26: =IF(Calc!$A$25="","",Calc!L$25) -> 38.17878 | Q26: =IF(Calc!$A$25="","",Calc!N$25) -> N/M | R26: =IF(Calc!$A$25="","",Calc!O$25) -> N/M | S26: =IF(Calc!$A$25="","",Calc!Q$25) -> 0.0021881838 | T26: =IF(Calc!$A$25="","",Calc!R$25) -> 1 | U26: =IF(Calc!$A$25="","",Calc!AK$25) | V26: =IF(Calc!$A$25="","",Calc!AL$25) | W26: =IF(Calc!$A$25="","",Calc!AN$25) -> 0
A27: =IF(Calc!$A$26="","",Calc!A$26) -> 6830 | B27: =IF(Calc!$A$26="","",Calc!B$26) -> 汎銓 | C27: =IF(Calc!$A$26="","",Calc!C$26) -> 池子 | D27: =IF(Calc!$A$26="","",Calc!D$26) -> 486.5 | E27: =IF(Calc!$A$26="","",Calc!AA$26) | F27: =IF(Calc!$A$26="","",Calc!AB$26) | G27: =IF(Calc!$A$26="","",Calc!AG$26) -> N/M | H27: =IF(Calc!$A$26="","",Calc!AH$26) | I27: =IF(Calc!$A$26="","",Calc!AI$26) -> N/M | J27: =IF(Calc!$A$26="","",Calc!T$26) | K27: =IF(Calc!$A$26="","",Calc!W$26) -> N/M | L27: =IF(Calc!$A$26="","",Calc!X$26) | M27: =IF(Calc!$A$26="","",Calc!Y$26) | N27: =IF(Calc!$A$26="","",Calc!AJ$26) -> 0 | O27: =IF(Calc!$A$26="","",Calc!J$26) -> N/M | P27: =IF(Calc!$A$26="","",Calc!L$26) -> 37.417084 | Q27: =IF(Calc!$A$26="","",Calc!N$26) -> N/M | R27: =IF(Calc!$A$26="","",Calc!O$26) -> 0.14843706 | S27: =IF(Calc!$A$26="","",Calc!Q$26) -> 不配息 | T27: =IF(Calc!$A$26="","",Calc!R$26) | U27: =IF(Calc!$A$26="","",Calc!AK$26) | V27: =IF(Calc!$A$26="","",Calc!AL$26) | W27: =IF(Calc!$A$26="","",Calc!AN$26) -> 0
A28: =IF(Calc!$A$27="","",Calc!A$27) -> 3443 | B28: =IF(Calc!$A$27="","",Calc!B$27) -> 創意 | C28: =IF(Calc!$A$27="","",Calc!C$27) -> 池子 | D28: =IF(Calc!$A$27="","",Calc!D$27) -> 7480 | E28: =IF(Calc!$A$27="","",Calc!AA$27) -> 0.22768049 | F28: =IF(Calc!$A$27="","",Calc!AB$27) -> 0.29319126 | G28: =IF(Calc!$A$27="","",Calc!AG$27) -> 0.43083514 | H28: =IF(Calc!$A$27="","",Calc!AH$27) -> 0.44701782 | I28: =IF(Calc!$A$27="","",Calc!AI$27) -> 0.53197597 | J28: =IF(Calc!$A$27="","",Calc!T$27) -> 0.21390507 | K28: =IF(Calc!$A$27="","",Calc!W$27) -> N/M | L28: =IF(Calc!$A$27="","",Calc!X$27) -> 由負轉正 | M28: =IF(Calc!$A$27="","",Calc!Y$27) -> 34.475837 | N28: =IF(Calc!$A$27="","",Calc!AJ$27) -> 12.35021 | O28: =IF(Calc!$A$27="","",Calc!J$27) -> 191.74571 | P28: =IF(Calc!$A$27="","",Calc!L$27) -> 69.879768 | Q28: =IF(Calc!$A$27="","",Calc!N$27) -> 4.3314987 | R28: =IF(Calc!$A$27="","",Calc!O$27) -> 0.55188593 | S28: =IF(Calc!$A$27="","",Calc!Q$27) -> 0.0026737968 | T28: =IF(Calc!$A$27="","",Calc!R$27) -> 0.25 | U28: =IF(Calc!$A$27="","",Calc!AK$27) -> FY2026Q3E | V28: =IF(Calc!$A$27="","",Calc!AL$27) -> consensus | W28: =IF(Calc!$A$27="","",Calc!AN$27) -> 0
A29: =IF(Calc!$A$28="","",Calc!A$28) | B29: =IF(Calc!$A$28="","",Calc!B$28) | C29: =IF(Calc!$A$28="","",Calc!C$28) | D29: =IF(Calc!$A$28="","",Calc!D$28) | E29: =IF(Calc!$A$28="","",Calc!AA$28) | F29: =IF(Calc!$A$28="","",Calc!AB$28) | G29: =IF(Calc!$A$28="","",Calc!AG$28) | H29: =IF(Calc!$A$28="","",Calc!AH$28) | I29: =IF(Calc!$A$28="","",Calc!AI$28) | J29: =IF(Calc!$A$28="","",Calc!T$28) | K29: =IF(Calc!$A$28="","",Calc!W$28) | L29: =IF(Calc!$A$28="","",Calc!X$28) | M29: =IF(Calc!$A$28="","",Calc!Y$28) | N29: =IF(Calc!$A$28="","",Calc!AJ$28) | O29: =IF(Calc!$A$28="","",Calc!J$28) | P29: =IF(Calc!$A$28="","",Calc!L$28) | Q29: =IF(Calc!$A$28="","",Calc!N$28) | R29: =IF(Calc!$A$28="","",Calc!O$28) | S29: =IF(Calc!$A$28="","",Calc!Q$28) | T29: =IF(Calc!$A$28="","",Calc!R$28) | U29: =IF(Calc!$A$28="","",Calc!AK$28) | V29: =IF(Calc!$A$28="","",Calc!AL$28) | W29: =IF(Calc!$A$28="","",Calc!AN$28)
A30: =IF(Calc!$A$29="","",Calc!A$29) | B30: =IF(Calc!$A$29="","",Calc!B$29) | C30: =IF(Calc!$A$29="","",Calc!C$29) | D30: =IF(Calc!$A$29="","",Calc!D$29) | E30: =IF(Calc!$A$29="","",Calc!AA$29) | F30: =IF(Calc!$A$29="","",Calc!AB$29) | G30: =IF(Calc!$A$29="","",Calc!AG$29) | H30: =IF(Calc!$A$29="","",Calc!AH$29) | I30: =IF(Calc!$A$29="","",Calc!AI$29) | J30: =IF(Calc!$A$29="","",Calc!T$29) | K30: =IF(Calc!$A$29="","",Calc!W$29) | L30: =IF(Calc!$A$29="","",Calc!X$29) | M30: =IF(Calc!$A$29="","",Calc!Y$29) | N30: =IF(Calc!$A$29="","",Calc!AJ$29) | O30: =IF(Calc!$A$29="","",Calc!J$29) | P30: =IF(Calc!$A$29="","",Calc!L$29) | Q30: =IF(Calc!$A$29="","",Calc!N$29) | R30: =IF(Calc!$A$29="","",Calc!O$29) | S30: =IF(Calc!$A$29="","",Calc!Q$29) | T30: =IF(Calc!$A$29="","",Calc!R$29) | U30: =IF(Calc!$A$29="","",Calc!AK$29) | V30: =IF(Calc!$A$29="","",Calc!AL$29) | W30: =IF(Calc!$A$29="","",Calc!AN$29)
A31: =IF(Calc!$A$30="","",Calc!A$30) | B31: =IF(Calc!$A$30="","",Calc!B$30) | C31: =IF(Calc!$A$30="","",Calc!C$30) | D31: =IF(Calc!$A$30="","",Calc!D$30) | E31: =IF(Calc!$A$30="","",Calc!AA$30) | F31: =IF(Calc!$A$30="","",Calc!AB$30) | G31: =IF(Calc!$A$30="","",Calc!AG$30) | H31: =IF(Calc!$A$30="","",Calc!AH$30) | I31: =IF(Calc!$A$30="","",Calc!AI$30) | J31: =IF(Calc!$A$30="","",Calc!T$30) | K31: =IF(Calc!$A$30="","",Calc!W$30) | L31: =IF(Calc!$A$30="","",Calc!X$30) | M31: =IF(Calc!$A$30="","",Calc!Y$30) | N31: =IF(Calc!$A$30="","",Calc!AJ$30) | O31: =IF(Calc!$A$30="","",Calc!J$30) | P31: =IF(Calc!$A$30="","",Calc!L$30) | Q31: =IF(Calc!$A$30="","",Calc!N$30) | R31: =IF(Calc!$A$30="","",Calc!O$30) | S31: =IF(Calc!$A$30="","",Calc!Q$30) | T31: =IF(Calc!$A$30="","",Calc!R$30) | U31: =IF(Calc!$A$30="","",Calc!AK$30) | V31: =IF(Calc!$A$30="","",Calc!AL$30) | W31: =IF(Calc!$A$30="","",Calc!AN$30)
A32: =IF(Calc!$A$31="","",Calc!A$31) | B32: =IF(Calc!$A$31="","",Calc!B$31) | C32: =IF(Calc!$A$31="","",Calc!C$31) | D32: =IF(Calc!$A$31="","",Calc!D$31) | E32: =IF(Calc!$A$31="","",Calc!AA$31) | F32: =IF(Calc!$A$31="","",Calc!AB$31) | G32: =IF(Calc!$A$31="","",Calc!AG$31) | H32: =IF(Calc!$A$31="","",Calc!AH$31) | I32: =IF(Calc!$A$31="","",Calc!AI$31) | J32: =IF(Calc!$A$31="","",Calc!T$31) | K32: =IF(Calc!$A$31="","",Calc!W$31) | L32: =IF(Calc!$A$31="","",Calc!X$31) | M32: =IF(Calc!$A$31="","",Calc!Y$31) | N32: =IF(Calc!$A$31="","",Calc!AJ$31) | O32: =IF(Calc!$A$31="","",Calc!J$31) | P32: =IF(Calc!$A$31="","",Calc!L$31) | Q32: =IF(Calc!$A$31="","",Calc!N$31) | R32: =IF(Calc!$A$31="","",Calc!O$31) | S32: =IF(Calc!$A$31="","",Calc!Q$31) | T32: =IF(Calc!$A$31="","",Calc!R$31) | U32: =IF(Calc!$A$31="","",Calc!AK$31) | V32: =IF(Calc!$A$31="","",Calc!AL$31) | W32: =IF(Calc!$A$31="","",Calc!AN$31)
A33: =IF(Calc!$A$32="","",Calc!A$32) | B33: =IF(Calc!$A$32="","",Calc!B$32) | C33: =IF(Calc!$A$32="","",Calc!C$32) | D33: =IF(Calc!$A$32="","",Calc!D$32) | E33: =IF(Calc!$A$32="","",Calc!AA$32) | F33: =IF(Calc!$A$32="","",Calc!AB$32) | G33: =IF(Calc!$A$32="","",Calc!AG$32) | H33: =IF(Calc!$A$32="","",Calc!AH$32) | I33: =IF(Calc!$A$32="","",Calc!AI$32) | J33: =IF(Calc!$A$32="","",Calc!T$32) | K33: =IF(Calc!$A$32="","",Calc!W$32) | L33: =IF(Calc!$A$32="","",Calc!X$32) | M33: =IF(Calc!$A$32="","",Calc!Y$32) | N33: =IF(Calc!$A$32="","",Calc!AJ$32) | O33: =IF(Calc!$A$32="","",Calc!J$32) | P33: =IF(Calc!$A$32="","",Calc!L$32) | Q33: =IF(Calc!$A$32="","",Calc!N$32) | R33: =IF(Calc!$A$32="","",Calc!O$32) | S33: =IF(Calc!$A$32="","",Calc!Q$32) | T33: =IF(Calc!$A$32="","",Calc!R$32) | U33: =IF(Calc!$A$32="","",Calc!AK$32) | V33: =IF(Calc!$A$32="","",Calc!AL$32) | W33: =IF(Calc!$A$32="","",Calc!AN$32)
A35: 加速度(pp) ＝ 最新季 QoQ − 上一季 QoQ。QoQ ＝ 本季營收 ÷ 上一季營收 − 1（季度成長率）。正值代表這一季的成長速度比上一季快。
A36: ROE 顯示 N/M 代表股東權益為負（大量庫藏股或累積虧損），此時 ROE 沒有比較意義。殖利率顯示「不配息」代表該檔近四季沒有配息紀錄。
A37: 資料來源：yfinance / yahooquery / Alpha Vantage / SEC EDGAR

Sheet Stock_Card
A1: 個股卡 | Z1: =IF(INDEX(Calc!$AM$2:$AM$100,MATCH($B$2,Calc!$A$2:$A$100,0))<Config!$B$7,"⚠ 分析師家數不足，共識預估可信度低 ","")&IF(NOT(ISNUMBER(INDEX(Calc!$AG$2:$AG$100,MATCH($B$2,Calc!$A$2:$A$100,0)))),"⚠ 股東權益為負，ROE 無比較意義 ","")&IF(INDEX(Calc!$P$2:$P$100,MATCH($B$2,Calc!$A$2:$A$100,0))=0,"ℹ 此檔近四季未配息 ","")
A2: 選擇股票 → | B2: 2330 | D2: =IF($B$2="","",IFERROR(INDEX(Calc!$B$2:$B$100,MATCH($B$2,Calc!$A$2:$A$100,0)),"")) -> 台積電 | G2: =IF($B$2="","",IFERROR(INDEX(Calc!$C$2:$C$100,MATCH($B$2,Calc!$A$2:$A$100,0)),"")) -> 核心
C3: ← 這個下拉同時驅動「年度檢視」與「季度檢視」兩頁
A4: 股價 | B4: =IF($B$2="","",IFERROR(INDEX(Calc!$D$2:$D$100,MATCH($B$2,Calc!$A$2:$A$100,0)),"")) -> 2420 | D4: 分析師家數 | E4: =IF($B$2="","",IFERROR(INDEX(Calc!$AM$2:$AM$100,MATCH($B$2,Calc!$A$2:$A$100,0)),"")) -> 20 | G4: 下次財報日 | H4: =IF($B$2="","",IFERROR(INDEX(Calc!$AN$2:$AN$100,MATCH($B$2,Calc!$A$2:$A$100,0)),"")) -> 0 | I4: 資料日期 | J4: =IF($B$2="","",IFERROR(INDEX(Calc!$AO$2:$AO$100,MATCH($B$2,Calc!$A$2:$A$100,0)),"")) -> 46311
A6: 估值 · 殖利率 | D6: 成長 | G6: 毛利率 · ROE
A7: PE_TTM | B7: =IF($B$2="","",IFERROR(INDEX(Calc!$J$2:$J$100,MATCH($B$2,Calc!$A$2:$A$100,0)),"")) -> 28.048215 | D7: 營收QoQ 最新季 | E7: =IF($B$2="","",IFERROR(INDEX(Calc!$T$2:$T$100,MATCH($B$2,Calc!$A$2:$A$100,0)),"")) -> 0.12016259 | G7: 毛利率_TTM | H7: =IF($B$2="","",IFERROR(INDEX(Calc!$AA$2:$AA$100,MATCH($B$2,Calc!$A$2:$A$100,0)),"")) -> 0.64230169
A8: PE Forward | B8: =IF($B$2="","",IFERROR(INDEX(Calc!$L$2:$L$100,MATCH($B$2,Calc!$A$2:$A$100,0)),"")) -> 17.246923 | D8: 上一季 QoQ | E8: =IF($B$2="","",IFERROR(INDEX(Calc!$U$2:$U$100,MATCH($B$2,Calc!$A$2:$A$100,0)),"")) -> 0.084135193 | G8: 5 年平均 | H8: =IF($B$2="","",IFERROR(INDEX(Calc!$AB$2:$AB$100,MATCH($B$2,Calc!$A$2:$A$100,0)),"")) -> 0.58974357
A9: PEG_T | B9: =IF($B$2="","",IFERROR(INDEX(Calc!$N$2:$N$100,MATCH($B$2,Calc!$A$2:$A$100,0)),"")) -> 0.52699199 | D9: 加速度 (pp) | E9: =IF($B$2="","",IFERROR(INDEX(Calc!$V$2:$V$100,MATCH($B$2,Calc!$A$2:$A$100,0)),"")) -> 3.60274 | G9: 差距 (bps) | H9: =IF($B$2="","",IFERROR(INDEX(Calc!$AC$2:$AC$100,MATCH($B$2,Calc!$A$2:$A$100,0)),"")) -> 525.58123
A10: PEG_F | B10: =IF($B$2="","",IFERROR(INDEX(Calc!$O$2:$O$100,MATCH($B$2,Calc!$A$2:$A$100,0)),"")) -> 0.51144944 | D10: 動能判讀 | E10: =IF($B$2="","",IFERROR(INDEX(Calc!$X$2:$X$100,MATCH($B$2,Calc!$A$2:$A$100,0)),"")) -> 成長且加速 | G10: ΔGM_YoY (bps) | H10: =IF($B$2="","",IFERROR(INDEX(Calc!$AD$2:$AD$100,MATCH($B$2,Calc!$A$2:$A$100,0)),"")) -> 910.28176
A11: EPS_TTM (Adj) | B11: =IF($B$2="","",IFERROR(INDEX(Calc!$F$2:$F$100,MATCH($B$2,Calc!$A$2:$A$100,0)),"")) -> 86.28 | D11: 同期加速度 (pp) | E11: =IF($B$2="","",IFERROR(INDEX(Calc!$Y$2:$Y$100,MATCH($B$2,Calc!$A$2:$A$100,0)),"")) -> 0.75170257 | G11: ROE_TTM | H11: =IF($B$2="","",IFERROR(INDEX(Calc!$AG$2:$AG$100,MATCH($B$2,Calc!$A$2:$A$100,0)),"")) -> 0.40630776
A12: EPS Forward | B12: =IF($B$2="","",IFERROR(INDEX(Calc!$H$2:$H$100,MATCH($B$2,Calc!$A$2:$A$100,0)),"")) -> 140.31488 | D12: 營收YoY 最新季 | E12: =IF($B$2="","",IFERROR(INDEX(Calc!$S$2:$S$100,MATCH($B$2,Calc!$A$2:$A$100,0)),"")) -> 0.36045332 | G12: 5 年平均 | H12: =IF($B$2="","",IFERROR(INDEX(Calc!$AH$2:$AH$100,MATCH($B$2,Calc!$A$2:$A$100,0)),"")) -> 0.3398412
A13: 殖利率 | B13: =IF($B$2="","",IFERROR(INDEX(Calc!$Q$2:$Q$100,MATCH($B$2,Calc!$A$2:$A$100,0)),"")) -> 0.0090909505 | D13: EPS_YoY 最新季 | E13: =IF($B$2="","",IFERROR(INDEX(Calc!$Z$2:$Z$100,MATCH($B$2,Calc!$A$2:$A$100,0)),"")) -> 0.77408854 | G13: ROE Forward | H13: =IF($B$2="","",IFERROR(INDEX(Calc!$AI$2:$AI$100,MATCH($B$2,Calc!$A$2:$A$100,0)),"")) -> 0.44646533
A14: 每股配息 TTM | B14: =IF($B$2="","",IFERROR(INDEX(Calc!$P$2:$P$100,MATCH($B$2,Calc!$A$2:$A$100,0)),"")) -> 22.0001 | D14: EPS成長_F (F1→F2) | E14: =IF($B$2="","",IFERROR(INDEX(Calc!$M$2:$M$100,MATCH($B$2,Calc!$A$2:$A$100,0)),"")) -> 0.33721659 | G14: 每股淨值 | H14: =IF($B$2="","",IFERROR(INDEX(Calc!$AE$2:$AE$100,MATCH($B$2,Calc!$A$2:$A$100,0)),"")) -> 248.04977
D15: 當季EPS預估 | E15: =IF($B$2="","",IFERROR(INDEX(Calc!$AJ$2:$AJ$100,MATCH($B$2,Calc!$A$2:$A$100,0)),"")) -> 28.19147
A16: 旗標 | B16: =IF($B$2="","",IF(LEN($Z$1)=0,"✓ 目前沒有觸發任何旗標",$Z$1)) -> ✓ 目前沒有觸發任何旗標

Sheet 年度檢視
A1: 年度檢視 · 近六財年逐年指標 | Z1: =IF(Stock_Card!$B$2="","",IFERROR(SUMIFS(Raw_Q!$C$2:$C$600,Raw_Q!$A$2:$A$600,Stock_Card!$B$2,Raw_Q!$R$2:$R$600,0),"")) -> 2026
A2: 股票 | B2: =Stock_Card!$B$2 -> 2330 | C2: ← 在 Stock_Card 換股票，這一頁與「季度檢視」同步。每一列＝一個完整財年，全部由 Raw_Q 的季度資料 rollup 而來。
A4: 財年 | B4: 實際季數 | C4: 營收($M) | D4: 營收YoY | E4: 毛利率 | F4: 毛利率變化(bps) | G4: EPS(Adj) | H4: EPS YoY | I4: ROE | J4: 每股配息 | K4: 年末股價 | L4: 殖利率 | M4: PE | N4: PEG_T
A5: =IF(Stock_Card!$B$2="","",IFERROR($Z$1-5,"")) -> 2021 | B5: =IF(Stock_Card!$B$2="","",COUNTIFS(Raw_Q!$A$2:$A$600,Stock_Card!$B$2,Raw_Q!$C$2:$C$600,$A5,Raw_Q!$F$2:$F$600,"N")) -> 4 | C5: =IF($B5>=4,SUMIFS(Raw_Q!$I$2:$I$600,Raw_Q!$A$2:$A$600,Stock_Card!$B$2,Raw_Q!$C$2:$C$600,$A5,Raw_Q!$F$2:$F$600,"N"),"") -> 1587415 | D5: =IFERROR(IF(AND(ISNUMBER(C5),ISNUMBER(C4)),C5/C4-1,""),"") | E5: =IF($B5>=4,IFERROR(SUMIFS(Raw_Q!$J$2:$J$600,Raw_Q!$A$2:$A$600,Stock_Card!$B$2,Raw_Q!$C$2:$C$600,$A5,Raw_Q!$F$2:$F$600,"N")/C5,""),"") -> 0.51627158 | F5: =IFERROR(IF(AND(ISNUMBER(E5),ISNUMBER(E4)),(E5-E4)*10000,""),"") | G5: =IF($B5>=4,SUMIFS(Raw_Q!$L$2:$L$600,Raw_Q!$A$2:$A$600,Stock_Card!$B$2,Raw_Q!$C$2:$C$600,$A5,Raw_Q!$F$2:$F$600,"N"),"") -> 23.02 | H5: =IFERROR(IF(AND(ISNUMBER(G5),ISNUMBER(G4)),G5/G4-1,""),"") | I5: =IF($B5>=4,IFERROR(IF(MIN(SUMIFS(Raw_Q!$O$2:$O$600,Raw_Q!$A$2:$A$600,Stock_Card!$B$2,Raw_Q!$C$2:$C$600,$A5,Raw_Q!$D$2:$D$600,4,Raw_Q!$F$2:$F$600,"N"),SUMIFS(Raw_Q!$O$2:$O$600,Raw_Q!$A$2:$A$600,Stock_Card!$B$2,Raw_Q!$C$2:$C$600,$A5-1,Raw_Q!$D$2:$D$600,4,Raw_Q!$F$2:$F$600,"N"))<=0,"N/M",SUMPRODUCT((Raw_Q!$A$2:$A$600=Stock_Card!$B$2)*(Raw_Q!$C$2:$C$600=$A5)*(Raw_Q!$F$2:$F$600="N")*Raw_Q!$L$2:$L$600*Raw_Q!$M$2:$M$600)/((SUMIFS(Raw_Q!$O$2:$O$600,Raw_Q!$A$2:$A$600,Stock_Card!$B$2,Raw_Q!$C$2:$C$600,$A5,Raw_Q!$D$2:$D$600,4,Raw_Q!$F$2:$F$600,"N")+SUMIFS(Raw_Q!$O$2:$O$600,Raw_Q!$A$2:$A$600,Stock_Card!$B$2,Raw_Q!$C$2:$C$600,$A5-1,Raw_Q!$D$2:$D$600,4,Raw_Q!$F$2:$F$600,"N"))/2)),"N/M"),"") -> 0.29712579 | J5: =IF($B5>=4,SUMIFS(Raw_Q!$P$2:$P$600,Raw_Q!$A$2:$A$600,Stock_Card!$B$2,Raw_Q!$C$2:$C$600,$A5,Raw_Q!$F$2:$F$600,"N"),"") -> 10.5 | K5: =IFERROR(IF(SUMIFS(Raw_Q!$Q$2:$Q$600,Raw_Q!$A$2:$A$600,Stock_Card!$B$2,Raw_Q!$C$2:$C$600,$A5,Raw_Q!$D$2:$D$600,4,Raw_Q!$F$2:$F$600,"N")=0,"",SUMIFS(Raw_Q!$Q$2:$Q$600,Raw_Q!$A$2:$A$600,Stock_Card!$B$2,Raw_Q!$C$2:$C$600,$A5,Raw_Q!$D$2:$D$600,4,Raw_Q!$F$2:$F$600,"N")),"") -> 615 | L5: =IFERROR(IF(OR(NOT(ISNUMBER(K5)),NOT(ISNUMBER(J5)),J5=0),"",J5/K5),"") -> 0.017073171 | M5: =IFERROR(IF(OR(NOT(ISNUMBER(K5)),NOT(ISNUMBER(G5)),G5<=0),"",K5/G5),"") -> 26.715899 | N5: =IFERROR(IF(OR(NOT(ISNUMBER(M5)),NOT(ISNUMBER(H5))),"",IF(H5<Config!$B$6,"N/M",M5/(H5*100))),"")
A6: =IF(Stock_Card!$B$2="","",IFERROR($Z$1-4,"")) -> 2022 | B6: =IF(Stock_Card!$B$2="","",COUNTIFS(Raw_Q!$A$2:$A$600,Stock_Card!$B$2,Raw_Q!$C$2:$C$600,$A6,Raw_Q!$F$2:$F$600,"N")) -> 4 | C6: =IF($B6>=4,SUMIFS(Raw_Q!$I$2:$I$600,Raw_Q!$A$2:$A$600,Stock_Card!$B$2,Raw_Q!$C$2:$C$600,$A6,Raw_Q!$F$2:$F$600,"N"),"") -> 2263891.3 | D6: =IFERROR(IF(AND(ISNUMBER(C6),ISNUMBER(C5)),C6/C5-1,""),"") -> 0.42614958 | E6: =IF($B6>=4,IFERROR(SUMIFS(Raw_Q!$J$2:$J$600,Raw_Q!$A$2:$A$600,Stock_Card!$B$2,Raw_Q!$C$2:$C$600,$A6,Raw_Q!$F$2:$F$600,"N")/C6,""),"") -> 0.59559167 | F6: =IFERROR(IF(AND(ISNUMBER(E6),ISNUMBER(E5)),(E6-E5)*10000,""),"") -> 793.20097 | G6: =IF($B6>=4,SUMIFS(Raw_Q!$L$2:$L$600,Raw_Q!$A$2:$A$600,Stock_Card!$B$2,Raw_Q!$C$2:$C$600,$A6,Raw_Q!$F$2:$F$600,"N"),"") -> 39.2 | H6: =IFERROR(IF(AND(ISNUMBER(G6),ISNUMBER(G5)),G6/G5-1,""),"") -> 0.70286707 | I6: =IF($B6>=4,IFERROR(IF(MIN(SUMIFS(Raw_Q!$O$2:$O$600,Raw_Q!$A$2:$A$600,Stock_Card!$B$2,Raw_Q!$C$2:$C$600,$A6,Raw_Q!$D$2:$D$600,4,Raw_Q!$F$2:$F$600,"N"),SUMIFS(Raw_Q!$O$2:$O$600,Raw_Q!$A$2:$A$600,Stock_Card!$B$2,Raw_Q!$C$2:$C$600,$A6-1,Raw_Q!$D$2:$D$600,4,Raw_Q!$F$2:$F$600,"N"))<=0,"N/M",SUMPRODUCT((Raw_Q!$A$2:$A$600=Stock_Card!$B$2)*(Raw_Q!$C$2:$C$600=$A6)*(Raw_Q!$F$2:$F$600="N")*Raw_Q!$L$2:$L$600*Raw_Q!$M$2:$M$600)/((SUMIFS(Raw_Q!$O$2:$O$600,Raw_Q!$A$2:$A$600,Stock_Card!$B$2,Raw_Q!$C$2:$C$600,$A6,Raw_Q!$D$2:$D$600,4,Raw_Q!$F$2:$F$600,"N")+SUMIFS(Raw_Q!$O$2:$O$600,Raw_Q!$A$2:$A$600,Stock_Card!$B$2,Raw_Q!$C$2:$C$600,$A6-1,Raw_Q!$D$2:$D$600,4,Raw_Q!$F$2:$F$600,"N"))/2)),"N/M"),"") -> 0.39753373 | J6: =IF($B6>=4,SUMIFS(Raw_Q!$P$2:$P$600,Raw_Q!$A$2:$A$600,Stock_Card!$B$2,Raw_Q!$C$2:$C$600,$A6,Raw_Q!$F$2:$F$600,"N"),"") -> 11 | K6: =IFERROR(IF(SUMIFS(Raw_Q!$Q$2:$Q$600,Raw_Q!$A$2:$A$600,Stock_Card!$B$2,Raw_Q!$C$2:$C$600,$A6,Raw_Q!$D$2:$D$600,4,Raw_Q!$F$2:$F$600,"N")=0,"",SUMIFS(Raw_Q!$Q$2:$Q$600,Raw_Q!$A$2:$A$600,Stock_Card!$B$2,Raw_Q!$C$2:$C$600,$A6,Raw_Q!$D$2:$D$600,4,Raw_Q!$F$2:$F$600,"N")),"") -> 448.5 | L6: =IFERROR(IF(OR(NOT(ISNUMBER(K6)),NOT(ISNUMBER(J6)),J6=0),"",J6/K6),"") -> 0.024526198 | M6: =IFERROR(IF(OR(NOT(ISNUMBER(K6)),NOT(ISNUMBER(G6)),G6<=0),"",K6/G6),"") -> 11.441327 | N6: =IFERROR(IF(OR(NOT(ISNUMBER(M6)),NOT(ISNUMBER(H6))),"",IF(H6<Config!$B$6,"N/M",M6/(H6*100))),"") -> 0.1627808
A7: =IF(Stock_Card!$B$2="","",IFERROR($Z$1-3,"")) -> 2023 | B7: =IF(Stock_Card!$B$2="","",COUNTIFS(Raw_Q!$A$2:$A$600,Stock_Card!$B$2,Raw_Q!$C$2:$C$600,$A7,Raw_Q!$F$2:$F$600,"N")) -> 4 | C7: =IF($B7>=4,SUMIFS(Raw_Q!$I$2:$I$600,Raw_Q!$A$2:$A$600,Stock_Card!$B$2,Raw_Q!$C$2:$C$600,$A7,Raw_Q!$F$2:$F$600,"N"),"") -> 2161735.8 | D7: =IFERROR(IF(AND(ISNUMBER(C7),ISNUMBER(C6)),C7/C6-1,""),"") -> -0.045123832 | E7: =IF($B7>=4,IFERROR(SUMIFS(Raw_Q!$J$2:$J$600,Raw_Q!$A$2:$A$600,Stock_Card!$B$2,Raw_Q!$C$2:$C$600,$A7,Raw_Q!$F$2:$F$600,"N")/C7,""),"") -> 0.54359585 | F7: =IFERROR(IF(AND(ISNUMBER(E7),ISNUMBER(E6)),(E7-E6)*10000,""),"") -> -519.95827 | G7: =IF($B7>=4,SUMIFS(Raw_Q!$L$2:$L$600,Raw_Q!$A$2:$A$600,Stock_Card!$B$2,Raw_Q!$C$2:$C$600,$A7,Raw_Q!$F$2:$F$600,"N"),"") -> 32.34 | H7: =IFERROR(IF(AND(ISNUMBER(G7),ISNUMBER(G6)),G7/G6-1,""),"") -> -0.175 | I7: =IF($B7>=4,IFERROR(IF(MIN(SUMIFS(Raw_Q!$O$2:$O$600,Raw_Q!$A$2:$A$600,Stock_Card!$B$2,Raw_Q!$C$2:$C$600,$A7,Raw_Q!$D$2:$D$600,4,Raw_Q!$F$2:$F$600,"N"),SUMIFS(Raw_Q!$O$2:$O$600,Raw_Q!$A$2:$A$600,Stock_Card!$B$2,Raw_Q!$C$2:$C$600,$A7-1,Raw_Q!$D$2:$D$600,4,Raw_Q!$F$2:$F$600,"N"))<=0,"N/M",SUMPRODUCT((Raw_Q!$A$2:$A$600=Stock_Card!$B$2)*(Raw_Q!$C$2:$C$600=$A7)*(Raw_Q!$F$2:$F$600="N")*Raw_Q!$L$2:$L$600*Raw_Q!$M$2:$M$600)/((SUMIFS(Raw_Q!$O$2:$O$600,Raw_Q!$A$2:$A$600,Stock_Card!$B$2,Raw_Q!$C$2:$C$600,$A7,Raw_Q!$D$2:$D$600,4,Raw_Q!$F$2:$F$600,"N")+SUMIFS(Raw_Q!$O$2:$O$600,Raw_Q!$A$2:$A$600,Stock_Card!$B$2,Raw_Q!$C$2:$C$600,$A7-1,Raw_Q!$D$2:$D$600,4,Raw_Q!$F$2:$F$600,"N"))/2)),"N/M"),"") -> 0.26189016 | J7: =IF($B7>=4,SUMIFS(Raw_Q!$P$2:$P$600,Raw_Q!$A$2:$A$600,Stock_Card!$B$2,Raw_Q!$C$2:$C$600,$A7,Raw_Q!$F$2:$F$600,"N"),"") -> 11.499641 | K7: =IFERROR(IF(SUMIFS(Raw_Q!$Q$2:$Q$600,Raw_Q!$A$2:$A$600,Stock_Card!$B$2,Raw_Q!$C$2:$C$600,$A7,Raw_Q!$D$2:$D$600,4,Raw_Q!$F$2:$F$600,"N")=0,"",SUMIFS(Raw_Q!$Q$2:$Q$600,Raw_Q!$A$2:$A$600,Stock_Card!$B$2,Raw_Q!$C$2:$C$600,$A7,Raw_Q!$D$2:$D$600,4,Raw_Q!$F$2:$F$600,"N")),"") -> 593 | L7: =IFERROR(IF(OR(NOT(ISNUMBER(K7)),NOT(ISNUMBER(J7)),J7=0),"",J7/K7),"") -> 0.019392313 | M7: =IFERROR(IF(OR(NOT(ISNUMBER(K7)),NOT(ISNUMBER(G7)),G7<=0),"",K7/G7),"") -> 18.336425 | N7: =IFERROR(IF(OR(NOT(ISNUMBER(M7)),NOT(ISNUMBER(H7))),"",IF(H7<Config!$B$6,"N/M",M7/(H7*100))),"") -> N/M
A8: =IF(Stock_Card!$B$2="","",IFERROR($Z$1-2,"")) -> 2024 | B8: =IF(Stock_Card!$B$2="","",COUNTIFS(Raw_Q!$A$2:$A$600,Stock_Card!$B$2,Raw_Q!$C$2:$C$600,$A8,Raw_Q!$F$2:$F$600,"N")) -> 4 | C8: =IF($B8>=4,SUMIFS(Raw_Q!$I$2:$I$600,Raw_Q!$A$2:$A$600,Stock_Card!$B$2,Raw_Q!$C$2:$C$600,$A8,Raw_Q!$F$2:$F$600,"N"),"") -> 2894307.7 | D8: =IFERROR(IF(AND(ISNUMBER(C8),ISNUMBER(C7)),C8/C7-1,""),"") -> 0.3388813 | E8: =IF($B8>=4,IFERROR(SUMIFS(Raw_Q!$J$2:$J$600,Raw_Q!$A$2:$A$600,Stock_Card!$B$2,Raw_Q!$C$2:$C$600,$A8,Raw_Q!$F$2:$F$600,"N")/C8,""),"") -> 0.56122352 | F8: =IFERROR(IF(AND(ISNUMBER(E8),ISNUMBER(E7)),(E8-E7)*10000,""),"") -> 176.27675 | G8: =IF($B8>=4,SUMIFS(Raw_Q!$L$2:$L$600,Raw_Q!$A$2:$A$600,Stock_Card!$B$2,Raw_Q!$C$2:$C$600,$A8,Raw_Q!$F$2:$F$600,"N"),"") -> 45.26 | H8: =IFERROR(IF(AND(ISNUMBER(G8),ISNUMBER(G7)),G8/G7-1,""),"") -> 0.39950526 | I8: =IF($B8>=4,IFERROR(IF(MIN(SUMIFS(Raw_Q!$O$2:$O$600,Raw_Q!$A$2:$A$600,Stock_Card!$B$2,Raw_Q!$C$2:$C$600,$A8,Raw_Q!$D$2:$D$600,4,Raw_Q!$F$2:$F$600,"N"),SUMIFS(Raw_Q!$O$2:$O$600,Raw_Q!$A$2:$A$600,Stock_Card!$B$2,Raw_Q!$C$2:$C$600,$A8-1,Raw_Q!$D$2:$D$600,4,Raw_Q!$F$2:$F$600,"N"))<=0,"N/M",SUMPRODUCT((Raw_Q!$A$2:$A$600=Stock_Card!$B$2)*(Raw_Q!$C$2:$C$600=$A8)*(Raw_Q!$F$2:$F$600="N")*Raw_Q!$L$2:$L$600*Raw_Q!$M$2:$M$600)/((SUMIFS(Raw_Q!$O$2:$O$600,Raw_Q!$A$2:$A$600,Stock_Card!$B$2,Raw_Q!$C$2:$C$600,$A8,Raw_Q!$D$2:$D$600,4,Raw_Q!$F$2:$F$600,"N")+SUMIFS(Raw_Q!$O$2:$O$600,Raw_Q!$A$2:$A$600,Stock_Card!$B$2,Raw_Q!$C$2:$C$600,$A8-1,Raw_Q!$D$2:$D$600,4,Raw_Q!$F$2:$F$600,"N"))/2)),"N/M"),"") -> 0.30300105 | J8: =IF($B8>=4,SUMIFS(Raw_Q!$P$2:$P$600,Raw_Q!$A$2:$A$600,Stock_Card!$B$2,Raw_Q!$C$2:$C$600,$A8,Raw_Q!$F$2:$F$600,"N"),"") -> 14.999355 | K8: =IFERROR(IF(SUMIFS(Raw_Q!$Q$2:$Q$600,Raw_Q!$A$2:$A$600,Stock_Card!$B$2,Raw_Q!$C$2:$C$600,$A8,Raw_Q!$D$2:$D$600,4,Raw_Q!$F$2:$F$600,"N")=0,"",SUMIFS(Raw_Q!$Q$2:$Q$600,Raw_Q!$A$2:$A$600,Stock_Card!$B$2,Raw_Q!$C$2:$C$600,$A8,Raw_Q!$D$2:$D$600,4,Raw_Q!$F$2:$F$600,"N")),"") -> 1075 | L8: =IFERROR(IF(OR(NOT(ISNUMBER(K8)),NOT(ISNUMBER(J8)),J8=0),"",J8/K8),"") -> 0.013952888 | M8: =IFERROR(IF(OR(NOT(ISNUMBER(K8)),NOT(ISNUMBER(G8)),G8<=0),"",K8/G8),"") -> 23.751657 | N8: =IFERROR(IF(OR(NOT(ISNUMBER(M8)),NOT(ISNUMBER(H8))),"",IF(H8<Config!$B$6,"N/M",M8/(H8*100))),"") -> 0.59452677
A9: =IF(Stock_Card!$B$2="","",IFERROR($Z$1-1,"")) -> 2025 | B9: =IF(Stock_Card!$B$2="","",COUNTIFS(Raw_Q!$A$2:$A$600,Stock_Card!$B$2,Raw_Q!$C$2:$C$600,$A9,Raw_Q!$F$2:$F$600,"N")) -> 4 | C9: =IF($B9>=4,SUMIFS(Raw_Q!$I$2:$I$600,Raw_Q!$A$2:$A$600,Stock_Card!$B$2,Raw_Q!$C$2:$C$600,$A9,Raw_Q!$F$2:$F$600,"N"),"") -> 3809054.3 | D9: =IFERROR(IF(AND(ISNUMBER(C9),ISNUMBER(C8)),C9/C8-1,""),"") -> 0.31605022 | E9: =IF($B9>=4,IFERROR(SUMIFS(Raw_Q!$J$2:$J$600,Raw_Q!$A$2:$A$600,Stock_Card!$B$2,Raw_Q!$C$2:$C$600,$A9,Raw_Q!$F$2:$F$600,"N")/C9,""),"") -> 0.59891349 | F9: =IFERROR(IF(AND(ISNUMBER(E9),ISNUMBER(E8)),(E9-E8)*10000,""),"") -> 376.89965 | G9: =IF($B9>=4,SUMIFS(Raw_Q!$L$2:$L$600,Raw_Q!$A$2:$A$600,Stock_Card!$B$2,Raw_Q!$C$2:$C$600,$A9,Raw_Q!$F$2:$F$600,"N"),"") -> 66.26 | H9: =IFERROR(IF(AND(ISNUMBER(G9),ISNUMBER(G8)),G9/G8-1,""),"") -> 0.46398586 | I9: =IF($B9>=4,IFERROR(IF(MIN(SUMIFS(Raw_Q!$O$2:$O$600,Raw_Q!$A$2:$A$600,Stock_Card!$B$2,Raw_Q!$C$2:$C$600,$A9,Raw_Q!$D$2:$D$600,4,Raw_Q!$F$2:$F$600,"N"),SUMIFS(Raw_Q!$O$2:$O$600,Raw_Q!$A$2:$A$600,Stock_Card!$B$2,Raw_Q!$C$2:$C$600,$A9-1,Raw_Q!$D$2:$D$600,4,Raw_Q!$F$2:$F$600,"N"))<=0,"N/M",SUMPRODUCT((Raw_Q!$A$2:$A$600=Stock_Card!$B$2)*(Raw_Q!$C$2:$C$600=$A9)*(Raw_Q!$F$2:$F$600="N")*Raw_Q!$L$2:$L$600*Raw_Q!$M$2:$M$600)/((SUMIFS(Raw_Q!$O$2:$O$600,Raw_Q!$A$2:$A$600,Stock_Card!$B$2,Raw_Q!$C$2:$C$600,$A9,Raw_Q!$D$2:$D$600,4,Raw_Q!$F$2:$F$600,"N")+SUMIFS(Raw_Q!$O$2:$O$600,Raw_Q!$A$2:$A$600,Stock_Card!$B$2,Raw_Q!$C$2:$C$600,$A9-1,Raw_Q!$D$2:$D$600,4,Raw_Q!$F$2:$F$600,"N"))/2)),"N/M"),"") -> 0.35399019 | J9: =IF($B9>=4,SUMIFS(Raw_Q!$P$2:$P$600,Raw_Q!$A$2:$A$600,Stock_Card!$B$2,Raw_Q!$C$2:$C$600,$A9,Raw_Q!$F$2:$F$600,"N"),"") -> 19.00007 | K9: =IFERROR(IF(SUMIFS(Raw_Q!$Q$2:$Q$600,Raw_Q!$A$2:$A$600,Stock_Card!$B$2,Raw_Q!$C$2:$C$600,$A9,Raw_Q!$D$2:$D$600,4,Raw_Q!$F$2:$F$600,"N")=0,"",SUMIFS(Raw_Q!$Q$2:$Q$600,Raw_Q!$A$2:$A$600,Stock_Card!$B$2,Raw_Q!$C$2:$C$600,$A9,Raw_Q!$D$2:$D$600,4,Raw_Q!$F$2:$F$600,"N")),"") -> 1550 | L9: =IFERROR(IF(OR(NOT(ISNUMBER(K9)),NOT(ISNUMBER(J9)),J9=0),"",J9/K9),"") -> 0.012258109 | M9: =IFERROR(IF(OR(NOT(ISNUMBER(K9)),NOT(ISNUMBER(G9)),G9<=0),"",K9/G9),"") -> 23.392695 | N9: =IFERROR(IF(OR(NOT(ISNUMBER(M9)),NOT(ISNUMBER(H9))),"",IF(H9<Config!$B$6,"N/M",M9/(H9*100))),"") -> 0.50416828
A10: =IF(Stock_Card!$B$2="","",IFERROR($Z$1-0,"")) -> 2026 | B10: =IF(Stock_Card!$B$2="","",COUNTIFS(Raw_Q!$A$2:$A$600,Stock_Card!$B$2,Raw_Q!$C$2:$C$600,$A10,Raw_Q!$F$2:$F$600,"N")) -> 2 | C10: =IF($B10>=4,SUMIFS(Raw_Q!$I$2:$I$600,Raw_Q!$A$2:$A$600,Stock_Card!$B$2,Raw_Q!$C$2:$C$600,$A10,Raw_Q!$F$2:$F$600,"N"),"") | D10: =IFERROR(IF(AND(ISNUMBER(C10),ISNUMBER(C9)),C10/C9-1,""),"") | E10: =IF($B10>=4,IFERROR(SUMIFS(Raw_Q!$J$2:$J$600,Raw_Q!$A$2:$A$600,Stock_Card!$B$2,Raw_Q!$C$2:$C$600,$A10,Raw_Q!$F$2:$F$600,"N")/C10,""),"") | F10: =IFERROR(IF(AND(ISNUMBER(E10),ISNUMBER(E9)),(E10-E9)*10000,""),"") | G10: =IF($B10>=4,SUMIFS(Raw_Q!$L$2:$L$600,Raw_Q!$A$2:$A$600,Stock_Card!$B$2,Raw_Q!$C$2:$C$600,$A10,Raw_Q!$F$2:$F$600,"N"),"") | H10: =IFERROR(IF(AND(ISNUMBER(G10),ISNUMBER(G9)),G10/G9-1,""),"") | I10: =IF($B10>=4,IFERROR(IF(MIN(SUMIFS(Raw_Q!$O$2:$O$600,Raw_Q!$A$2:$A$600,Stock_Card!$B$2,Raw_Q!$C$2:$C$600,$A10,Raw_Q!$D$2:$D$600,4,Raw_Q!$F$2:$F$600,"N"),SUMIFS(Raw_Q!$O$2:$O$600,Raw_Q!$A$2:$A$600,Stock_Card!$B$2,Raw_Q!$C$2:$C$600,$A10-1,Raw_Q!$D$2:$D$600,4,Raw_Q!$F$2:$F$600,"N"))<=0,"N/M",SUMPRODUCT((Raw_Q!$A$2:$A$600=Stock_Card!$B$2)*(Raw_Q!$C$2:$C$600=$A10)*(Raw_Q!$F$2:$F$600="N")*Raw_Q!$L$2:$L$600*Raw_Q!$M$2:$M$600)/((SUMIFS(Raw_Q!$O$2:$O$600,Raw_Q!$A$2:$A$600,Stock_Card!$B$2,Raw_Q!$C$2:$C$600,$A10,Raw_Q!$D$2:$D$600,4,Raw_Q!$F$2:$F$600,"N")+SUMIFS(Raw_Q!$O$2:$O$600,Raw_Q!$A$2:$A$600,Stock_Card!$B$2,Raw_Q!$C$2:$C$600,$A10-1,Raw_Q!$D$2:$D$600,4,Raw_Q!$F$2:$F$600,"N"))/2)),"N/M"),"") | J10: =IF($B10>=4,SUMIFS(Raw_Q!$P$2:$P$600,Raw_Q!$A$2:$A$600,Stock_Card!$B$2,Raw_Q!$C$2:$C$600,$A10,Raw_Q!$F$2:$F$600,"N"),"") | K10: =IFERROR(IF(SUMIFS(Raw_Q!$Q$2:$Q$600,Raw_Q!$A$2:$A$600,Stock_Card!$B$2,Raw_Q!$C$2:$C$600,$A10,Raw_Q!$D$2:$D$600,4,Raw_Q!$F$2:$F$600,"N")=0,"",SUMIFS(Raw_Q!$Q$2:$Q$600,Raw_Q!$A$2:$A$600,Stock_Card!$B$2,Raw_Q!$C$2:$C$600,$A10,Raw_Q!$D$2:$D$600,4,Raw_Q!$F$2:$F$600,"N")),"") | L10: =IFERROR(IF(OR(NOT(ISNUMBER(K10)),NOT(ISNUMBER(J10)),J10=0),"",J10/K10),"") | M10: =IFERROR(IF(OR(NOT(ISNUMBER(K10)),NOT(ISNUMBER(G10)),G10<=0),"",K10/G10),"") | N10: =IFERROR(IF(OR(NOT(ISNUMBER(M10)),NOT(ISNUMBER(H10))),"",IF(H10<Config!$B$6,"N/M",M10/(H10*100))),"")
A11: ↓ 以下兩列是「現況」，不是年度值。F 欄在 TTM 列是「最新毛利率 − 5 年平均」。
A12: TTM / 最新季 | C12: =IF(Stock_Card!$B$2="","",IFERROR(INDEX(Calc!$E$2:$E$100,MATCH(Stock_Card!$B$2,Calc!$A$2:$A$100,0)),"")) -> 4440492.4 | D12: =IF(Stock_Card!$B$2="","",IFERROR(INDEX(Calc!$S$2:$S$100,MATCH(Stock_Card!$B$2,Calc!$A$2:$A$100,0)),"")) -> 0.36045332 | E12: =IF(Stock_Card!$B$2="","",IFERROR(INDEX(Calc!$AA$2:$AA$100,MATCH(Stock_Card!$B$2,Calc!$A$2:$A$100,0)),"")) -> 0.64230169 | F12: =IF(Stock_Card!$B$2="","",IFERROR(INDEX(Calc!$AC$2:$AC$100,MATCH(Stock_Card!$B$2,Calc!$A$2:$A$100,0)),"")) -> 525.58123 | G12: =IF(Stock_Card!$B$2="","",IFERROR(INDEX(Calc!$F$2:$F$100,MATCH(Stock_Card!$B$2,Calc!$A$2:$A$100,0)),"")) -> 86.28 | H12: =IF(Stock_Card!$B$2="","",IFERROR(INDEX(Calc!$I$2:$I$100,MATCH(Stock_Card!$B$2,Calc!$A$2:$A$100,0)),"")) -> 0.53223229 | I12: =IF(Stock_Card!$B$2="","",IFERROR(INDEX(Calc!$AG$2:$AG$100,MATCH(Stock_Card!$B$2,Calc!$A$2:$A$100,0)),"")) -> 0.40630776 | J12: =IF(Stock_Card!$B$2="","",IFERROR(INDEX(Calc!$P$2:$P$100,MATCH(Stock_Card!$B$2,Calc!$A$2:$A$100,0)),"")) -> 22.0001 | K12: =IF(Stock_Card!$B$2="","",IFERROR(INDEX(Calc!$D$2:$D$100,MATCH(Stock_Card!$B$2,Calc!$A$2:$A$100,0)),"")) -> 2420 | L12: =IF(Stock_Card!$B$2="","",IFERROR(INDEX(Calc!$Q$2:$Q$100,MATCH(Stock_Card!$B$2,Calc!$A$2:$A$100,0)),"")) -> 0.0090909505 | M12: =IF(Stock_Card!$B$2="","",IFERROR(INDEX(Calc!$J$2:$J$100,MATCH(Stock_Card!$B$2,Calc!$A$2:$A$100,0)),"")) -> 28.048215 | N12: =IF(Stock_Card!$B$2="","",IFERROR(INDEX(Calc!$N$2:$N$100,MATCH(Stock_Card!$B$2,Calc!$A$2:$A$100,0)),"")) -> 0.52699199
A13: Forward（分析師共識） | G13: =IF(Stock_Card!$B$2="","",IFERROR(INDEX(Calc!$H$2:$H$100,MATCH(Stock_Card!$B$2,Calc!$A$2:$A$100,0)),"")) -> 140.31488 | H13: =IF(Stock_Card!$B$2="","",IFERROR(INDEX(Calc!$M$2:$M$100,MATCH(Stock_Card!$B$2,Calc!$A$2:$A$100,0)),"")) -> 0.33721659 | I13: =IF(Stock_Card!$B$2="","",IFERROR(INDEX(Calc!$AI$2:$AI$100,MATCH(Stock_Card!$B$2,Calc!$A$2:$A$100,0)),"")) -> 0.44646533 | M13: =IF(Stock_Card!$B$2="","",IFERROR(INDEX(Calc!$L$2:$L$100,MATCH(Stock_Card!$B$2,Calc!$A$2:$A$100,0)),"")) -> 17.246923 | N13: =IF(Stock_Card!$B$2="","",IFERROR(INDEX(Calc!$O$2:$O$100,MATCH(Stock_Card!$B$2,Calc!$A$2:$A$100,0)),"")) -> 0.51144944
A15: 近五年摘要
A16: 5 年平均毛利率 | C16: =IF(Stock_Card!$B$2="","",IFERROR(AVERAGE(E5:E9),"")) -> 0.56311922 | D16: 五個完整財年的算術平均
A17: 最新毛利率 − 5 年平均 (bps) | C17: =IF(Stock_Card!$B$2="","",IFERROR((E12-AVERAGE(E5:E9))*10000,"")) -> 791.82465 | D17: 正值＝目前毛利率高於五年常態
A18: 5 年平均 ROE | C18: =IF(Stock_Card!$B$2="","",IFERROR(AVERAGE(I5:I9),"")) -> 0.32270818 | D18: N/M 的年度會被自動略過
A19: 5 年平均殖利率 | C19: =IF(Stock_Card!$B$2="","",IFERROR(AVERAGE(L5:L9),"")) -> 0.017440536 | D19: 以各財年年末股價計算
A22: PE 與殖利率都用「該財年年末股價」計算，不是用今天的股價除歷史數字——後者沒有估值意義。這需要 Raw_Q 的 price_at_end 欄。
A23: PEG_T ＝ 當年 PE ÷ 當年 EPS 成長率，是「市場當時為已實現成長付了多少」；PEG_F ＝ 前瞻 PE ÷ 預估成長率，才是估值指標。兩者不要混著解讀。
A24: 年度層刻意不放加速度——加速度是季度層的訊號（這一季有沒有比上一季快），放在年度層會遲鈍到失去意義。

Sheet 季度檢視
A1: 季度檢視 · 近 12 季 + 當季預估 | Z1: =IF(Stock_Card!$B$2="","",IFERROR(SUMIFS(Raw_Q!$C$2:$C$600,Raw_Q!$A$2:$A$600,Stock_Card!$B$2,Raw_Q!$R$2:$R$600,0),"")) -> 2026
A2: 股票 | B2: =Stock_Card!$B$2 -> 2330 | C2: ← 與 Stock_Card / 年度檢視 同步。每一列＝一個財季。加速度只做在這一層。
A4: 期別 | B4: 期末日 | C4: 營收($M) | D4: 營收QoQ | E4: 上一季QoQ | F4: 加速度(pp) | G4: 動能判讀 | H4: 同期加速度(pp) | I4: 營收YoY | J4: 毛利率 | K4: ΔGM_YoY(bps) | L4: EPS(Adj) | M4: EPS YoY | N4: 每股配息 | O4: 狀態
A5: =IF(Stock_Card!$B$2="","",IFERROR(INDEX(Raw_Q!$B$2:$B$600,MATCH(Stock_Card!$B$2&"|"&12,Raw_Q!$S$2:$S$600,0)),"")) -> FY2023Q3 | B5: =IF(Stock_Card!$B$2="","",IFERROR(IF(SUMIFS(Raw_Q!$E$2:$E$600,Raw_Q!$A$2:$A$600,Stock_Card!$B$2,Raw_Q!$R$2:$R$600,12)=0,"",SUMIFS(Raw_Q!$E$2:$E$600,Raw_Q!$A$2:$A$600,Stock_Card!$B$2,Raw_Q!$R$2:$R$600,12)),"")) -> 45199 | C5: =IF(Stock_Card!$B$2="","",IFERROR(SUMIFS(Raw_Q!$I$2:$I$600,Raw_Q!$A$2:$A$600,Stock_Card!$B$2,Raw_Q!$R$2:$R$600,12),"")) -> 546732.76 | D5: =IF(Stock_Card!$B$2="","",IFERROR((SUMIFS(Raw_Q!$I$2:$I$600,Raw_Q!$A$2:$A$600,Stock_Card!$B$2,Raw_Q!$R$2:$R$600,12)/SUMIFS(Raw_Q!$I$2:$I$600,Raw_Q!$A$2:$A$600,Stock_Card!$B$2,Raw_Q!$R$2:$R$600,13)-1),"")) -> 0.1370338 | E5: =IF(Stock_Card!$B$2="","",IFERROR((SUMIFS(Raw_Q!$I$2:$I$600,Raw_Q!$A$2:$A$600,Stock_Card!$B$2,Raw_Q!$R$2:$R$600,13)/SUMIFS(Raw_Q!$I$2:$I$600,Raw_Q!$A$2:$A$600,Stock_Card!$B$2,Raw_Q!$R$2:$R$600,14)-1),"")) -> -0.054640026 | F5: =IF(Stock_Card!$B$2="","",IFERROR(((SUMIFS(Raw_Q!$I$2:$I$600,Raw_Q!$A$2:$A$600,Stock_Card!$B$2,Raw_Q!$R$2:$R$600,12)/SUMIFS(Raw_Q!$I$2:$I$600,Raw_Q!$A$2:$A$600,Stock_Card!$B$2,Raw_Q!$R$2:$R$600,13)-1)-(SUMIFS(Raw_Q!$I$2:$I$600,Raw_Q!$A$2:$A$600,Stock_Card!$B$2,Raw_Q!$R$2:$R$600,13)/SUMIFS(Raw_Q!$I$2:$I$600,Raw_Q!$A$2:$A$600,Stock_Card!$B$2,Raw_Q!$R$2:$R$600,14)-1))*100,"")) -> 19.167383 | G5: =IF(Stock_Card!$B$2="","",IFERROR(IF(NOT(ISNUMBER(D5)),"",IF(D5>0,IF(F5>0,"成長且加速","成長但減速"),IF(F5>0,"衰退但收斂","衰退且惡化"))),"")) -> 成長且加速 | H5: =IF(Stock_Card!$B$2="","",IFERROR(((SUMIFS(Raw_Q!$I$2:$I$600,Raw_Q!$A$2:$A$600,Stock_Card!$B$2,Raw_Q!$R$2:$R$600,12)/SUMIFS(Raw_Q!$I$2:$I$600,Raw_Q!$A$2:$A$600,Stock_Card!$B$2,Raw_Q!$R$2:$R$600,13)-1)-(SUMIFS(Raw_Q!$I$2:$I$600,Raw_Q!$A$2:$A$600,Stock_Card!$B$2,Raw_Q!$R$2:$R$600,16)/SUMIFS(Raw_Q!$I$2:$I$600,Raw_Q!$A$2:$A$600,Stock_Card!$B$2,Raw_Q!$R$2:$R$600,17)-1))*100,"")) -> -1.0870899 | I5: =IF(Stock_Card!$B$2="","",IFERROR((SUMIFS(Raw_Q!$I$2:$I$600,Raw_Q!$A$2:$A$600,Stock_Card!$B$2,Raw_Q!$R$2:$R$600,12)/SUMIFS(Raw_Q!$I$2:$I$600,Raw_Q!$A$2:$A$600,Stock_Card!$B$2,Raw_Q!$R$2:$R$600,16)-1),"")) -> -0.10831081 | J5: =IF(Stock_Card!$B$2="","",IFERROR(SUMIFS(Raw_Q!$J$2:$J$600,Raw_Q!$A$2:$A$600,Stock_Card!$B$2,Raw_Q!$R$2:$R$600,12)/SUMIFS(Raw_Q!$I$2:$I$600,Raw_Q!$A$2:$A$600,Stock_Card!$B$2,Raw_Q!$R$2:$R$600,12),"")) -> 0.54257306 | K5: =IF(Stock_Card!$B$2="","",IFERROR((SUMIFS(Raw_Q!$J$2:$J$600,Raw_Q!$A$2:$A$600,Stock_Card!$B$2,Raw_Q!$R$2:$R$600,12)/SUMIFS(Raw_Q!$I$2:$I$600,Raw_Q!$A$2:$A$600,Stock_Card!$B$2,Raw_Q!$R$2:$R$600,12)-SUMIFS(Raw_Q!$J$2:$J$600,Raw_Q!$A$2:$A$600,Stock_Card!$B$2,Raw_Q!$R$2:$R$600,16)/SUMIFS(Raw_Q!$I$2:$I$600,Raw_Q!$A$2:$A$600,Stock_Card!$B$2,Raw_Q!$R$2:$R$600,16))*10000,"")) -> -616.88709 | L5: =IF(Stock_Card!$B$2="","",IFERROR(SUMIFS(Raw_Q!$L$2:$L$600,Raw_Q!$A$2:$A$600,Stock_Card!$B$2,Raw_Q!$R$2:$R$600,12),"")) -> 8.14 | M5: =IF(Stock_Card!$B$2="","",IFERROR((SUMIFS(Raw_Q!$L$2:$L$600,Raw_Q!$A$2:$A$600,Stock_Card!$B$2,Raw_Q!$R$2:$R$600,12)/SUMIFS(Raw_Q!$L$2:$L$600,Raw_Q!$A$2:$A$600,Stock_Card!$B$2,Raw_Q!$R$2:$R$600,16)-1),"")) -> -0.24838412 | N5: =IF(Stock_Card!$B$2="","",IFERROR(SUMIFS(Raw_Q!$P$2:$P$600,Raw_Q!$A$2:$A$600,Stock_Card!$B$2,Raw_Q!$R$2:$R$600,12),"")) -> 3 | O5: =IF(Stock_Card!$B$2="","",IF(12=0,"預估","實際")) -> 實際
A6: =IF(Stock_Card!$B$2="","",IFERROR(INDEX(Raw_Q!$B$2:$B$600,MATCH(Stock_Card!$B$2&"|"&11,Raw_Q!$S$2:$S$600,0)),"")) -> FY2023Q4 | B6: =IF(Stock_Card!$B$2="","",IFERROR(IF(SUMIFS(Raw_Q!$E$2:$E$600,Raw_Q!$A$2:$A$600,Stock_Card!$B$2,Raw_Q!$R$2:$R$600,11)=0,"",SUMIFS(Raw_Q!$E$2:$E$600,Raw_Q!$A$2:$A$600,Stock_Card!$B$2,Raw_Q!$R$2:$R$600,11)),"")) -> 45291 | C6: =IF(Stock_Card!$B$2="","",IFERROR(SUMIFS(Raw_Q!$I$2:$I$600,Raw_Q!$A$2:$A$600,Stock_Card!$B$2,Raw_Q!$R$2:$R$600,11),"")) -> 625528.86 | D6: =IF(Stock_Card!$B$2="","",IFERROR((SUMIFS(Raw_Q!$I$2:$I$600,Raw_Q!$A$2:$A$600,Stock_Card!$B$2,Raw_Q!$R$2:$R$600,11)/SUMIFS(Raw_Q!$I$2:$I$600,Raw_Q!$A$2:$A$600,Stock_Card!$B$2,Raw_Q!$R$2:$R$600,12)-1),"")) -> 0.14412178 | E6: =IF(Stock_Card!$B$2="","",IFERROR((SUMIFS(Raw_Q!$I$2:$I$600,Raw_Q!$A$2:$A$600,Stock_Card!$B$2,Raw_Q!$R$2:$R$600,12)/SUMIFS(Raw_Q!$I$2:$I$600,Raw_Q!$A$2:$A$600,Stock_Card!$B$2,Raw_Q!$R$2:$R$600,13)-1),"")) -> 0.1370338 | F6: =IF(Stock_Card!$B$2="","",IFERROR(((SUMIFS(Raw_Q!$I$2:$I$600,Raw_Q!$A$2:$A$600,Stock_Card!$B$2,Raw_Q!$R$2:$R$600,11)/SUMIFS(Raw_Q!$I$2:$I$600,Raw_Q!$A$2:$A$600,Stock_Card!$B$2,Raw_Q!$R$2:$R$600,12)-1)-(SUMIFS(Raw_Q!$I$2:$I$600,Raw_Q!$A$2:$A$600,Stock_Card!$B$2,Raw_Q!$R$2:$R$600,12)/SUMIFS(Raw_Q!$I$2:$I$600,Raw_Q!$A$2:$A$600,Stock_Card!$B$2,Raw_Q!$R$2:$R$600,13)-1))*100,"")) -> 0.708798 | G6: =IF(Stock_Card!$B$2="","",IFERROR(IF(NOT(ISNUMBER(D6)),"",IF(D6>0,IF(F6>0,"成長且加速","成長但減速"),IF(F6>0,"衰退但收斂","衰退且惡化"))),"")) -> 成長且加速 | H6: =IF(Stock_Card!$B$2="","",IFERROR(((SUMIFS(Raw_Q!$I$2:$I$600,Raw_Q!$A$2:$A$600,Stock_Card!$B$2,Raw_Q!$R$2:$R$600,11)/SUMIFS(Raw_Q!$I$2:$I$600,Raw_Q!$A$2:$A$600,Stock_Card!$B$2,Raw_Q!$R$2:$R$600,12)-1)-(SUMIFS(Raw_Q!$I$2:$I$600,Raw_Q!$A$2:$A$600,Stock_Card!$B$2,Raw_Q!$R$2:$R$600,15)/SUMIFS(Raw_Q!$I$2:$I$600,Raw_Q!$A$2:$A$600,Stock_Card!$B$2,Raw_Q!$R$2:$R$600,16)-1))*100,"")) -> 12.391584 | I6: =IF(Stock_Card!$B$2="","",IFERROR((SUMIFS(Raw_Q!$I$2:$I$600,Raw_Q!$A$2:$A$600,Stock_Card!$B$2,Raw_Q!$R$2:$R$600,11)/SUMIFS(Raw_Q!$I$2:$I$600,Raw_Q!$A$2:$A$600,Stock_Card!$B$2,Raw_Q!$R$2:$R$600,15)-1),"")) -> -4.8151024e-06 | J6: =IF(Stock_Card!$B$2="","",IFERROR(SUMIFS(Raw_Q!$J$2:$J$600,Raw_Q!$A$2:$A$600,Stock_Card!$B$2,Raw_Q!$R$2:$R$600,11)/SUMIFS(Raw_Q!$I$2:$I$600,Raw_Q!$A$2:$A$600,Stock_Card!$B$2,Raw_Q!$R$2:$R$600,11),"")) -> 0.53037989 | K6: =IF(Stock_Card!$B$2="","",IFERROR((SUMIFS(Raw_Q!$J$2:$J$600,Raw_Q!$A$2:$A$600,Stock_Card!$B$2,Raw_Q!$R$2:$R$600,11)/SUMIFS(Raw_Q!$I$2:$I$600,Raw_Q!$A$2:$A$600,Stock_Card!$B$2,Raw_Q!$R$2:$R$600,11)-SUMIFS(Raw_Q!$J$2:$J$600,Raw_Q!$A$2:$A$600,Stock_Card!$B$2,Raw_Q!$R$2:$R$600,15)/SUMIFS(Raw_Q!$I$2:$I$600,Raw_Q!$A$2:$A$600,Stock_Card!$B$2,Raw_Q!$R$2:$R$600,15))*10000,"")) -> -917.86541 | L6: =IF(Stock_Card!$B$2="","",IFERROR(SUMIFS(Raw_Q!$L$2:$L$600,Raw_Q!$A$2:$A$600,Stock_Card!$B$2,Raw_Q!$R$2:$R$600,11),"")) -> 9.21 | M6: =IF(Stock_Card!$B$2="","",IFERROR((SUMIFS(Raw_Q!$L$2:$L$600,Raw_Q!$A$2:$A$600,Stock_Card!$B$2,Raw_Q!$R$2:$R$600,11)/SUMIFS(Raw_Q!$L$2:$L$600,Raw_Q!$A$2:$A$600,Stock_Card!$B$2,Raw_Q!$R$2:$R$600,15)-1),"")) -> -0.19281332 | N6: =IF(Stock_Card!$B$2="","",IFERROR(SUMIFS(Raw_Q!$P$2:$P$600,Raw_Q!$A$2:$A$600,Stock_Card!$B$2,Raw_Q!$R$2:$R$600,11),"")) -> 3 | O6: =IF(Stock_Card!$B$2="","",IF(11=0,"預估","實際")) -> 實際
A7: =IF(Stock_Card!$B$2="","",IFERROR(INDEX(Raw_Q!$B$2:$B$600,MATCH(Stock_Card!$B$2&"|"&10,Raw_Q!$S$2:$S$600,0)),"")) -> FY2024Q1 | B7: =IF(Stock_Card!$B$2="","",IFERROR(IF(SUMIFS(Raw_Q!$E$2:$E$600,Raw_Q!$A$2:$A$600,Stock_Card!$B$2,Raw_Q!$R$2:$R$600,10)=0,"",SUMIFS(Raw_Q!$E$2:$E$600,Raw_Q!$A$2:$A$600,Stock_Card!$B$2,Raw_Q!$R$2:$R$600,10)),"")) -> 45382 | C7: =IF(Stock_Card!$B$2="","",IFERROR(SUMIFS(Raw_Q!$I$2:$I$600,Raw_Q!$A$2:$A$600,Stock_Card!$B$2,Raw_Q!$R$2:$R$600,10),"")) -> 592644.2 | D7: =IF(Stock_Card!$B$2="","",IFERROR((SUMIFS(Raw_Q!$I$2:$I$600,Raw_Q!$A$2:$A$600,Stock_Card!$B$2,Raw_Q!$R$2:$R$600,10)/SUMIFS(Raw_Q!$I$2:$I$600,Raw_Q!$A$2:$A$600,Stock_Card!$B$2,Raw_Q!$R$2:$R$600,11)-1),"")) -> -0.052570964 | E7: =IF(Stock_Card!$B$2="","",IFERROR((SUMIFS(Raw_Q!$I$2:$I$600,Raw_Q!$A$2:$A$600,Stock_Card!$B$2,Raw_Q!$R$2:$R$600,11)/SUMIFS(Raw_Q!$I$2:$I$600,Raw_Q!$A$2:$A$600,Stock_Card!$B$2,Raw_Q!$R$2:$R$600,12)-1),"")) -> 0.14412178 | F7: =IF(Stock_Card!$B$2="","",IFERROR(((SUMIFS(Raw_Q!$I$2:$I$600,Raw_Q!$A$2:$A$600,Stock_Card!$B$2,Raw_Q!$R$2:$R$600,10)/SUMIFS(Raw_Q!$I$2:$I$600,Raw_Q!$A$2:$A$600,Stock_Card!$B$2,Raw_Q!$R$2:$R$600,11)-1)-(SUMIFS(Raw_Q!$I$2:$I$600,Raw_Q!$A$2:$A$600,Stock_Card!$B$2,Raw_Q!$R$2:$R$600,11)/SUMIFS(Raw_Q!$I$2:$I$600,Raw_Q!$A$2:$A$600,Stock_Card!$B$2,Raw_Q!$R$2:$R$600,12)-1))*100,"")) -> -19.669274 | G7: =IF(Stock_Card!$B$2="","",IFERROR(IF(NOT(ISNUMBER(D7)),"",IF(D7>0,IF(F7>0,"成長且加速","成長但減速"),IF(F7>0,"衰退但收斂","衰退且惡化"))),"")) -> 衰退且惡化 | H7: =IF(Stock_Card!$B$2="","",IFERROR(((SUMIFS(Raw_Q!$I$2:$I$600,Raw_Q!$A$2:$A$600,Stock_Card!$B$2,Raw_Q!$R$2:$R$600,10)/SUMIFS(Raw_Q!$I$2:$I$600,Raw_Q!$A$2:$A$600,Stock_Card!$B$2,Raw_Q!$R$2:$R$600,11)-1)-(SUMIFS(Raw_Q!$I$2:$I$600,Raw_Q!$A$2:$A$600,Stock_Card!$B$2,Raw_Q!$R$2:$R$600,14)/SUMIFS(Raw_Q!$I$2:$I$600,Raw_Q!$A$2:$A$600,Stock_Card!$B$2,Raw_Q!$R$2:$R$600,15)-1))*100,"")) -> 13.430824 | I7: =IF(Stock_Card!$B$2="","",IFERROR((SUMIFS(Raw_Q!$I$2:$I$600,Raw_Q!$A$2:$A$600,Stock_Card!$B$2,Raw_Q!$R$2:$R$600,10)/SUMIFS(Raw_Q!$I$2:$I$600,Raw_Q!$A$2:$A$600,Stock_Card!$B$2,Raw_Q!$R$2:$R$600,14)-1),"")) -> 0.16517063 | J7: =IF(Stock_Card!$B$2="","",IFERROR(SUMIFS(Raw_Q!$J$2:$J$600,Raw_Q!$A$2:$A$600,Stock_Card!$B$2,Raw_Q!$R$2:$R$600,10)/SUMIFS(Raw_Q!$I$2:$I$600,Raw_Q!$A$2:$A$600,Stock_Card!$B$2,Raw_Q!$R$2:$R$600,10),"")) -> 0.53068142 | K7: =IF(Stock_Card!$B$2="","",IFERROR((SUMIFS(Raw_Q!$J$2:$J$600,Raw_Q!$A$2:$A$600,Stock_Card!$B$2,Raw_Q!$R$2:$R$600,10)/SUMIFS(Raw_Q!$I$2:$I$600,Raw_Q!$A$2:$A$600,Stock_Card!$B$2,Raw_Q!$R$2:$R$600,10)-SUMIFS(Raw_Q!$J$2:$J$600,Raw_Q!$A$2:$A$600,Stock_Card!$B$2,Raw_Q!$R$2:$R$600,14)/SUMIFS(Raw_Q!$I$2:$I$600,Raw_Q!$A$2:$A$600,Stock_Card!$B$2,Raw_Q!$R$2:$R$600,14))*10000,"")) -> -325.93878 | L7: =IF(Stock_Card!$B$2="","",IFERROR(SUMIFS(Raw_Q!$L$2:$L$600,Raw_Q!$A$2:$A$600,Stock_Card!$B$2,Raw_Q!$R$2:$R$600,10),"")) -> 8.7 | M7: =IF(Stock_Card!$B$2="","",IFERROR((SUMIFS(Raw_Q!$L$2:$L$600,Raw_Q!$A$2:$A$600,Stock_Card!$B$2,Raw_Q!$R$2:$R$600,10)/SUMIFS(Raw_Q!$L$2:$L$600,Raw_Q!$A$2:$A$600,Stock_Card!$B$2,Raw_Q!$R$2:$R$600,14)-1),"")) -> 0.090225564 | N7: =IF(Stock_Card!$B$2="","",IFERROR(SUMIFS(Raw_Q!$P$2:$P$600,Raw_Q!$A$2:$A$600,Stock_Card!$B$2,Raw_Q!$R$2:$R$600,10),"")) -> 3.4997897 | O7: =IF(Stock_Card!$B$2="","",IF(10=0,"預估","實際")) -> 實際
A8: =IF(Stock_Card!$B$2="","",IFERROR(INDEX(Raw_Q!$B$2:$B$600,MATCH(Stock_Card!$B$2&"|"&9,Raw_Q!$S$2:$S$600,0)),"")) -> FY2024Q2 | B8: =IF(Stock_Card!$B$2="","",IFERROR(IF(SUMIFS(Raw_Q!$E$2:$E$600,Raw_Q!$A$2:$A$600,Stock_Card!$B$2,Raw_Q!$R$2:$R$600,9)=0,"",SUMIFS(Raw_Q!$E$2:$E$600,Raw_Q!$A$2:$A$600,Stock_Card!$B$2,Raw_Q!$R$2:$R$600,9)),"")) -> 45473 | C8: =IF(Stock_Card!$B$2="","",IFERROR(SUMIFS(Raw_Q!$I$2:$I$600,Raw_Q!$A$2:$A$600,Stock_Card!$B$2,Raw_Q!$R$2:$R$600,9),"")) -> 673510.18 | D8: =IF(Stock_Card!$B$2="","",IFERROR((SUMIFS(Raw_Q!$I$2:$I$600,Raw_Q!$A$2:$A$600,Stock_Card!$B$2,Raw_Q!$R$2:$R$600,9)/SUMIFS(Raw_Q!$I$2:$I$600,Raw_Q!$A$2:$A$600,Stock_Card!$B$2,Raw_Q!$R$2:$R$600,10)-1),"")) -> 0.13644945 | E8: =IF(Stock_Card!$B$2="","",IFERROR((SUMIFS(Raw_Q!$I$2:$I$600,Raw_Q!$A$2:$A$600,Stock_Card!$B$2,Raw_Q!$R$2:$R$600,10)/SUMIFS(Raw_Q!$I$2:$I$600,Raw_Q!$A$2:$A$600,Stock_Card!$B$2,Raw_Q!$R$2:$R$600,11)-1),"")) -> -0.052570964 | F8: =IF(Stock_Card!$B$2="","",IFERROR(((SUMIFS(Raw_Q!$I$2:$I$600,Raw_Q!$A$2:$A$600,Stock_Card!$B$2,Raw_Q!$R$2:$R$600,9)/SUMIFS(Raw_Q!$I$2:$I$600,Raw_Q!$A$2:$A$600,Stock_Card!$B$2,Raw_Q!$R$2:$R$600,10)-1)-(SUMIFS(Raw_Q!$I$2:$I$600,Raw_Q!$A$2:$A$600,Stock_Card!$B$2,Raw_Q!$R$2:$R$600,10)/SUMIFS(Raw_Q!$I$2:$I$600,Raw_Q!$A$2:$A$600,Stock_Card!$B$2,Raw_Q!$R$2:$R$600,11)-1))*100,"")) -> 18.902042 | G8: =IF(Stock_Card!$B$2="","",IFERROR(IF(NOT(ISNUMBER(D8)),"",IF(D8>0,IF(F8>0,"成長且加速","成長但減速"),IF(F8>0,"衰退但收斂","衰退且惡化"))),"")) -> 成長且加速 | H8: =IF(Stock_Card!$B$2="","",IFERROR(((SUMIFS(Raw_Q!$I$2:$I$600,Raw_Q!$A$2:$A$600,Stock_Card!$B$2,Raw_Q!$R$2:$R$600,9)/SUMIFS(Raw_Q!$I$2:$I$600,Raw_Q!$A$2:$A$600,Stock_Card!$B$2,Raw_Q!$R$2:$R$600,10)-1)-(SUMIFS(Raw_Q!$I$2:$I$600,Raw_Q!$A$2:$A$600,Stock_Card!$B$2,Raw_Q!$R$2:$R$600,13)/SUMIFS(Raw_Q!$I$2:$I$600,Raw_Q!$A$2:$A$600,Stock_Card!$B$2,Raw_Q!$R$2:$R$600,14)-1))*100,"")) -> 19.108948 | I8: =IF(Stock_Card!$B$2="","",IFERROR((SUMIFS(Raw_Q!$I$2:$I$600,Raw_Q!$A$2:$A$600,Stock_Card!$B$2,Raw_Q!$R$2:$R$600,9)/SUMIFS(Raw_Q!$I$2:$I$600,Raw_Q!$A$2:$A$600,Stock_Card!$B$2,Raw_Q!$R$2:$R$600,13)-1),"")) -> 0.40069133 | J8: =IF(Stock_Card!$B$2="","",IFERROR(SUMIFS(Raw_Q!$J$2:$J$600,Raw_Q!$A$2:$A$600,Stock_Card!$B$2,Raw_Q!$R$2:$R$600,9)/SUMIFS(Raw_Q!$I$2:$I$600,Raw_Q!$A$2:$A$600,Stock_Card!$B$2,Raw_Q!$R$2:$R$600,9),"")) -> 0.53172838 | K8: =IF(Stock_Card!$B$2="","",IFERROR((SUMIFS(Raw_Q!$J$2:$J$600,Raw_Q!$A$2:$A$600,Stock_Card!$B$2,Raw_Q!$R$2:$R$600,9)/SUMIFS(Raw_Q!$I$2:$I$600,Raw_Q!$A$2:$A$600,Stock_Card!$B$2,Raw_Q!$R$2:$R$600,9)-SUMIFS(Raw_Q!$J$2:$J$600,Raw_Q!$A$2:$A$600,Stock_Card!$B$2,Raw_Q!$R$2:$R$600,13)/SUMIFS(Raw_Q!$I$2:$I$600,Raw_Q!$A$2:$A$600,Stock_Card!$B$2,Raw_Q!$R$2:$R$600,13))*10000,"")) -> -94.062313 | L8: =IF(Stock_Card!$B$2="","",IFERROR(SUMIFS(Raw_Q!$L$2:$L$600,Raw_Q!$A$2:$A$600,Stock_Card!$B$2,Raw_Q!$R$2:$R$600,9),"")) -> 9.56 | M8: =IF(Stock_Card!$B$2="","",IFERROR((SUMIFS(Raw_Q!$L$2:$L$600,Raw_Q!$A$2:$A$600,Stock_Card!$B$2,Raw_Q!$R$2:$R$600,9)/SUMIFS(Raw_Q!$L$2:$L$600,Raw_Q!$A$2:$A$600,Stock_Card!$B$2,Raw_Q!$R$2:$R$600,13)-1),"")) -> 0.36376605 | N8: =IF(Stock_Card!$B$2="","",IFERROR(SUMIFS(Raw_Q!$P$2:$P$600,Raw_Q!$A$2:$A$600,Stock_Card!$B$2,Raw_Q!$R$2:$R$600,9),"")) -> 3.4997897 | O8: =IF(Stock_Card!$B$2="","",IF(9=0,"預估","實際")) -> 實際
A9: =IF(Stock_Card!$B$2="","",IFERROR(INDEX(Raw_Q!$B$2:$B$600,MATCH(Stock_Card!$B$2&"|"&8,Raw_Q!$S$2:$S$600,0)),"")) -> FY2024Q3 | B9: =IF(Stock_Card!$B$2="","",IFERROR(IF(SUMIFS(Raw_Q!$E$2:$E$600,Raw_Q!$A$2:$A$600,Stock_Card!$B$2,Raw_Q!$R$2:$R$600,8)=0,"",SUMIFS(Raw_Q!$E$2:$E$600,Raw_Q!$A$2:$A$600,Stock_Card!$B$2,Raw_Q!$R$2:$R$600,8)),"")) -> 45565 | C9: =IF(Stock_Card!$B$2="","",IFERROR(SUMIFS(Raw_Q!$I$2:$I$600,Raw_Q!$A$2:$A$600,Stock_Card!$B$2,Raw_Q!$R$2:$R$600,8),"")) -> 759692.14 | D9: =IF(Stock_Card!$B$2="","",IFERROR((SUMIFS(Raw_Q!$I$2:$I$600,Raw_Q!$A$2:$A$600,Stock_Card!$B$2,Raw_Q!$R$2:$R$600,8)/SUMIFS(Raw_Q!$I$2:$I$600,Raw_Q!$A$2:$A$600,Stock_Card!$B$2,Raw_Q!$R$2:$R$600,9)-1),"")) -> 0.12795941 | E9: =IF(Stock_Card!$B$2="","",IFERROR((SUMIFS(Raw_Q!$I$2:$I$600,Raw_Q!$A$2:$A$600,Stock_Card!$B$2,Raw_Q!$R$2:$R$600,9)/SUMIFS(Raw_Q!$I$2:$I$600,Raw_Q!$A$2:$A$600,Stock_Card!$B$2,Raw_Q!$R$2:$R$600,10)-1),"")) -> 0.13644945 | F9: =IF(Stock_Card!$B$2="","",IFERROR(((SUMIFS(Raw_Q!$I$2:$I$600,Raw_Q!$A$2:$A$600,Stock_Card!$B$2,Raw_Q!$R$2:$R$600,8)/SUMIFS(Raw_Q!$I$2:$I$600,Raw_Q!$A$2:$A$600,Stock_Card!$B$2,Raw_Q!$R$2:$R$600,9)-1)-(SUMIFS(Raw_Q!$I$2:$I$600,Raw_Q!$A$2:$A$600,Stock_Card!$B$2,Raw_Q!$R$2:$R$600,9)/SUMIFS(Raw_Q!$I$2:$I$600,Raw_Q!$A$2:$A$600,Stock_Card!$B$2,Raw_Q!$R$2:$R$600,10)-1))*100,"")) -> -0.84900396 | G9: =IF(Stock_Card!$B$2="","",IFERROR(IF(NOT(ISNUMBER(D9)),"",IF(D9>0,IF(F9>0,"成長且加速","成長但減速"),IF(F9>0,"衰退但收斂","衰退且惡化"))),"")) -> 成長但減速 | H9: =IF(Stock_Card!$B$2="","",IFERROR(((SUMIFS(Raw_Q!$I$2:$I$600,Raw_Q!$A$2:$A$600,Stock_Card!$B$2,Raw_Q!$R$2:$R$600,8)/SUMIFS(Raw_Q!$I$2:$I$600,Raw_Q!$A$2:$A$600,Stock_Card!$B$2,Raw_Q!$R$2:$R$600,9)-1)-(SUMIFS(Raw_Q!$I$2:$I$600,Raw_Q!$A$2:$A$600,Stock_Card!$B$2,Raw_Q!$R$2:$R$600,12)/SUMIFS(Raw_Q!$I$2:$I$600,Raw_Q!$A$2:$A$600,Stock_Card!$B$2,Raw_Q!$R$2:$R$600,13)-1))*100,"")) -> -0.90743879 | I9: =IF(Stock_Card!$B$2="","",IFERROR((SUMIFS(Raw_Q!$I$2:$I$600,Raw_Q!$A$2:$A$600,Stock_Card!$B$2,Raw_Q!$R$2:$R$600,8)/SUMIFS(Raw_Q!$I$2:$I$600,Raw_Q!$A$2:$A$600,Stock_Card!$B$2,Raw_Q!$R$2:$R$600,12)-1),"")) -> 0.38951276 | J9: =IF(Stock_Card!$B$2="","",IFERROR(SUMIFS(Raw_Q!$J$2:$J$600,Raw_Q!$A$2:$A$600,Stock_Card!$B$2,Raw_Q!$R$2:$R$600,8)/SUMIFS(Raw_Q!$I$2:$I$600,Raw_Q!$A$2:$A$600,Stock_Card!$B$2,Raw_Q!$R$2:$R$600,8),"")) -> 0.57832067 | K9: =IF(Stock_Card!$B$2="","",IFERROR((SUMIFS(Raw_Q!$J$2:$J$600,Raw_Q!$A$2:$A$600,Stock_Card!$B$2,Raw_Q!$R$2:$R$600,8)/SUMIFS(Raw_Q!$I$2:$I$600,Raw_Q!$A$2:$A$600,Stock_Card!$B$2,Raw_Q!$R$2:$R$600,8)-SUMIFS(Raw_Q!$J$2:$J$600,Raw_Q!$A$2:$A$600,Stock_Card!$B$2,Raw_Q!$R$2:$R$600,12)/SUMIFS(Raw_Q!$I$2:$I$600,Raw_Q!$A$2:$A$600,Stock_Card!$B$2,Raw_Q!$R$2:$R$600,12))*10000,"")) -> 357.47609 | L9: =IF(Stock_Card!$B$2="","",IFERROR(SUMIFS(Raw_Q!$L$2:$L$600,Raw_Q!$A$2:$A$600,Stock_Card!$B$2,Raw_Q!$R$2:$R$600,8),"")) -> 12.55 | M9: =IF(Stock_Card!$B$2="","",IFERROR((SUMIFS(Raw_Q!$L$2:$L$600,Raw_Q!$A$2:$A$600,Stock_Card!$B$2,Raw_Q!$R$2:$R$600,8)/SUMIFS(Raw_Q!$L$2:$L$600,Raw_Q!$A$2:$A$600,Stock_Card!$B$2,Raw_Q!$R$2:$R$600,12)-1),"")) -> 0.54176904 | N9: =IF(Stock_Card!$B$2="","",IFERROR(SUMIFS(Raw_Q!$P$2:$P$600,Raw_Q!$A$2:$A$600,Stock_Card!$B$2,Raw_Q!$R$2:$R$600,8),"")) -> 4.0001382 | O9: =IF(Stock_Card!$B$2="","",IF(8=0,"預估","實際")) -> 實際
A10: =IF(Stock_Card!$B$2="","",IFERROR(INDEX(Raw_Q!$B$2:$B$600,MATCH(Stock_Card!$B$2&"|"&7,Raw_Q!$S$2:$S$600,0)),"")) -> FY2024Q4 | B10: =IF(Stock_Card!$B$2="","",IFERROR(IF(SUMIFS(Raw_Q!$E$2:$E$600,Raw_Q!$A$2:$A$600,Stock_Card!$B$2,Raw_Q!$R$2:$R$600,7)=0,"",SUMIFS(Raw_Q!$E$2:$E$600,Raw_Q!$A$2:$A$600,Stock_Card!$B$2,Raw_Q!$R$2:$R$600,7)),"")) -> 45657 | C10: =IF(Stock_Card!$B$2="","",IFERROR(SUMIFS(Raw_Q!$I$2:$I$600,Raw_Q!$A$2:$A$600,Stock_Card!$B$2,Raw_Q!$R$2:$R$600,7),"")) -> 868461.18 | D10: =IF(Stock_Card!$B$2="","",IFERROR((SUMIFS(Raw_Q!$I$2:$I$600,Raw_Q!$A$2:$A$600,Stock_Card!$B$2,Raw_Q!$R$2:$R$600,7)/SUMIFS(Raw_Q!$I$2:$I$600,Raw_Q!$A$2:$A$600,Stock_Card!$B$2,Raw_Q!$R$2:$R$600,8)-1),"")) -> 0.14317515 | E10: =IF(Stock_Card!$B$2="","",IFERROR((SUMIFS(Raw_Q!$I$2:$I$600,Raw_Q!$A$2:$A$600,Stock_Card!$B$2,Raw_Q!$R$2:$R$600,8)/SUMIFS(Raw_Q!$I$2:$I$600,Raw_Q!$A$2:$A$600,Stock_Card!$B$2,Raw_Q!$R$2:$R$600,9)-1),"")) -> 0.12795941 | F10: =IF(Stock_Card!$B$2="","",IFERROR(((SUMIFS(Raw_Q!$I$2:$I$600,Raw_Q!$A$2:$A$600,Stock_Card!$B$2,Raw_Q!$R$2:$R$600,7)/SUMIFS(Raw_Q!$I$2:$I$600,Raw_Q!$A$2:$A$600,Stock_Card!$B$2,Raw_Q!$R$2:$R$600,8)-1)-(SUMIFS(Raw_Q!$I$2:$I$600,Raw_Q!$A$2:$A$600,Stock_Card!$B$2,Raw_Q!$R$2:$R$600,8)/SUMIFS(Raw_Q!$I$2:$I$600,Raw_Q!$A$2:$A$600,Stock_Card!$B$2,Raw_Q!$R$2:$R$600,9)-1))*100,"")) -> 1.5215736 | G10: =IF(Stock_Card!$B$2="","",IFERROR(IF(NOT(ISNUMBER(D10)),"",IF(D10>0,IF(F10>0,"成長且加速","成長但減速"),IF(F10>0,"衰退但收斂","衰退且惡化"))),"")) -> 成長且加速 | H10: =IF(Stock_Card!$B$2="","",IFERROR(((SUMIFS(Raw_Q!$I$2:$I$600,Raw_Q!$A$2:$A$600,Stock_Card!$B$2,Raw_Q!$R$2:$R$600,7)/SUMIFS(Raw_Q!$I$2:$I$600,Raw_Q!$A$2:$A$600,Stock_Card!$B$2,Raw_Q!$R$2:$R$600,8)-1)-(SUMIFS(Raw_Q!$I$2:$I$600,Raw_Q!$A$2:$A$600,Stock_Card!$B$2,Raw_Q!$R$2:$R$600,11)/SUMIFS(Raw_Q!$I$2:$I$600,Raw_Q!$A$2:$A$600,Stock_Card!$B$2,Raw_Q!$R$2:$R$600,12)-1))*100,"")) -> -0.094663152 | I10: =IF(Stock_Card!$B$2="","",IFERROR((SUMIFS(Raw_Q!$I$2:$I$600,Raw_Q!$A$2:$A$600,Stock_Card!$B$2,Raw_Q!$R$2:$R$600,7)/SUMIFS(Raw_Q!$I$2:$I$600,Raw_Q!$A$2:$A$600,Stock_Card!$B$2,Raw_Q!$R$2:$R$600,11)-1),"")) -> 0.38836309 | J10: =IF(Stock_Card!$B$2="","",IFERROR(SUMIFS(Raw_Q!$J$2:$J$600,Raw_Q!$A$2:$A$600,Stock_Card!$B$2,Raw_Q!$R$2:$R$600,7)/SUMIFS(Raw_Q!$I$2:$I$600,Raw_Q!$A$2:$A$600,Stock_Card!$B$2,Raw_Q!$R$2:$R$600,7),"")) -> 0.58998394 | K10: =IF(Stock_Card!$B$2="","",IFERROR((SUMIFS(Raw_Q!$J$2:$J$600,Raw_Q!$A$2:$A$600,Stock_Card!$B$2,Raw_Q!$R$2:$R$600,7)/SUMIFS(Raw_Q!$I$2:$I$600,Raw_Q!$A$2:$A$600,Stock_Card!$B$2,Raw_Q!$R$2:$R$600,7)-SUMIFS(Raw_Q!$J$2:$J$600,Raw_Q!$A$2:$A$600,Stock_Card!$B$2,Raw_Q!$R$2:$R$600,11)/SUMIFS(Raw_Q!$I$2:$I$600,Raw_Q!$A$2:$A$600,Stock_Card!$B$2,Raw_Q!$R$2:$R$600,11))*10000,"")) -> 596.04055 | L10: =IF(Stock_Card!$B$2="","",IFERROR(SUMIFS(Raw_Q!$L$2:$L$600,Raw_Q!$A$2:$A$600,Stock_Card!$B$2,Raw_Q!$R$2:$R$600,7),"")) -> 14.45 | M10: =IF(Stock_Card!$B$2="","",IFERROR((SUMIFS(Raw_Q!$L$2:$L$600,Raw_Q!$A$2:$A$600,Stock_Card!$B$2,Raw_Q!$R$2:$R$600,7)/SUMIFS(Raw_Q!$L$2:$L$600,Raw_Q!$A$2:$A$600,Stock_Card!$B$2,Raw_Q!$R$2:$R$600,11)-1),"")) -> 0.5689468 | N10: =IF(Stock_Card!$B$2="","",IFERROR(SUMIFS(Raw_Q!$P$2:$P$600,Raw_Q!$A$2:$A$600,Stock_Card!$B$2,Raw_Q!$R$2:$R$600,7),"")) -> 3.9996371 | O10: =IF(Stock_Card!$B$2="","",IF(7=0,"預估","實際")) -> 實際
A11: =IF(Stock_Card!$B$2="","",IFERROR(INDEX(Raw_Q!$B$2:$B$600,MATCH(Stock_Card!$B$2&"|"&6,Raw_Q!$S$2:$S$600,0)),"")) -> FY2025Q1 | B11: =IF(Stock_Card!$B$2="","",IFERROR(IF(SUMIFS(Raw_Q!$E$2:$E$600,Raw_Q!$A$2:$A$600,Stock_Card!$B$2,Raw_Q!$R$2:$R$600,6)=0,"",SUMIFS(Raw_Q!$E$2:$E$600,Raw_Q!$A$2:$A$600,Stock_Card!$B$2,Raw_Q!$R$2:$R$600,6)),"")) -> 45747 | C11: =IF(Stock_Card!$B$2="","",IFERROR(SUMIFS(Raw_Q!$I$2:$I$600,Raw_Q!$A$2:$A$600,Stock_Card!$B$2,Raw_Q!$R$2:$R$600,6),"")) -> 839253.66 | D11: =IF(Stock_Card!$B$2="","",IFERROR((SUMIFS(Raw_Q!$I$2:$I$600,Raw_Q!$A$2:$A$600,Stock_Card!$B$2,Raw_Q!$R$2:$R$600,6)/SUMIFS(Raw_Q!$I$2:$I$600,Raw_Q!$A$2:$A$600,Stock_Card!$B$2,Raw_Q!$R$2:$R$600,7)-1),"")) -> -0.033631341 | E11: =IF(Stock_Card!$B$2="","",IFERROR((SUMIFS(Raw_Q!$I$2:$I$600,Raw_Q!$A$2:$A$600,Stock_Card!$B$2,Raw_Q!$R$2:$R$600,7)/SUMIFS(Raw_Q!$I$2:$I$600,Raw_Q!$A$2:$A$600,Stock_Card!$B$2,Raw_Q!$R$2:$R$600,8)-1),"")) -> 0.14317515 | F11: =IF(Stock_Card!$B$2="","",IFERROR(((SUMIFS(Raw_Q!$I$2:$I$600,Raw_Q!$A$2:$A$600,Stock_Card!$B$2,Raw_Q!$R$2:$R$600,6)/SUMIFS(Raw_Q!$I$2:$I$600,Raw_Q!$A$2:$A$600,Stock_Card!$B$2,Raw_Q!$R$2:$R$600,7)-1)-(SUMIFS(Raw_Q!$I$2:$I$600,Raw_Q!$A$2:$A$600,Stock_Card!$B$2,Raw_Q!$R$2:$R$600,7)/SUMIFS(Raw_Q!$I$2:$I$600,Raw_Q!$A$2:$A$600,Stock_Card!$B$2,Raw_Q!$R$2:$R$600,8)-1))*100,"")) -> -17.680649 | G11: =IF(Stock_Card!$B$2="","",IFERROR(IF(NOT(ISNUMBER(D11)),"",IF(D11>0,IF(F11>0,"成長且加速","成長但減速"),IF(F11>0,"衰退但收斂","衰退且惡化"))),"")) -> 衰退且惡化 | H11: =IF(Stock_Card!$B$2="","",IFERROR(((SUMIFS(Raw_Q!$I$2:$I$600,Raw_Q!$A$2:$A$600,Stock_Card!$B$2,Raw_Q!$R$2:$R$600,6)/SUMIFS(Raw_Q!$I$2:$I$600,Raw_Q!$A$2:$A$600,Stock_Card!$B$2,Raw_Q!$R$2:$R$600,7)-1)-(SUMIFS(Raw_Q!$I$2:$I$600,Raw_Q!$A$2:$A$600,Stock_Card!$B$2,Raw_Q!$R$2:$R$600,10)/SUMIFS(Raw_Q!$I$2:$I$600,Raw_Q!$A$2:$A$600,Stock_Card!$B$2,Raw_Q!$R$2:$R$600,11)-1))*100,"")) -> 1.8939623 | I11: =IF(Stock_Card!$B$2="","",IFERROR((SUMIFS(Raw_Q!$I$2:$I$600,Raw_Q!$A$2:$A$600,Stock_Card!$B$2,Raw_Q!$R$2:$R$600,6)/SUMIFS(Raw_Q!$I$2:$I$600,Raw_Q!$A$2:$A$600,Stock_Card!$B$2,Raw_Q!$R$2:$R$600,10)-1),"")) -> 0.41611723 | J11: =IF(Stock_Card!$B$2="","",IFERROR(SUMIFS(Raw_Q!$J$2:$J$600,Raw_Q!$A$2:$A$600,Stock_Card!$B$2,Raw_Q!$R$2:$R$600,6)/SUMIFS(Raw_Q!$I$2:$I$600,Raw_Q!$A$2:$A$600,Stock_Card!$B$2,Raw_Q!$R$2:$R$600,6),"")) -> 0.58789743 | K11: =IF(Stock_Card!$B$2="","",IFERROR((SUMIFS(Raw_Q!$J$2:$J$600,Raw_Q!$A$2:$A$600,Stock_Card!$B$2,Raw_Q!$R$2:$R$600,6)/SUMIFS(Raw_Q!$I$2:$I$600,Raw_Q!$A$2:$A$600,Stock_Card!$B$2,Raw_Q!$R$2:$R$600,6)-SUMIFS(Raw_Q!$J$2:$J$600,Raw_Q!$A$2:$A$600,Stock_Card!$B$2,Raw_Q!$R$2:$R$600,10)/SUMIFS(Raw_Q!$I$2:$I$600,Raw_Q!$A$2:$A$600,Stock_Card!$B$2,Raw_Q!$R$2:$R$600,10))*10000,"")) -> 572.1601 | L11: =IF(Stock_Card!$B$2="","",IFERROR(SUMIFS(Raw_Q!$L$2:$L$600,Raw_Q!$A$2:$A$600,Stock_Card!$B$2,Raw_Q!$R$2:$R$600,6),"")) -> 13.95 | M11: =IF(Stock_Card!$B$2="","",IFERROR((SUMIFS(Raw_Q!$L$2:$L$600,Raw_Q!$A$2:$A$600,Stock_Card!$B$2,Raw_Q!$R$2:$R$600,6)/SUMIFS(Raw_Q!$L$2:$L$600,Raw_Q!$A$2:$A$600,Stock_Card!$B$2,Raw_Q!$R$2:$R$600,10)-1),"")) -> 0.60344828 | N11: =IF(Stock_Card!$B$2="","",IFERROR(SUMIFS(Raw_Q!$P$2:$P$600,Raw_Q!$A$2:$A$600,Stock_Card!$B$2,Raw_Q!$R$2:$R$600,6),"")) -> 4.5000204 | O11: =IF(Stock_Card!$B$2="","",IF(6=0,"預估","實際")) -> 實際
A12: =IF(Stock_Card!$B$2="","",IFERROR(INDEX(Raw_Q!$B$2:$B$600,MATCH(Stock_Card!$B$2&"|"&5,Raw_Q!$S$2:$S$600,0)),"")) -> FY2025Q2 | B12: =IF(Stock_Card!$B$2="","",IFERROR(IF(SUMIFS(Raw_Q!$E$2:$E$600,Raw_Q!$A$2:$A$600,Stock_Card!$B$2,Raw_Q!$R$2:$R$600,5)=0,"",SUMIFS(Raw_Q!$E$2:$E$600,Raw_Q!$A$2:$A$600,Stock_Card!$B$2,Raw_Q!$R$2:$R$600,5)),"")) -> 45838 | C12: =IF(Stock_Card!$B$2="","",IFERROR(SUMIFS(Raw_Q!$I$2:$I$600,Raw_Q!$A$2:$A$600,Stock_Card!$B$2,Raw_Q!$R$2:$R$600,5),"")) -> 933791.87 | D12: =IF(Stock_Card!$B$2="","",IFERROR((SUMIFS(Raw_Q!$I$2:$I$600,Raw_Q!$A$2:$A$600,Stock_Card!$B$2,Raw_Q!$R$2:$R$600,5)/SUMIFS(Raw_Q!$I$2:$I$600,Raw_Q!$A$2:$A$600,Stock_Card!$B$2,Raw_Q!$R$2:$R$600,6)-1),"")) -> 0.11264557 | E12: =IF(Stock_Card!$B$2="","",IFERROR((SUMIFS(Raw_Q!$I$2:$I$600,Raw_Q!$A$2:$A$600,Stock_Card!$B$2,Raw_Q!$R$2:$R$600,6)/SUMIFS(Raw_Q!$I$2:$I$600,Raw_Q!$A$2:$A$600,Stock_Card!$B$2,Raw_Q!$R$2:$R$600,7)-1),"")) -> -0.033631341 | F12: =IF(Stock_Card!$B$2="","",IFERROR(((SUMIFS(Raw_Q!$I$2:$I$600,Raw_Q!$A$2:$A$600,Stock_Card!$B$2,Raw_Q!$R$2:$R$600,5)/SUMIFS(Raw_Q!$I$2:$I$600,Raw_Q!$A$2:$A$600,Stock_Card!$B$2,Raw_Q!$R$2:$R$600,6)-1)-(SUMIFS(Raw_Q!$I$2:$I$600,Raw_Q!$A$2:$A$600,Stock_Card!$B$2,Raw_Q!$R$2:$R$600,6)/SUMIFS(Raw_Q!$I$2:$I$600,Raw_Q!$A$2:$A$600,Stock_Card!$B$2,Raw_Q!$R$2:$R$600,7)-1))*100,"")) -> 14.627691 | G12: =IF(Stock_Card!$B$2="","",IFERROR(IF(NOT(ISNUMBER(D12)),"",IF(D12>0,IF(F12>0,"成長且加速","成長但減速"),IF(F12>0,"衰退但收斂","衰退且惡化"))),"")) -> 成長且加速 | H12: =IF(Stock_Card!$B$2="","",IFERROR(((SUMIFS(Raw_Q!$I$2:$I$600,Raw_Q!$A$2:$A$600,Stock_Card!$B$2,Raw_Q!$R$2:$R$600,5)/SUMIFS(Raw_Q!$I$2:$I$600,Raw_Q!$A$2:$A$600,Stock_Card!$B$2,Raw_Q!$R$2:$R$600,6)-1)-(SUMIFS(Raw_Q!$I$2:$I$600,Raw_Q!$A$2:$A$600,Stock_Card!$B$2,Raw_Q!$R$2:$R$600,9)/SUMIFS(Raw_Q!$I$2:$I$600,Raw_Q!$A$2:$A$600,Stock_Card!$B$2,Raw_Q!$R$2:$R$600,10)-1))*100,"")) -> -2.3803884 | I12: =IF(Stock_Card!$B$2="","",IFERROR((SUMIFS(Raw_Q!$I$2:$I$600,Raw_Q!$A$2:$A$600,Stock_Card!$B$2,Raw_Q!$R$2:$R$600,5)/SUMIFS(Raw_Q!$I$2:$I$600,Raw_Q!$A$2:$A$600,Stock_Card!$B$2,Raw_Q!$R$2:$R$600,9)-1),"")) -> 0.38645547 | J12: =IF(Stock_Card!$B$2="","",IFERROR(SUMIFS(Raw_Q!$J$2:$J$600,Raw_Q!$A$2:$A$600,Stock_Card!$B$2,Raw_Q!$R$2:$R$600,5)/SUMIFS(Raw_Q!$I$2:$I$600,Raw_Q!$A$2:$A$600,Stock_Card!$B$2,Raw_Q!$R$2:$R$600,5),"")) -> 0.58617906 | K12: =IF(Stock_Card!$B$2="","",IFERROR((SUMIFS(Raw_Q!$J$2:$J$600,Raw_Q!$A$2:$A$600,Stock_Card!$B$2,Raw_Q!$R$2:$R$600,5)/SUMIFS(Raw_Q!$I$2:$I$600,Raw_Q!$A$2:$A$600,Stock_Card!$B$2,Raw_Q!$R$2:$R$600,5)-SUMIFS(Raw_Q!$J$2:$J$600,Raw_Q!$A$2:$A$600,Stock_Card!$B$2,Raw_Q!$R$2:$R$600,9)/SUMIFS(Raw_Q!$I$2:$I$600,Raw_Q!$A$2:$A$600,Stock_Card!$B$2,Raw_Q!$R$2:$R$600,9))*10000,"")) -> 544.50674 | L12: =IF(Stock_Card!$B$2="","",IFERROR(SUMIFS(Raw_Q!$L$2:$L$600,Raw_Q!$A$2:$A$600,Stock_Card!$B$2,Raw_Q!$R$2:$R$600,5),"")) -> 15.36 | M12: =IF(Stock_Card!$B$2="","",IFERROR((SUMIFS(Raw_Q!$L$2:$L$600,Raw_Q!$A$2:$A$600,Stock_Card!$B$2,Raw_Q!$R$2:$R$600,5)/SUMIFS(Raw_Q!$L$2:$L$600,Raw_Q!$A$2:$A$600,Stock_Card!$B$2,Raw_Q!$R$2:$R$600,9)-1),"")) -> 0.60669456 | N12: =IF(Stock_Card!$B$2="","",IFERROR(SUMIFS(Raw_Q!$P$2:$P$600,Raw_Q!$A$2:$A$600,Stock_Card!$B$2,Raw_Q!$R$2:$R$600,5),"")) -> 4.5000204 | O12: =IF(Stock_Card!$B$2="","",IF(5=0,"預估","實際")) -> 實際
A13: =IF(Stock_Card!$B$2="","",IFERROR(INDEX(Raw_Q!$B$2:$B$600,MATCH(Stock_Card!$B$2&"|"&4,Raw_Q!$S$2:$S$600,0)),"")) -> FY2025Q3 | B13: =IF(Stock_Card!$B$2="","",IFERROR(IF(SUMIFS(Raw_Q!$E$2:$E$600,Raw_Q!$A$2:$A$600,Stock_Card!$B$2,Raw_Q!$R$2:$R$600,4)=0,"",SUMIFS(Raw_Q!$E$2:$E$600,Raw_Q!$A$2:$A$600,Stock_Card!$B$2,Raw_Q!$R$2:$R$600,4)),"")) -> 45930 | C13: =IF(Stock_Card!$B$2="","",IFERROR(SUMIFS(Raw_Q!$I$2:$I$600,Raw_Q!$A$2:$A$600,Stock_Card!$B$2,Raw_Q!$R$2:$R$600,4),"")) -> 989918.32 | D13: =IF(Stock_Card!$B$2="","",IFERROR((SUMIFS(Raw_Q!$I$2:$I$600,Raw_Q!$A$2:$A$600,Stock_Card!$B$2,Raw_Q!$R$2:$R$600,4)/SUMIFS(Raw_Q!$I$2:$I$600,Raw_Q!$A$2:$A$600,Stock_Card!$B$2,Raw_Q!$R$2:$R$600,5)-1),"")) -> 0.060105952 | E13: =IF(Stock_Card!$B$2="","",IFERROR((SUMIFS(Raw_Q!$I$2:$I$600,Raw_Q!$A$2:$A$600,Stock_Card!$B$2,Raw_Q!$R$2:$R$600,5)/SUMIFS(Raw_Q!$I$2:$I$600,Raw_Q!$A$2:$A$600,Stock_Card!$B$2,Raw_Q!$R$2:$R$600,6)-1),"")) -> 0.11264557 | F13: =IF(Stock_Card!$B$2="","",IFERROR(((SUMIFS(Raw_Q!$I$2:$I$600,Raw_Q!$A$2:$A$600,Stock_Card!$B$2,Raw_Q!$R$2:$R$600,4)/SUMIFS(Raw_Q!$I$2:$I$600,Raw_Q!$A$2:$A$600,Stock_Card!$B$2,Raw_Q!$R$2:$R$600,5)-1)-(SUMIFS(Raw_Q!$I$2:$I$600,Raw_Q!$A$2:$A$600,Stock_Card!$B$2,Raw_Q!$R$2:$R$600,5)/SUMIFS(Raw_Q!$I$2:$I$600,Raw_Q!$A$2:$A$600,Stock_Card!$B$2,Raw_Q!$R$2:$R$600,6)-1))*100,"")) -> -5.2539615 | G13: =IF(Stock_Card!$B$2="","",IFERROR(IF(NOT(ISNUMBER(D13)),"",IF(D13>0,IF(F13>0,"成長且加速","成長但減速"),IF(F13>0,"衰退但收斂","衰退且惡化"))),"")) -> 成長但減速 | H13: =IF(Stock_Card!$B$2="","",IFERROR(((SUMIFS(Raw_Q!$I$2:$I$600,Raw_Q!$A$2:$A$600,Stock_Card!$B$2,Raw_Q!$R$2:$R$600,4)/SUMIFS(Raw_Q!$I$2:$I$600,Raw_Q!$A$2:$A$600,Stock_Card!$B$2,Raw_Q!$R$2:$R$600,5)-1)-(SUMIFS(Raw_Q!$I$2:$I$600,Raw_Q!$A$2:$A$600,Stock_Card!$B$2,Raw_Q!$R$2:$R$600,8)/SUMIFS(Raw_Q!$I$2:$I$600,Raw_Q!$A$2:$A$600,Stock_Card!$B$2,Raw_Q!$R$2:$R$600,9)-1))*100,"")) -> -6.785346 | I13: =IF(Stock_Card!$B$2="","",IFERROR((SUMIFS(Raw_Q!$I$2:$I$600,Raw_Q!$A$2:$A$600,Stock_Card!$B$2,Raw_Q!$R$2:$R$600,4)/SUMIFS(Raw_Q!$I$2:$I$600,Raw_Q!$A$2:$A$600,Stock_Card!$B$2,Raw_Q!$R$2:$R$600,8)-1),"")) -> 0.30305194 | J13: =IF(Stock_Card!$B$2="","",IFERROR(SUMIFS(Raw_Q!$J$2:$J$600,Raw_Q!$A$2:$A$600,Stock_Card!$B$2,Raw_Q!$R$2:$R$600,4)/SUMIFS(Raw_Q!$I$2:$I$600,Raw_Q!$A$2:$A$600,Stock_Card!$B$2,Raw_Q!$R$2:$R$600,4),"")) -> 0.59453676 | K13: =IF(Stock_Card!$B$2="","",IFERROR((SUMIFS(Raw_Q!$J$2:$J$600,Raw_Q!$A$2:$A$600,Stock_Card!$B$2,Raw_Q!$R$2:$R$600,4)/SUMIFS(Raw_Q!$I$2:$I$600,Raw_Q!$A$2:$A$600,Stock_Card!$B$2,Raw_Q!$R$2:$R$600,4)-SUMIFS(Raw_Q!$J$2:$J$600,Raw_Q!$A$2:$A$600,Stock_Card!$B$2,Raw_Q!$R$2:$R$600,8)/SUMIFS(Raw_Q!$I$2:$I$600,Raw_Q!$A$2:$A$600,Stock_Card!$B$2,Raw_Q!$R$2:$R$600,8))*10000,"")) -> 162.16094 | L13: =IF(Stock_Card!$B$2="","",IFERROR(SUMIFS(Raw_Q!$L$2:$L$600,Raw_Q!$A$2:$A$600,Stock_Card!$B$2,Raw_Q!$R$2:$R$600,4),"")) -> 17.44 | M13: =IF(Stock_Card!$B$2="","",IFERROR((SUMIFS(Raw_Q!$L$2:$L$600,Raw_Q!$A$2:$A$600,Stock_Card!$B$2,Raw_Q!$R$2:$R$600,4)/SUMIFS(Raw_Q!$L$2:$L$600,Raw_Q!$A$2:$A$600,Stock_Card!$B$2,Raw_Q!$R$2:$R$600,8)-1),"")) -> 0.38964143 | N13: =IF(Stock_Card!$B$2="","",IFERROR(SUMIFS(Raw_Q!$P$2:$P$600,Raw_Q!$A$2:$A$600,Stock_Card!$B$2,Raw_Q!$R$2:$R$600,4),"")) -> 5.0000175 | O13: =IF(Stock_Card!$B$2="","",IF(4=0,"預估","實際")) -> 實際
A14: =IF(Stock_Card!$B$2="","",IFERROR(INDEX(Raw_Q!$B$2:$B$600,MATCH(Stock_Card!$B$2&"|"&3,Raw_Q!$S$2:$S$600,0)),"")) -> FY2025Q4 | B14: =IF(Stock_Card!$B$2="","",IFERROR(IF(SUMIFS(Raw_Q!$E$2:$E$600,Raw_Q!$A$2:$A$600,Stock_Card!$B$2,Raw_Q!$R$2:$R$600,3)=0,"",SUMIFS(Raw_Q!$E$2:$E$600,Raw_Q!$A$2:$A$600,Stock_Card!$B$2,Raw_Q!$R$2:$R$600,3)),"")) -> 46022 | C14: =IF(Stock_Card!$B$2="","",IFERROR(SUMIFS(Raw_Q!$I$2:$I$600,Raw_Q!$A$2:$A$600,Stock_Card!$B$2,Raw_Q!$R$2:$R$600,3),"")) -> 1046090.4 | D14: =IF(Stock_Card!$B$2="","",IFERROR((SUMIFS(Raw_Q!$I$2:$I$600,Raw_Q!$A$2:$A$600,Stock_Card!$B$2,Raw_Q!$R$2:$R$600,3)/SUMIFS(Raw_Q!$I$2:$I$600,Raw_Q!$A$2:$A$600,Stock_Card!$B$2,Raw_Q!$R$2:$R$600,4)-1),"")) -> 0.05674418 | E14: =IF(Stock_Card!$B$2="","",IFERROR((SUMIFS(Raw_Q!$I$2:$I$600,Raw_Q!$A$2:$A$600,Stock_Card!$B$2,Raw_Q!$R$2:$R$600,4)/SUMIFS(Raw_Q!$I$2:$I$600,Raw_Q!$A$2:$A$600,Stock_Card!$B$2,Raw_Q!$R$2:$R$600,5)-1),"")) -> 0.060105952 | F14: =IF(Stock_Card!$B$2="","",IFERROR(((SUMIFS(Raw_Q!$I$2:$I$600,Raw_Q!$A$2:$A$600,Stock_Card!$B$2,Raw_Q!$R$2:$R$600,3)/SUMIFS(Raw_Q!$I$2:$I$600,Raw_Q!$A$2:$A$600,Stock_Card!$B$2,Raw_Q!$R$2:$R$600,4)-1)-(SUMIFS(Raw_Q!$I$2:$I$600,Raw_Q!$A$2:$A$600,Stock_Card!$B$2,Raw_Q!$R$2:$R$600,4)/SUMIFS(Raw_Q!$I$2:$I$600,Raw_Q!$A$2:$A$600,Stock_Card!$B$2,Raw_Q!$R$2:$R$600,5)-1))*100,"")) -> -0.33617719 | G14: =IF(Stock_Card!$B$2="","",IFERROR(IF(NOT(ISNUMBER(D14)),"",IF(D14>0,IF(F14>0,"成長且加速","成長但減速"),IF(F14>0,"衰退但收斂","衰退且惡化"))),"")) -> 成長但減速 | H14: =IF(Stock_Card!$B$2="","",IFERROR(((SUMIFS(Raw_Q!$I$2:$I$600,Raw_Q!$A$2:$A$600,Stock_Card!$B$2,Raw_Q!$R$2:$R$600,3)/SUMIFS(Raw_Q!$I$2:$I$600,Raw_Q!$A$2:$A$600,Stock_Card!$B$2,Raw_Q!$R$2:$R$600,4)-1)-(SUMIFS(Raw_Q!$I$2:$I$600,Raw_Q!$A$2:$A$600,Stock_Card!$B$2,Raw_Q!$R$2:$R$600,7)/SUMIFS(Raw_Q!$I$2:$I$600,Raw_Q!$A$2:$A$600,Stock_Card!$B$2,Raw_Q!$R$2:$R$600,8)-1))*100,"")) -> -8.6430968 | I14: =IF(Stock_Card!$B$2="","",IFERROR((SUMIFS(Raw_Q!$I$2:$I$600,Raw_Q!$A$2:$A$600,Stock_Card!$B$2,Raw_Q!$R$2:$R$600,3)/SUMIFS(Raw_Q!$I$2:$I$600,Raw_Q!$A$2:$A$600,Stock_Card!$B$2,Raw_Q!$R$2:$R$600,7)-1),"")) -> 0.20453331 | J14: =IF(Stock_Card!$B$2="","",IFERROR(SUMIFS(Raw_Q!$J$2:$J$600,Raw_Q!$A$2:$A$600,Stock_Card!$B$2,Raw_Q!$R$2:$R$600,3)/SUMIFS(Raw_Q!$I$2:$I$600,Raw_Q!$A$2:$A$600,Stock_Card!$B$2,Raw_Q!$R$2:$R$600,3),"")) -> 0.6232605 | K14: =IF(Stock_Card!$B$2="","",IFERROR((SUMIFS(Raw_Q!$J$2:$J$600,Raw_Q!$A$2:$A$600,Stock_Card!$B$2,Raw_Q!$R$2:$R$600,3)/SUMIFS(Raw_Q!$I$2:$I$600,Raw_Q!$A$2:$A$600,Stock_Card!$B$2,Raw_Q!$R$2:$R$600,3)-SUMIFS(Raw_Q!$J$2:$J$600,Raw_Q!$A$2:$A$600,Stock_Card!$B$2,Raw_Q!$R$2:$R$600,7)/SUMIFS(Raw_Q!$I$2:$I$600,Raw_Q!$A$2:$A$600,Stock_Card!$B$2,Raw_Q!$R$2:$R$600,7))*10000,"")) -> 332.76553 | L14: =IF(Stock_Card!$B$2="","",IFERROR(SUMIFS(Raw_Q!$L$2:$L$600,Raw_Q!$A$2:$A$600,Stock_Card!$B$2,Raw_Q!$R$2:$R$600,3),"")) -> 19.51 | M14: =IF(Stock_Card!$B$2="","",IFERROR((SUMIFS(Raw_Q!$L$2:$L$600,Raw_Q!$A$2:$A$600,Stock_Card!$B$2,Raw_Q!$R$2:$R$600,3)/SUMIFS(Raw_Q!$L$2:$L$600,Raw_Q!$A$2:$A$600,Stock_Card!$B$2,Raw_Q!$R$2:$R$600,7)-1),"")) -> 0.35017301 | N14: =IF(Stock_Card!$B$2="","",IFERROR(SUMIFS(Raw_Q!$P$2:$P$600,Raw_Q!$A$2:$A$600,Stock_Card!$B$2,Raw_Q!$R$2:$R$600,3),"")) -> 5.0000112 | O14: =IF(Stock_Card!$B$2="","",IF(3=0,"預估","實際")) -> 實際
A15: =IF(Stock_Card!$B$2="","",IFERROR(INDEX(Raw_Q!$B$2:$B$600,MATCH(Stock_Card!$B$2&"|"&2,Raw_Q!$S$2:$S$600,0)),"")) -> FY2026Q1 | B15: =IF(Stock_Card!$B$2="","",IFERROR(IF(SUMIFS(Raw_Q!$E$2:$E$600,Raw_Q!$A$2:$A$600,Stock_Card!$B$2,Raw_Q!$R$2:$R$600,2)=0,"",SUMIFS(Raw_Q!$E$2:$E$600,Raw_Q!$A$2:$A$600,Stock_Card!$B$2,Raw_Q!$R$2:$R$600,2)),"")) -> 46112 | C15: =IF(Stock_Card!$B$2="","",IFERROR(SUMIFS(Raw_Q!$I$2:$I$600,Raw_Q!$A$2:$A$600,Stock_Card!$B$2,Raw_Q!$R$2:$R$600,2),"")) -> 1134103.4 | D15: =IF(Stock_Card!$B$2="","",IFERROR((SUMIFS(Raw_Q!$I$2:$I$600,Raw_Q!$A$2:$A$600,Stock_Card!$B$2,Raw_Q!$R$2:$R$600,2)/SUMIFS(Raw_Q!$I$2:$I$600,Raw_Q!$A$2:$A$600,Stock_Card!$B$2,Raw_Q!$R$2:$R$600,3)-1),"")) -> 0.084135193 | E15: =IF(Stock_Card!$B$2="","",IFERROR((SUMIFS(Raw_Q!$I$2:$I$600,Raw_Q!$A$2:$A$600,Stock_Card!$B$2,Raw_Q!$R$2:$R$600,3)/SUMIFS(Raw_Q!$I$2:$I$600,Raw_Q!$A$2:$A$600,Stock_Card!$B$2,Raw_Q!$R$2:$R$600,4)-1),"")) -> 0.05674418 | F15: =IF(Stock_Card!$B$2="","",IFERROR(((SUMIFS(Raw_Q!$I$2:$I$600,Raw_Q!$A$2:$A$600,Stock_Card!$B$2,Raw_Q!$R$2:$R$600,2)/SUMIFS(Raw_Q!$I$2:$I$600,Raw_Q!$A$2:$A$600,Stock_Card!$B$2,Raw_Q!$R$2:$R$600,3)-1)-(SUMIFS(Raw_Q!$I$2:$I$600,Raw_Q!$A$2:$A$600,Stock_Card!$B$2,Raw_Q!$R$2:$R$600,3)/SUMIFS(Raw_Q!$I$2:$I$600,Raw_Q!$A$2:$A$600,Stock_Card!$B$2,Raw_Q!$R$2:$R$600,4)-1))*100,"")) -> 2.7391013 | G15: =IF(Stock_Card!$B$2="","",IFERROR(IF(NOT(ISNUMBER(D15)),"",IF(D15>0,IF(F15>0,"成長且加速","成長但減速"),IF(F15>0,"衰退但收斂","衰退且惡化"))),"")) -> 成長且加速 | H15: =IF(Stock_Card!$B$2="","",IFERROR(((SUMIFS(Raw_Q!$I$2:$I$600,Raw_Q!$A$2:$A$600,Stock_Card!$B$2,Raw_Q!$R$2:$R$600,2)/SUMIFS(Raw_Q!$I$2:$I$600,Raw_Q!$A$2:$A$600,Stock_Card!$B$2,Raw_Q!$R$2:$R$600,3)-1)-(SUMIFS(Raw_Q!$I$2:$I$600,Raw_Q!$A$2:$A$600,Stock_Card!$B$2,Raw_Q!$R$2:$R$600,6)/SUMIFS(Raw_Q!$I$2:$I$600,Raw_Q!$A$2:$A$600,Stock_Card!$B$2,Raw_Q!$R$2:$R$600,7)-1))*100,"")) -> 11.776653 | I15: =IF(Stock_Card!$B$2="","",IFERROR((SUMIFS(Raw_Q!$I$2:$I$600,Raw_Q!$A$2:$A$600,Stock_Card!$B$2,Raw_Q!$R$2:$R$600,2)/SUMIFS(Raw_Q!$I$2:$I$600,Raw_Q!$A$2:$A$600,Stock_Card!$B$2,Raw_Q!$R$2:$R$600,6)-1),"")) -> 0.35132379 | J15: =IF(Stock_Card!$B$2="","",IFERROR(SUMIFS(Raw_Q!$J$2:$J$600,Raw_Q!$A$2:$A$600,Stock_Card!$B$2,Raw_Q!$R$2:$R$600,2)/SUMIFS(Raw_Q!$I$2:$I$600,Raw_Q!$A$2:$A$600,Stock_Card!$B$2,Raw_Q!$R$2:$R$600,2),"")) -> 0.66245758 | K15: =IF(Stock_Card!$B$2="","",IFERROR((SUMIFS(Raw_Q!$J$2:$J$600,Raw_Q!$A$2:$A$600,Stock_Card!$B$2,Raw_Q!$R$2:$R$600,2)/SUMIFS(Raw_Q!$I$2:$I$600,Raw_Q!$A$2:$A$600,Stock_Card!$B$2,Raw_Q!$R$2:$R$600,2)-SUMIFS(Raw_Q!$J$2:$J$600,Raw_Q!$A$2:$A$600,Stock_Card!$B$2,Raw_Q!$R$2:$R$600,6)/SUMIFS(Raw_Q!$I$2:$I$600,Raw_Q!$A$2:$A$600,Stock_Card!$B$2,Raw_Q!$R$2:$R$600,6))*10000,"")) -> 745.60146 | L15: =IF(Stock_Card!$B$2="","",IFERROR(SUMIFS(Raw_Q!$L$2:$L$600,Raw_Q!$A$2:$A$600,Stock_Card!$B$2,Raw_Q!$R$2:$R$600,2),"")) -> 22.08 | M15: =IF(Stock_Card!$B$2="","",IFERROR((SUMIFS(Raw_Q!$L$2:$L$600,Raw_Q!$A$2:$A$600,Stock_Card!$B$2,Raw_Q!$R$2:$R$600,2)/SUMIFS(Raw_Q!$L$2:$L$600,Raw_Q!$A$2:$A$600,Stock_Card!$B$2,Raw_Q!$R$2:$R$600,6)-1),"")) -> 0.5827957 | N15: =IF(Stock_Card!$B$2="","",IFERROR(SUMIFS(Raw_Q!$P$2:$P$600,Raw_Q!$A$2:$A$600,Stock_Card!$B$2,Raw_Q!$R$2:$R$600,2),"")) -> 6.0000357 | O15: =IF(Stock_Card!$B$2="","",IF(2=0,"預估","實際")) -> 實際
A16: =IF(Stock_Card!$B$2="","",IFERROR(INDEX(Raw_Q!$B$2:$B$600,MATCH(Stock_Card!$B$2&"|"&1,Raw_Q!$S$2:$S$600,0)),"")) -> FY2026Q2 | B16: =IF(Stock_Card!$B$2="","",IFERROR(IF(SUMIFS(Raw_Q!$E$2:$E$600,Raw_Q!$A$2:$A$600,Stock_Card!$B$2,Raw_Q!$R$2:$R$600,1)=0,"",SUMIFS(Raw_Q!$E$2:$E$600,Raw_Q!$A$2:$A$600,Stock_Card!$B$2,Raw_Q!$R$2:$R$600,1)),"")) -> 46203 | C16: =IF(Stock_Card!$B$2="","",IFERROR(SUMIFS(Raw_Q!$I$2:$I$600,Raw_Q!$A$2:$A$600,Stock_Card!$B$2,Raw_Q!$R$2:$R$600,1),"")) -> 1270380.2 | D16: =IF(Stock_Card!$B$2="","",IFERROR((SUMIFS(Raw_Q!$I$2:$I$600,Raw_Q!$A$2:$A$600,Stock_Card!$B$2,Raw_Q!$R$2:$R$600,1)/SUMIFS(Raw_Q!$I$2:$I$600,Raw_Q!$A$2:$A$600,Stock_Card!$B$2,Raw_Q!$R$2:$R$600,2)-1),"")) -> 0.12016259 | E16: =IF(Stock_Card!$B$2="","",IFERROR((SUMIFS(Raw_Q!$I$2:$I$600,Raw_Q!$A$2:$A$600,Stock_Card!$B$2,Raw_Q!$R$2:$R$600,2)/SUMIFS(Raw_Q!$I$2:$I$600,Raw_Q!$A$2:$A$600,Stock_Card!$B$2,Raw_Q!$R$2:$R$600,3)-1),"")) -> 0.084135193 | F16: =IF(Stock_Card!$B$2="","",IFERROR(((SUMIFS(Raw_Q!$I$2:$I$600,Raw_Q!$A$2:$A$600,Stock_Card!$B$2,Raw_Q!$R$2:$R$600,1)/SUMIFS(Raw_Q!$I$2:$I$600,Raw_Q!$A$2:$A$600,Stock_Card!$B$2,Raw_Q!$R$2:$R$600,2)-1)-(SUMIFS(Raw_Q!$I$2:$I$600,Raw_Q!$A$2:$A$600,Stock_Card!$B$2,Raw_Q!$R$2:$R$600,2)/SUMIFS(Raw_Q!$I$2:$I$600,Raw_Q!$A$2:$A$600,Stock_Card!$B$2,Raw_Q!$R$2:$R$600,3)-1))*100,"")) -> 3.60274 | G16: =IF(Stock_Card!$B$2="","",IFERROR(IF(NOT(ISNUMBER(D16)),"",IF(D16>0,IF(F16>0,"成長且加速","成長但減速"),IF(F16>0,"衰退但收斂","衰退且惡化"))),"")) -> 成長且加速 | H16: =IF(Stock_Card!$B$2="","",IFERROR(((SUMIFS(Raw_Q!$I$2:$I$600,Raw_Q!$A$2:$A$600,Stock_Card!$B$2,Raw_Q!$R$2:$R$600,1)/SUMIFS(Raw_Q!$I$2:$I$600,Raw_Q!$A$2:$A$600,Stock_Card!$B$2,Raw_Q!$R$2:$R$600,2)-1)-(SUMIFS(Raw_Q!$I$2:$I$600,Raw_Q!$A$2:$A$600,Stock_Card!$B$2,Raw_Q!$R$2:$R$600,5)/SUMIFS(Raw_Q!$I$2:$I$600,Raw_Q!$A$2:$A$600,Stock_Card!$B$2,Raw_Q!$R$2:$R$600,6)-1))*100,"")) -> 0.75170257 | I16: =IF(Stock_Card!$B$2="","",IFERROR((SUMIFS(Raw_Q!$I$2:$I$600,Raw_Q!$A$2:$A$600,Stock_Card!$B$2,Raw_Q!$R$2:$R$600,1)/SUMIFS(Raw_Q!$I$2:$I$600,Raw_Q!$A$2:$A$600,Stock_Card!$B$2,Raw_Q!$R$2:$R$600,5)-1),"")) -> 0.36045332 | J16: =IF(Stock_Card!$B$2="","",IFERROR(SUMIFS(Raw_Q!$J$2:$J$600,Raw_Q!$A$2:$A$600,Stock_Card!$B$2,Raw_Q!$R$2:$R$600,1)/SUMIFS(Raw_Q!$I$2:$I$600,Raw_Q!$A$2:$A$600,Stock_Card!$B$2,Raw_Q!$R$2:$R$600,1),"")) -> 0.67720723 | K16: =IF(Stock_Card!$B$2="","",IFERROR((SUMIFS(Raw_Q!$J$2:$J$600,Raw_Q!$A$2:$A$600,Stock_Card!$B$2,Raw_Q!$R$2:$R$600,1)/SUMIFS(Raw_Q!$I$2:$I$600,Raw_Q!$A$2:$A$600,Stock_Card!$B$2,Raw_Q!$R$2:$R$600,1)-SUMIFS(Raw_Q!$J$2:$J$600,Raw_Q!$A$2:$A$600,Stock_Card!$B$2,Raw_Q!$R$2:$R$600,5)/SUMIFS(Raw_Q!$I$2:$I$600,Raw_Q!$A$2:$A$600,Stock_Card!$B$2,Raw_Q!$R$2:$R$600,5))*10000,"")) -> 910.28176 | L16: =IF(Stock_Card!$B$2="","",IFERROR(SUMIFS(Raw_Q!$L$2:$L$600,Raw_Q!$A$2:$A$600,Stock_Card!$B$2,Raw_Q!$R$2:$R$600,1),"")) -> 27.25 | M16: =IF(Stock_Card!$B$2="","",IFERROR((SUMIFS(Raw_Q!$L$2:$L$600,Raw_Q!$A$2:$A$600,Stock_Card!$B$2,Raw_Q!$R$2:$R$600,1)/SUMIFS(Raw_Q!$L$2:$L$600,Raw_Q!$A$2:$A$600,Stock_Card!$B$2,Raw_Q!$R$2:$R$600,5)-1),"")) -> 0.77408854 | N16: =IF(Stock_Card!$B$2="","",IFERROR(SUMIFS(Raw_Q!$P$2:$P$600,Raw_Q!$A$2:$A$600,Stock_Card!$B$2,Raw_Q!$R$2:$R$600,1),"")) -> 6.0000357 | O16: =IF(Stock_Card!$B$2="","",IF(1=0,"預估","實際")) -> 實際
A17: =IF(Stock_Card!$B$2="","",IFERROR(INDEX(Raw_Q!$B$2:$B$600,MATCH(Stock_Card!$B$2&"|"&0,Raw_Q!$S$2:$S$600,0)),"")) -> FY2026Q3E | B17: =IF(Stock_Card!$B$2="","",IFERROR(IF(SUMIFS(Raw_Q!$E$2:$E$600,Raw_Q!$A$2:$A$600,Stock_Card!$B$2,Raw_Q!$R$2:$R$600,0)=0,"",SUMIFS(Raw_Q!$E$2:$E$600,Raw_Q!$A$2:$A$600,Stock_Card!$B$2,Raw_Q!$R$2:$R$600,0)),"")) -> 46295 | C17: =IF(Stock_Card!$B$2="","",IFERROR(SUMIFS(Raw_Q!$I$2:$I$600,Raw_Q!$A$2:$A$600,Stock_Card!$B$2,Raw_Q!$R$2:$R$600,0),"")) -> 0 | D17: =IF(Stock_Card!$B$2="","",IFERROR((SUMIFS(Raw_Q!$I$2:$I$600,Raw_Q!$A$2:$A$600,Stock_Card!$B$2,Raw_Q!$R$2:$R$600,0)/SUMIFS(Raw_Q!$I$2:$I$600,Raw_Q!$A$2:$A$600,Stock_Card!$B$2,Raw_Q!$R$2:$R$600,1)-1),"")) -> -1 | E17: =IF(Stock_Card!$B$2="","",IFERROR((SUMIFS(Raw_Q!$I$2:$I$600,Raw_Q!$A$2:$A$600,Stock_Card!$B$2,Raw_Q!$R$2:$R$600,1)/SUMIFS(Raw_Q!$I$2:$I$600,Raw_Q!$A$2:$A$600,Stock_Card!$B$2,Raw_Q!$R$2:$R$600,2)-1),"")) -> 0.12016259 | F17: =IF(Stock_Card!$B$2="","",IFERROR(((SUMIFS(Raw_Q!$I$2:$I$600,Raw_Q!$A$2:$A$600,Stock_Card!$B$2,Raw_Q!$R$2:$R$600,0)/SUMIFS(Raw_Q!$I$2:$I$600,Raw_Q!$A$2:$A$600,Stock_Card!$B$2,Raw_Q!$R$2:$R$600,1)-1)-(SUMIFS(Raw_Q!$I$2:$I$600,Raw_Q!$A$2:$A$600,Stock_Card!$B$2,Raw_Q!$R$2:$R$600,1)/SUMIFS(Raw_Q!$I$2:$I$600,Raw_Q!$A$2:$A$600,Stock_Card!$B$2,Raw_Q!$R$2:$R$600,2)-1))*100,"")) -> -112.01626 | G17: =IF(Stock_Card!$B$2="","",IFERROR(IF(NOT(ISNUMBER(D17)),"",IF(D17>0,IF(F17>0,"成長且加速","成長但減速"),IF(F17>0,"衰退但收斂","衰退且惡化"))),"")) -> 衰退且惡化 | H17: =IF(Stock_Card!$B$2="","",IFERROR(((SUMIFS(Raw_Q!$I$2:$I$600,Raw_Q!$A$2:$A$600,Stock_Card!$B$2,Raw_Q!$R$2:$R$600,0)/SUMIFS(Raw_Q!$I$2:$I$600,Raw_Q!$A$2:$A$600,Stock_Card!$B$2,Raw_Q!$R$2:$R$600,1)-1)-(SUMIFS(Raw_Q!$I$2:$I$600,Raw_Q!$A$2:$A$600,Stock_Card!$B$2,Raw_Q!$R$2:$R$600,4)/SUMIFS(Raw_Q!$I$2:$I$600,Raw_Q!$A$2:$A$600,Stock_Card!$B$2,Raw_Q!$R$2:$R$600,5)-1))*100,"")) -> -106.0106 | I17: =IF(Stock_Card!$B$2="","",IFERROR((SUMIFS(Raw_Q!$I$2:$I$600,Raw_Q!$A$2:$A$600,Stock_Card!$B$2,Raw_Q!$R$2:$R$600,0)/SUMIFS(Raw_Q!$I$2:$I$600,Raw_Q!$A$2:$A$600,Stock_Card!$B$2,Raw_Q!$R$2:$R$600,4)-1),"")) -> -1 | J17: =IF(Stock_Card!$B$2="","",IFERROR(SUMIFS(Raw_Q!$J$2:$J$600,Raw_Q!$A$2:$A$600,Stock_Card!$B$2,Raw_Q!$R$2:$R$600,0)/SUMIFS(Raw_Q!$I$2:$I$600,Raw_Q!$A$2:$A$600,Stock_Card!$B$2,Raw_Q!$R$2:$R$600,0),"")) | K17: =IF(Stock_Card!$B$2="","",IFERROR((SUMIFS(Raw_Q!$J$2:$J$600,Raw_Q!$A$2:$A$600,Stock_Card!$B$2,Raw_Q!$R$2:$R$600,0)/SUMIFS(Raw_Q!$I$2:$I$600,Raw_Q!$A$2:$A$600,Stock_Card!$B$2,Raw_Q!$R$2:$R$600,0)-SUMIFS(Raw_Q!$J$2:$J$600,Raw_Q!$A$2:$A$600,Stock_Card!$B$2,Raw_Q!$R$2:$R$600,4)/SUMIFS(Raw_Q!$I$2:$I$600,Raw_Q!$A$2:$A$600,Stock_Card!$B$2,Raw_Q!$R$2:$R$600,4))*10000,"")) | L17: =IF(Stock_Card!$B$2="","",IFERROR(SUMIFS(Raw_Q!$L$2:$L$600,Raw_Q!$A$2:$A$600,Stock_Card!$B$2,Raw_Q!$R$2:$R$600,0),"")) -> 28.19147 | M17: =IF(Stock_Card!$B$2="","",IFERROR((SUMIFS(Raw_Q!$L$2:$L$600,Raw_Q!$A$2:$A$600,Stock_Card!$B$2,Raw_Q!$R$2:$R$600,0)/SUMIFS(Raw_Q!$L$2:$L$600,Raw_Q!$A$2:$A$600,Stock_Card!$B$2,Raw_Q!$R$2:$R$600,4)-1),"")) -> 0.61648337 | N17: =IF(Stock_Card!$B$2="","",IFERROR(SUMIFS(Raw_Q!$P$2:$P$600,Raw_Q!$A$2:$A$600,Stock_Card!$B$2,Raw_Q!$R$2:$R$600,0),"")) -> 0 | O17: =IF(Stock_Card!$B$2="","",IF(0=0,"預估","實際")) -> 預估
A18: 營收QoQ（季度成長率）＝ 本季營收 ÷ 上一季營收 − 1。加速度(pp) ＝ 本季QoQ − 上一季QoQ。注意：加速度是「成長率的變化」，不是營收的變化——營收在衰退但衰退幅度縮小時，加速度一樣是正的。「動能判讀」欄就是為了讓正負號不再誤導。
A19: ⚠ 加速度(pp) 會被季節性主宰：旺季那一季 QoQ 天生就高、淡季天生就低，所以這一欄每年會在同一季出現同樣的大幅震盪，那是季節性不是動能。同期加速度(pp) ＝ 本季QoQ − 去年同一財季的QoQ：一樣是在比「季度成長率」，但拿去年同一季當基準，季節性自動抵消，剩下的才是真正的動能變化。最後一列黃底＝當季預估。
A21: 以下兩張矩陣同一欄＝同一個財季。長條排列會把旺季誤讀成成長，排成矩陣才看得出季節性與真實趨勢。黃底斜體＝當季預估。
A22: EPS (Adjusted) · 年 × 季矩陣
A23: 財年 | B23: Q1 | C23: Q2 | D23: Q3 | E23: Q4 | F23: FY 合計 | G23: FY YoY
A24: =IF(Stock_Card!$B$2="","",IFERROR($Z$1-4,"")) -> 2022 | B24: =IF(Stock_Card!$B$2="","",IF(COUNTIFS(Raw_Q!$A$2:$A$600,Stock_Card!$B$2,Raw_Q!$C$2:$C$600,$A24,Raw_Q!$D$2:$D$600,1)=0,"",SUMIFS(Raw_Q!$L$2:$L$600,Raw_Q!$A$2:$A$600,Stock_Card!$B$2,Raw_Q!$C$2:$C$600,$A24,Raw_Q!$D$2:$D$600,1))) -> 7.82 | C24: =IF(Stock_Card!$B$2="","",IF(COUNTIFS(Raw_Q!$A$2:$A$600,Stock_Card!$B$2,Raw_Q!$C$2:$C$600,$A24,Raw_Q!$D$2:$D$600,2)=0,"",SUMIFS(Raw_Q!$L$2:$L$600,Raw_Q!$A$2:$A$600,Stock_Card!$B$2,Raw_Q!$C$2:$C$600,$A24,Raw_Q!$D$2:$D$600,2))) -> 9.14 | D24: =IF(Stock_Card!$B$2="","",IF(COUNTIFS(Raw_Q!$A$2:$A$600,Stock_Card!$B$2,Raw_Q!$C$2:$C$600,$A24,Raw_Q!$D$2:$D$600,3)=0,"",SUMIFS(Raw_Q!$L$2:$L$600,Raw_Q!$A$2:$A$600,Stock_Card!$B$2,Raw_Q!$C$2:$C$600,$A24,Raw_Q!$D$2:$D$600,3))) -> 10.83 | E24: =IF(Stock_Card!$B$2="","",IF(COUNTIFS(Raw_Q!$A$2:$A$600,Stock_Card!$B$2,Raw_Q!$C$2:$C$600,$A24,Raw_Q!$D$2:$D$600,4)=0,"",SUMIFS(Raw_Q!$L$2:$L$600,Raw_Q!$A$2:$A$600,Stock_Card!$B$2,Raw_Q!$C$2:$C$600,$A24,Raw_Q!$D$2:$D$600,4))) -> 11.41 | F24: =IF(Stock_Card!$B$2="","",IF(COUNTIFS(Raw_Q!$A$2:$A$600,Stock_Card!$B$2,Raw_Q!$C$2:$C$600,$A24)<4,"未滿4季",SUM(B24:E24))) -> 39.2
A25: =IF(Stock_Card!$B$2="","",IFERROR($Z$1-3,"")) -> 2023 | B25: =IF(Stock_Card!$B$2="","",IF(COUNTIFS(Raw_Q!$A$2:$A$600,Stock_Card!$B$2,Raw_Q!$C$2:$C$600,$A25,Raw_Q!$D$2:$D$600,1)=0,"",SUMIFS(Raw_Q!$L$2:$L$600,Raw_Q!$A$2:$A$600,Stock_Card!$B$2,Raw_Q!$C$2:$C$600,$A25,Raw_Q!$D$2:$D$600,1))) -> 7.98 | C25: =IF(Stock_Card!$B$2="","",IF(COUNTIFS(Raw_Q!$A$2:$A$600,Stock_Card!$B$2,Raw_Q!$C$2:$C$600,$A25,Raw_Q!$D$2:$D$600,2)=0,"",SUMIFS(Raw_Q!$L$2:$L$600,Raw_Q!$A$2:$A$600,Stock_Card!$B$2,Raw_Q!$C$2:$C$600,$A25,Raw_Q!$D$2:$D$600,2))) -> 7.01 | D25: =IF(Stock_Card!$B$2="","",IF(COUNTIFS(Raw_Q!$A$2:$A$600,Stock_Card!$B$2,Raw_Q!$C$2:$C$600,$A25,Raw_Q!$D$2:$D$600,3)=0,"",SUMIFS(Raw_Q!$L$2:$L$600,Raw_Q!$A$2:$A$600,Stock_Card!$B$2,Raw_Q!$C$2:$C$600,$A25,Raw_Q!$D$2:$D$600,3))) -> 8.14 | E25: =IF(Stock_Card!$B$2="","",IF(COUNTIFS(Raw_Q!$A$2:$A$600,Stock_Card!$B$2,Raw_Q!$C$2:$C$600,$A25,Raw_Q!$D$2:$D$600,4)=0,"",SUMIFS(Raw_Q!$L$2:$L$600,Raw_Q!$A$2:$A$600,Stock_Card!$B$2,Raw_Q!$C$2:$C$600,$A25,Raw_Q!$D$2:$D$600,4))) -> 9.21 | F25: =IF(Stock_Card!$B$2="","",IF(COUNTIFS(Raw_Q!$A$2:$A$600,Stock_Card!$B$2,Raw_Q!$C$2:$C$600,$A25)<4,"未滿4季",SUM(B25:E25))) -> 32.34 | G25: =IFERROR(IF(OR(NOT(ISNUMBER(F25)),NOT(ISNUMBER(F24))),"",F25/F24-1),"") -> -0.175
A26: =IF(Stock_Card!$B$2="","",IFERROR($Z$1-2,"")) -> 2024 | B26: =IF(Stock_Card!$B$2="","",IF(COUNTIFS(Raw_Q!$A$2:$A$600,Stock_Card!$B$2,Raw_Q!$C$2:$C$600,$A26,Raw_Q!$D$2:$D$600,1)=0,"",SUMIFS(Raw_Q!$L$2:$L$600,Raw_Q!$A$2:$A$600,Stock_Card!$B$2,Raw_Q!$C$2:$C$600,$A26,Raw_Q!$D$2:$D$600,1))) -> 8.7 | C26: =IF(Stock_Card!$B$2="","",IF(COUNTIFS(Raw_Q!$A$2:$A$600,Stock_Card!$B$2,Raw_Q!$C$2:$C$600,$A26,Raw_Q!$D$2:$D$600,2)=0,"",SUMIFS(Raw_Q!$L$2:$L$600,Raw_Q!$A$2:$A$600,Stock_Card!$B$2,Raw_Q!$C$2:$C$600,$A26,Raw_Q!$D$2:$D$600,2))) -> 9.56 | D26: =IF(Stock_Card!$B$2="","",IF(COUNTIFS(Raw_Q!$A$2:$A$600,Stock_Card!$B$2,Raw_Q!$C$2:$C$600,$A26,Raw_Q!$D$2:$D$600,3)=0,"",SUMIFS(Raw_Q!$L$2:$L$600,Raw_Q!$A$2:$A$600,Stock_Card!$B$2,Raw_Q!$C$2:$C$600,$A26,Raw_Q!$D$2:$D$600,3))) -> 12.55 | E26: =IF(Stock_Card!$B$2="","",IF(COUNTIFS(Raw_Q!$A$2:$A$600,Stock_Card!$B$2,Raw_Q!$C$2:$C$600,$A26,Raw_Q!$D$2:$D$600,4)=0,"",SUMIFS(Raw_Q!$L$2:$L$600,Raw_Q!$A$2:$A$600,Stock_Card!$B$2,Raw_Q!$C$2:$C$600,$A26,Raw_Q!$D$2:$D$600,4))) -> 14.45 | F26: =IF(Stock_Card!$B$2="","",IF(COUNTIFS(Raw_Q!$A$2:$A$600,Stock_Card!$B$2,Raw_Q!$C$2:$C$600,$A26)<4,"未滿4季",SUM(B26:E26))) -> 45.26 | G26: =IFERROR(IF(OR(NOT(ISNUMBER(F26)),NOT(ISNUMBER(F25))),"",F26/F25-1),"") -> 0.39950526
A27: =IF(Stock_Card!$B$2="","",IFERROR($Z$1-1,"")) -> 2025 | B27: =IF(Stock_Card!$B$2="","",IF(COUNTIFS(Raw_Q!$A$2:$A$600,Stock_Card!$B$2,Raw_Q!$C$2:$C$600,$A27,Raw_Q!$D$2:$D$600,1)=0,"",SUMIFS(Raw_Q!$L$2:$L$600,Raw_Q!$A$2:$A$600,Stock_Card!$B$2,Raw_Q!$C$2:$C$600,$A27,Raw_Q!$D$2:$D$600,1))) -> 13.95 | C27: =IF(Stock_Card!$B$2="","",IF(COUNTIFS(Raw_Q!$A$2:$A$600,Stock_Card!$B$2,Raw_Q!$C$2:$C$600,$A27,Raw_Q!$D$2:$D$600,2)=0,"",SUMIFS(Raw_Q!$L$2:$L$600,Raw_Q!$A$2:$A$600,Stock_Card!$B$2,Raw_Q!$C$2:$C$600,$A27,Raw_Q!$D$2:$D$600,2))) -> 15.36 | D27: =IF(Stock_Card!$B$2="","",IF(COUNTIFS(Raw_Q!$A$2:$A$600,Stock_Card!$B$2,Raw_Q!$C$2:$C$600,$A27,Raw_Q!$D$2:$D$600,3)=0,"",SUMIFS(Raw_Q!$L$2:$L$600,Raw_Q!$A$2:$A$600,Stock_Card!$B$2,Raw_Q!$C$2:$C$600,$A27,Raw_Q!$D$2:$D$600,3))) -> 17.44 | E27: =IF(Stock_Card!$B$2="","",IF(COUNTIFS(Raw_Q!$A$2:$A$600,Stock_Card!$B$2,Raw_Q!$C$2:$C$600,$A27,Raw_Q!$D$2:$D$600,4)=0,"",SUMIFS(Raw_Q!$L$2:$L$600,Raw_Q!$A$2:$A$600,Stock_Card!$B$2,Raw_Q!$C$2:$C$600,$A27,Raw_Q!$D$2:$D$600,4))) -> 19.51 | F27: =IF(Stock_Card!$B$2="","",IF(COUNTIFS(Raw_Q!$A$2:$A$600,Stock_Card!$B$2,Raw_Q!$C$2:$C$600,$A27)<4,"未滿4季",SUM(B27:E27))) -> 66.26 | G27: =IFERROR(IF(OR(NOT(ISNUMBER(F27)),NOT(ISNUMBER(F26))),"",F27/F26-1),"") -> 0.46398586
A28: =IF(Stock_Card!$B$2="","",IFERROR($Z$1-0,"")) -> 2026 | B28: =IF(Stock_Card!$B$2="","",IF(COUNTIFS(Raw_Q!$A$2:$A$600,Stock_Card!$B$2,Raw_Q!$C$2:$C$600,$A28,Raw_Q!$D$2:$D$600,1)=0,"",SUMIFS(Raw_Q!$L$2:$L$600,Raw_Q!$A$2:$A$600,Stock_Card!$B$2,Raw_Q!$C$2:$C$600,$A28,Raw_Q!$D$2:$D$600,1))) -> 22.08 | C28: =IF(Stock_Card!$B$2="","",IF(COUNTIFS(Raw_Q!$A$2:$A$600,Stock_Card!$B$2,Raw_Q!$C$2:$C$600,$A28,Raw_Q!$D$2:$D$600,2)=0,"",SUMIFS(Raw_Q!$L$2:$L$600,Raw_Q!$A$2:$A$600,Stock_Card!$B$2,Raw_Q!$C$2:$C$600,$A28,Raw_Q!$D$2:$D$600,2))) -> 27.25 | D28: =IF(Stock_Card!$B$2="","",IF(COUNTIFS(Raw_Q!$A$2:$A$600,Stock_Card!$B$2,Raw_Q!$C$2:$C$600,$A28,Raw_Q!$D$2:$D$600,3)=0,"",SUMIFS(Raw_Q!$L$2:$L$600,Raw_Q!$A$2:$A$600,Stock_Card!$B$2,Raw_Q!$C$2:$C$600,$A28,Raw_Q!$D$2:$D$600,3))) -> 28.19147 | E28: =IF(Stock_Card!$B$2="","",IF(COUNTIFS(Raw_Q!$A$2:$A$600,Stock_Card!$B$2,Raw_Q!$C$2:$C$600,$A28,Raw_Q!$D$2:$D$600,4)=0,"",SUMIFS(Raw_Q!$L$2:$L$600,Raw_Q!$A$2:$A$600,Stock_Card!$B$2,Raw_Q!$C$2:$C$600,$A28,Raw_Q!$D$2:$D$600,4))) | F28: =IF(Stock_Card!$B$2="","",IF(COUNTIFS(Raw_Q!$A$2:$A$600,Stock_Card!$B$2,Raw_Q!$C$2:$C$600,$A28)<4,"未滿4季",SUM(B28:E28))) -> 未滿4季 | G28: =IFERROR(IF(OR(NOT(ISNUMBER(F28)),NOT(ISNUMBER(F27))),"",F28/F27-1),"")
A30: ↓ 這張就是「每季營收成長率」，季節可比。
A31: 營收 YoY 成長率 · 年 × 季矩陣
A32: 財年 | B32: Q1 | C32: Q2 | D32: Q3 | E32: Q4
A33: =IF(Stock_Card!$B$2="","",IFERROR($Z$1-4,"")) -> 2022 | B33: =IF(Stock_Card!$B$2="","",IF(COUNTIFS(Raw_Q!$A$2:$A$600,Stock_Card!$B$2,Raw_Q!$C$2:$C$600,$A33,Raw_Q!$D$2:$D$600,1)=0,"",IFERROR(SUMIFS(Raw_Q!$I$2:$I$600,Raw_Q!$A$2:$A$600,Stock_Card!$B$2,Raw_Q!$C$2:$C$600,$A33,Raw_Q!$D$2:$D$600,1)/SUMIFS(Raw_Q!$I$2:$I$600,Raw_Q!$A$2:$A$600,Stock_Card!$B$2,Raw_Q!$C$2:$C$600,$A33-1,Raw_Q!$D$2:$D$600,1)-1,""))) -> 0.35502762 | C33: =IF(Stock_Card!$B$2="","",IF(COUNTIFS(Raw_Q!$A$2:$A$600,Stock_Card!$B$2,Raw_Q!$C$2:$C$600,$A33,Raw_Q!$D$2:$D$600,2)=0,"",IFERROR(SUMIFS(Raw_Q!$I$2:$I$600,Raw_Q!$A$2:$A$600,Stock_Card!$B$2,Raw_Q!$C$2:$C$600,$A33,Raw_Q!$D$2:$D$600,2)/SUMIFS(Raw_Q!$I$2:$I$600,Raw_Q!$A$2:$A$600,Stock_Card!$B$2,Raw_Q!$C$2:$C$600,$A33-1,Raw_Q!$D$2:$D$600,2)-1,""))) -> 0.43530246 | D33: =IF(Stock_Card!$B$2="","",IF(COUNTIFS(Raw_Q!$A$2:$A$600,Stock_Card!$B$2,Raw_Q!$C$2:$C$600,$A33,Raw_Q!$D$2:$D$600,3)=0,"",IFERROR(SUMIFS(Raw_Q!$I$2:$I$600,Raw_Q!$A$2:$A$600,Stock_Card!$B$2,Raw_Q!$C$2:$C$600,$A33,Raw_Q!$D$2:$D$600,3)/SUMIFS(Raw_Q!$I$2:$I$600,Raw_Q!$A$2:$A$600,Stock_Card!$B$2,Raw_Q!$C$2:$C$600,$A33-1,Raw_Q!$D$2:$D$600,3)-1,""))) -> 0.47862682 | E33: =IF(Stock_Card!$B$2="","",IF(COUNTIFS(Raw_Q!$A$2:$A$600,Stock_Card!$B$2,Raw_Q!$C$2:$C$600,$A33,Raw_Q!$D$2:$D$600,4)=0,"",IFERROR(SUMIFS(Raw_Q!$I$2:$I$600,Raw_Q!$A$2:$A$600,Stock_Card!$B$2,Raw_Q!$C$2:$C$600,$A33,Raw_Q!$D$2:$D$600,4)/SUMIFS(Raw_Q!$I$2:$I$600,Raw_Q!$A$2:$A$600,Stock_Card!$B$2,Raw_Q!$C$2:$C$600,$A33-1,Raw_Q!$D$2:$D$600,4)-1,""))) -> 0.42753796
A34: =IF(Stock_Card!$B$2="","",IFERROR($Z$1-3,"")) -> 2023 | B34: =IF(Stock_Card!$B$2="","",IF(COUNTIFS(Raw_Q!$A$2:$A$600,Stock_Card!$B$2,Raw_Q!$C$2:$C$600,$A34,Raw_Q!$D$2:$D$600,1)=0,"",IFERROR(SUMIFS(Raw_Q!$I$2:$I$600,Raw_Q!$A$2:$A$600,Stock_Card!$B$2,Raw_Q!$C$2:$C$600,$A34,Raw_Q!$D$2:$D$600,1)/SUMIFS(Raw_Q!$I$2:$I$600,Raw_Q!$A$2:$A$600,Stock_Card!$B$2,Raw_Q!$C$2:$C$600,$A34-1,Raw_Q!$D$2:$D$600,1)-1,""))) -> 0.035752316 | C34: =IF(Stock_Card!$B$2="","",IF(COUNTIFS(Raw_Q!$A$2:$A$600,Stock_Card!$B$2,Raw_Q!$C$2:$C$600,$A34,Raw_Q!$D$2:$D$600,2)=0,"",IFERROR(SUMIFS(Raw_Q!$I$2:$I$600,Raw_Q!$A$2:$A$600,Stock_Card!$B$2,Raw_Q!$C$2:$C$600,$A34,Raw_Q!$D$2:$D$600,2)/SUMIFS(Raw_Q!$I$2:$I$600,Raw_Q!$A$2:$A$600,Stock_Card!$B$2,Raw_Q!$C$2:$C$600,$A34-1,Raw_Q!$D$2:$D$600,2)-1,""))) -> -0.099785587 | D34: =IF(Stock_Card!$B$2="","",IF(COUNTIFS(Raw_Q!$A$2:$A$600,Stock_Card!$B$2,Raw_Q!$C$2:$C$600,$A34,Raw_Q!$D$2:$D$600,3)=0,"",IFERROR(SUMIFS(Raw_Q!$I$2:$I$600,Raw_Q!$A$2:$A$600,Stock_Card!$B$2,Raw_Q!$C$2:$C$600,$A34,Raw_Q!$D$2:$D$600,3)/SUMIFS(Raw_Q!$I$2:$I$600,Raw_Q!$A$2:$A$600,Stock_Card!$B$2,Raw_Q!$C$2:$C$600,$A34-1,Raw_Q!$D$2:$D$600,3)-1,""))) -> -0.10831081 | E34: =IF(Stock_Card!$B$2="","",IF(COUNTIFS(Raw_Q!$A$2:$A$600,Stock_Card!$B$2,Raw_Q!$C$2:$C$600,$A34,Raw_Q!$D$2:$D$600,4)=0,"",IFERROR(SUMIFS(Raw_Q!$I$2:$I$600,Raw_Q!$A$2:$A$600,Stock_Card!$B$2,Raw_Q!$C$2:$C$600,$A34,Raw_Q!$D$2:$D$600,4)/SUMIFS(Raw_Q!$I$2:$I$600,Raw_Q!$A$2:$A$600,Stock_Card!$B$2,Raw_Q!$C$2:$C$600,$A34-1,Raw_Q!$D$2:$D$600,4)-1,""))) -> -4.8151024e-06
A35: =IF(Stock_Card!$B$2="","",IFERROR($Z$1-2,"")) -> 2024 | B35: =IF(Stock_Card!$B$2="","",IF(COUNTIFS(Raw_Q!$A$2:$A$600,Stock_Card!$B$2,Raw_Q!$C$2:$C$600,$A35,Raw_Q!$D$2:$D$600,1)=0,"",IFERROR(SUMIFS(Raw_Q!$I$2:$I$600,Raw_Q!$A$2:$A$600,Stock_Card!$B$2,Raw_Q!$C$2:$C$600,$A35,Raw_Q!$D$2:$D$600,1)/SUMIFS(Raw_Q!$I$2:$I$600,Raw_Q!$A$2:$A$600,Stock_Card!$B$2,Raw_Q!$C$2:$C$600,$A35-1,Raw_Q!$D$2:$D$600,1)-1,""))) -> 0.16517063 | C35: =IF(Stock_Card!$B$2="","",IF(COUNTIFS(Raw_Q!$A$2:$A$600,Stock_Card!$B$2,Raw_Q!$C$2:$C$600,$A35,Raw_Q!$D$2:$D$600,2)=0,"",IFERROR(SUMIFS(Raw_Q!$I$2:$I$600,Raw_Q!$A$2:$A$600,Stock_Card!$B$2,Raw_Q!$C$2:$C$600,$A35,Raw_Q!$D$2:$D$600,2)/SUMIFS(Raw_Q!$I$2:$I$600,Raw_Q!$A$2:$A$600,Stock_Card!$B$2,Raw_Q!$C$2:$C$600,$A35-1,Raw_Q!$D$2:$D$600,2)-1,""))) -> 0.40069133 | D35: =IF(Stock_Card!$B$2="","",IF(COUNTIFS(Raw_Q!$A$2:$A$600,Stock_Card!$B$2,Raw_Q!$C$2:$C$600,$A35,Raw_Q!$D$2:$D$600,3)=0,"",IFERROR(SUMIFS(Raw_Q!$I$2:$I$600,Raw_Q!$A$2:$A$600,Stock_Card!$B$2,Raw_Q!$C$2:$C$600,$A35,Raw_Q!$D$2:$D$600,3)/SUMIFS(Raw_Q!$I$2:$I$600,Raw_Q!$A$2:$A$600,Stock_Card!$B$2,Raw_Q!$C$2:$C$600,$A35-1,Raw_Q!$D$2:$D$600,3)-1,""))) -> 0.38951276 | E35: =IF(Stock_Card!$B$2="","",IF(COUNTIFS(Raw_Q!$A$2:$A$600,Stock_Card!$B$2,Raw_Q!$C$2:$C$600,$A35,Raw_Q!$D$2:$D$600,4)=0,"",IFERROR(SUMIFS(Raw_Q!$I$2:$I$600,Raw_Q!$A$2:$A$600,Stock_Card!$B$2,Raw_Q!$C$2:$C$600,$A35,Raw_Q!$D$2:$D$600,4)/SUMIFS(Raw_Q!$I$2:$I$600,Raw_Q!$A$2:$A$600,Stock_Card!$B$2,Raw_Q!$C$2:$C$600,$A35-1,Raw_Q!$D$2:$D$600,4)-1,""))) -> 0.38836309
A36: =IF(Stock_Card!$B$2="","",IFERROR($Z$1-1,"")) -> 2025 | B36: =IF(Stock_Card!$B$2="","",IF(COUNTIFS(Raw_Q!$A$2:$A$600,Stock_Card!$B$2,Raw_Q!$C$2:$C$600,$A36,Raw_Q!$D$2:$D$600,1)=0,"",IFERROR(SUMIFS(Raw_Q!$I$2:$I$600,Raw_Q!$A$2:$A$600,Stock_Card!$B$2,Raw_Q!$C$2:$C$600,$A36,Raw_Q!$D$2:$D$600,1)/SUMIFS(Raw_Q!$I$2:$I$600,Raw_Q!$A$2:$A$600,Stock_Card!$B$2,Raw_Q!$C$2:$C$600,$A36-1,Raw_Q!$D$2:$D$600,1)-1,""))) -> 0.41611723 | C36: =IF(Stock_Card!$B$2="","",IF(COUNTIFS(Raw_Q!$A$2:$A$600,Stock_Card!$B$2,Raw_Q!$C$2:$C$600,$A36,Raw_Q!$D$2:$D$600,2)=0,"",IFERROR(SUMIFS(Raw_Q!$I$2:$I$600,Raw_Q!$A$2:$A$600,Stock_Card!$B$2,Raw_Q!$C$2:$C$600,$A36,Raw_Q!$D$2:$D$600,2)/SUMIFS(Raw_Q!$I$2:$I$600,Raw_Q!$A$2:$A$600,Stock_Card!$B$2,Raw_Q!$C$2:$C$600,$A36-1,Raw_Q!$D$2:$D$600,2)-1,""))) -> 0.38645547 | D36: =IF(Stock_Card!$B$2="","",IF(COUNTIFS(Raw_Q!$A$2:$A$600,Stock_Card!$B$2,Raw_Q!$C$2:$C$600,$A36,Raw_Q!$D$2:$D$600,3)=0,"",IFERROR(SUMIFS(Raw_Q!$I$2:$I$600,Raw_Q!$A$2:$A$600,Stock_Card!$B$2,Raw_Q!$C$2:$C$600,$A36,Raw_Q!$D$2:$D$600,3)/SUMIFS(Raw_Q!$I$2:$I$600,Raw_Q!$A$2:$A$600,Stock_Card!$B$2,Raw_Q!$C$2:$C$600,$A36-1,Raw_Q!$D$2:$D$600,3)-1,""))) -> 0.30305194 | E36: =IF(Stock_Card!$B$2="","",IF(COUNTIFS(Raw_Q!$A$2:$A$600,Stock_Card!$B$2,Raw_Q!$C$2:$C$600,$A36,Raw_Q!$D$2:$D$600,4)=0,"",IFERROR(SUMIFS(Raw_Q!$I$2:$I$600,Raw_Q!$A$2:$A$600,Stock_Card!$B$2,Raw_Q!$C$2:$C$600,$A36,Raw_Q!$D$2:$D$600,4)/SUMIFS(Raw_Q!$I$2:$I$600,Raw_Q!$A$2:$A$600,Stock_Card!$B$2,Raw_Q!$C$2:$C$600,$A36-1,Raw_Q!$D$2:$D$600,4)-1,""))) -> 0.20453331
A37: =IF(Stock_Card!$B$2="","",IFERROR($Z$1-0,"")) -> 2026 | B37: =IF(Stock_Card!$B$2="","",IF(COUNTIFS(Raw_Q!$A$2:$A$600,Stock_Card!$B$2,Raw_Q!$C$2:$C$600,$A37,Raw_Q!$D$2:$D$600,1)=0,"",IFERROR(SUMIFS(Raw_Q!$I$2:$I$600,Raw_Q!$A$2:$A$600,Stock_Card!$B$2,Raw_Q!$C$2:$C$600,$A37,Raw_Q!$D$2:$D$600,1)/SUMIFS(Raw_Q!$I$2:$I$600,Raw_Q!$A$2:$A$600,Stock_Card!$B$2,Raw_Q!$C$2:$C$600,$A37-1,Raw_Q!$D$2:$D$600,1)-1,""))) -> 0.35132379 | C37: =IF(Stock_Card!$B$2="","",IF(COUNTIFS(Raw_Q!$A$2:$A$600,Stock_Card!$B$2,Raw_Q!$C$2:$C$600,$A37,Raw_Q!$D$2:$D$600,2)=0,"",IFERROR(SUMIFS(Raw_Q!$I$2:$I$600,Raw_Q!$A$2:$A$600,Stock_Card!$B$2,Raw_Q!$C$2:$C$600,$A37,Raw_Q!$D$2:$D$600,2)/SUMIFS(Raw_Q!$I$2:$I$600,Raw_Q!$A$2:$A$600,Stock_Card!$B$2,Raw_Q!$C$2:$C$600,$A37-1,Raw_Q!$D$2:$D$600,2)-1,""))) -> 0.36045332 | D37: =IF(Stock_Card!$B$2="","",IF(COUNTIFS(Raw_Q!$A$2:$A$600,Stock_Card!$B$2,Raw_Q!$C$2:$C$600,$A37,Raw_Q!$D$2:$D$600,3)=0,"",IFERROR(SUMIFS(Raw_Q!$I$2:$I$600,Raw_Q!$A$2:$A$600,Stock_Card!$B$2,Raw_Q!$C$2:$C$600,$A37,Raw_Q!$D$2:$D$600,3)/SUMIFS(Raw_Q!$I$2:$I$600,Raw_Q!$A$2:$A$600,Stock_Card!$B$2,Raw_Q!$C$2:$C$600,$A37-1,Raw_Q!$D$2:$D$600,3)-1,""))) -> -1 | E37: =IF(Stock_Card!$B$2="","",IF(COUNTIFS(Raw_Q!$A$2:$A$600,Stock_Card!$B$2,Raw_Q!$C$2:$C$600,$A37,Raw_Q!$D$2:$D$600,4)=0,"",IFERROR(SUMIFS(Raw_Q!$I$2:$I$600,Raw_Q!$A$2:$A$600,Stock_Card!$B$2,Raw_Q!$C$2:$C$600,$A37,Raw_Q!$D$2:$D$600,4)/SUMIFS(Raw_Q!$I$2:$I$600,Raw_Q!$A$2:$A$600,Stock_Card!$B$2,Raw_Q!$C$2:$C$600,$A37-1,Raw_Q!$D$2:$D$600,4)-1,"")))

Sheet 月營收檢視
A1: 月營收檢視 · 近 18 個月
A2: 股票 | B2: =Stock_Card!$B$2 -> 2330 | C2: ← 與 Stock_Card 同步。台股每月 10 日前公布上月營收，比季報早兩三個月透露轉折。
A4: 月份 | B4: 月營收(百萬元) | C4: 月增率 | D4: 月增加速度(pp) | E4: 月增加速度(%) | F4: 年增率 | G4: 年增加速度(pp) | H4: 年增加速度(%) | I4: 動能判讀 | J4: 累計(百萬元) | K4: 累計年增率
A5: =IF(Stock_Card!$B$2="","",IFERROR(INDEX(Raw_M!$B$2:$B$2000,MATCH(Stock_Card!$B$2&"|1",Raw_M!$G$2:$G$2000,0)),"")) -> 2026-10 | B5: =IF(Stock_Card!$B$2="","",IFERROR(SUMIFS(Raw_M!$E$2:$E$2000,Raw_M!$A$2:$A$2000,Stock_Card!$B$2,Raw_M!$F$2:$F$2000,1),"")) -> 511857.4 | C5: =IF(Stock_Card!$B$2="","",IFERROR((SUMIFS(Raw_M!$E$2:$E$2000,Raw_M!$A$2:$A$2000,Stock_Card!$B$2,Raw_M!$F$2:$F$2000,1)/SUMIFS(Raw_M!$E$2:$E$2000,Raw_M!$A$2:$A$2000,Stock_Card!$B$2,Raw_M!$F$2:$F$2000,2)-1),"")) -> -0.0057263159 | D5: =IF(Stock_Card!$B$2="","",IFERROR(((SUMIFS(Raw_M!$E$2:$E$2000,Raw_M!$A$2:$A$2000,Stock_Card!$B$2,Raw_M!$F$2:$F$2000,1)/SUMIFS(Raw_M!$E$2:$E$2000,Raw_M!$A$2:$A$2000,Stock_Card!$B$2,Raw_M!$F$2:$F$2000,2)-1)-(SUMIFS(Raw_M!$E$2:$E$2000,Raw_M!$A$2:$A$2000,Stock_Card!$B$2,Raw_M!$F$2:$F$2000,2)/SUMIFS(Raw_M!$E$2:$E$2000,Raw_M!$A$2:$A$2000,Stock_Card!$B$2,Raw_M!$F$2:$F$2000,3)-1))*100,"")) -> -10.672451 | E5: =IF(Stock_Card!$B$2="","",IFERROR(IF(OR(NOT(ISNUMBER((SUMIFS(Raw_M!$E$2:$E$2000,Raw_M!$A$2:$A$2000,Stock_Card!$B$2,Raw_M!$F$2:$F$2000,2)/SUMIFS(Raw_M!$E$2:$E$2000,Raw_M!$A$2:$A$2000,Stock_Card!$B$2,Raw_M!$F$2:$F$2000,3)-1))),(SUMIFS(Raw_M!$E$2:$E$2000,Raw_M!$A$2:$A$2000,Stock_Card!$B$2,Raw_M!$F$2:$F$2000,2)/SUMIFS(Raw_M!$E$2:$E$2000,Raw_M!$A$2:$A$2000,Stock_Card!$B$2,Raw_M!$F$2:$F$2000,3)-1)<=0,ABS((SUMIFS(Raw_M!$E$2:$E$2000,Raw_M!$A$2:$A$2000,Stock_Card!$B$2,Raw_M!$F$2:$F$2000,2)/SUMIFS(Raw_M!$E$2:$E$2000,Raw_M!$A$2:$A$2000,Stock_Card!$B$2,Raw_M!$F$2:$F$2000,3)-1))<Config!$B$9),"N/M",((SUMIFS(Raw_M!$E$2:$E$2000,Raw_M!$A$2:$A$2000,Stock_Card!$B$2,Raw_M!$F$2:$F$2000,1)/SUMIFS(Raw_M!$E$2:$E$2000,Raw_M!$A$2:$A$2000,Stock_Card!$B$2,Raw_M!$F$2:$F$2000,2)-1)-(SUMIFS(Raw_M!$E$2:$E$2000,Raw_M!$A$2:$A$2000,Stock_Card!$B$2,Raw_M!$F$2:$F$2000,2)/SUMIFS(Raw_M!$E$2:$E$2000,Raw_M!$A$2:$A$2000,Stock_Card!$B$2,Raw_M!$F$2:$F$2000,3)-1))/ABS((SUMIFS(Raw_M!$E$2:$E$2000,Raw_M!$A$2:$A$2000,Stock_Card!$B$2,Raw_M!$F$2:$F$2000,2)/SUMIFS(Raw_M!$E$2:$E$2000,Raw_M!$A$2:$A$2000,Stock_Card!$B$2,Raw_M!$F$2:$F$2000,3)-1))),"N/M")) -> -1.0566972 | F5: =IF(Stock_Card!$B$2="","",IFERROR((SUMIFS(Raw_M!$E$2:$E$2000,Raw_M!$A$2:$A$2000,Stock_Card!$B$2,Raw_M!$F$2:$F$2000,1)/SUMIFS(Raw_M!$E$2:$E$2000,Raw_M!$A$2:$A$2000,Stock_Card!$B$2,Raw_M!$F$2:$F$2000,13)-1),"")) -> 0.54648612 | G5: =IF(Stock_Card!$B$2="","",IFERROR(((SUMIFS(Raw_M!$E$2:$E$2000,Raw_M!$A$2:$A$2000,Stock_Card!$B$2,Raw_M!$F$2:$F$2000,1)/SUMIFS(Raw_M!$E$2:$E$2000,Raw_M!$A$2:$A$2000,Stock_Card!$B$2,Raw_M!$F$2:$F$2000,13)-1)-(SUMIFS(Raw_M!$E$2:$E$2000,Raw_M!$A$2:$A$2000,Stock_Card!$B$2,Raw_M!$F$2:$F$2000,2)/SUMIFS(Raw_M!$E$2:$E$2000,Raw_M!$A$2:$A$2000,Stock_Card!$B$2,Raw_M!$F$2:$F$2000,14)-1))*100,"")) -> 1.3285584 | H5: =IF(Stock_Card!$B$2="","",IFERROR(IF(OR(NOT(ISNUMBER((SUMIFS(Raw_M!$E$2:$E$2000,Raw_M!$A$2:$A$2000,Stock_Card!$B$2,Raw_M!$F$2:$F$2000,2)/SUMIFS(Raw_M!$E$2:$E$2000,Raw_M!$A$2:$A$2000,Stock_Card!$B$2,Raw_M!$F$2:$F$2000,14)-1))),(SUMIFS(Raw_M!$E$2:$E$2000,Raw_M!$A$2:$A$2000,Stock_Card!$B$2,Raw_M!$F$2:$F$2000,2)/SUMIFS(Raw_M!$E$2:$E$2000,Raw_M!$A$2:$A$2000,Stock_Card!$B$2,Raw_M!$F$2:$F$2000,14)-1)<=0,ABS((SUMIFS(Raw_M!$E$2:$E$2000,Raw_M!$A$2:$A$2000,Stock_Card!$B$2,Raw_M!$F$2:$F$2000,2)/SUMIFS(Raw_M!$E$2:$E$2000,Raw_M!$A$2:$A$2000,Stock_Card!$B$2,Raw_M!$F$2:$F$2000,14)-1))<Config!$B$9),"N/M",((SUMIFS(Raw_M!$E$2:$E$2000,Raw_M!$A$2:$A$2000,Stock_Card!$B$2,Raw_M!$F$2:$F$2000,1)/SUMIFS(Raw_M!$E$2:$E$2000,Raw_M!$A$2:$A$2000,Stock_Card!$B$2,Raw_M!$F$2:$F$2000,13)-1)-(SUMIFS(Raw_M!$E$2:$E$2000,Raw_M!$A$2:$A$2000,Stock_Card!$B$2,Raw_M!$F$2:$F$2000,2)/SUMIFS(Raw_M!$E$2:$E$2000,Raw_M!$A$2:$A$2000,Stock_Card!$B$2,Raw_M!$F$2:$F$2000,14)-1))/ABS((SUMIFS(Raw_M!$E$2:$E$2000,Raw_M!$A$2:$A$2000,Stock_Card!$B$2,Raw_M!$F$2:$F$2000,2)/SUMIFS(Raw_M!$E$2:$E$2000,Raw_M!$A$2:$A$2000,Stock_Card!$B$2,Raw_M!$F$2:$F$2000,14)-1))),"N/M")) -> 0.024916673 | I5: =IF(Stock_Card!$B$2="","",IFERROR(IF(AND((SUMIFS(Raw_M!$E$2:$E$2000,Raw_M!$A$2:$A$2000,Stock_Card!$B$2,Raw_M!$F$2:$F$2000,2)/SUMIFS(Raw_M!$E$2:$E$2000,Raw_M!$A$2:$A$2000,Stock_Card!$B$2,Raw_M!$F$2:$F$2000,14)-1)>0,(SUMIFS(Raw_M!$E$2:$E$2000,Raw_M!$A$2:$A$2000,Stock_Card!$B$2,Raw_M!$F$2:$F$2000,1)/SUMIFS(Raw_M!$E$2:$E$2000,Raw_M!$A$2:$A$2000,Stock_Card!$B$2,Raw_M!$F$2:$F$2000,13)-1)<=0),"由正轉負",IF(AND((SUMIFS(Raw_M!$E$2:$E$2000,Raw_M!$A$2:$A$2000,Stock_Card!$B$2,Raw_M!$F$2:$F$2000,2)/SUMIFS(Raw_M!$E$2:$E$2000,Raw_M!$A$2:$A$2000,Stock_Card!$B$2,Raw_M!$F$2:$F$2000,14)-1)<=0,(SUMIFS(Raw_M!$E$2:$E$2000,Raw_M!$A$2:$A$2000,Stock_Card!$B$2,Raw_M!$F$2:$F$2000,1)/SUMIFS(Raw_M!$E$2:$E$2000,Raw_M!$A$2:$A$2000,Stock_Card!$B$2,Raw_M!$F$2:$F$2000,13)-1)>0),"由負轉正",IF((SUMIFS(Raw_M!$E$2:$E$2000,Raw_M!$A$2:$A$2000,Stock_Card!$B$2,Raw_M!$F$2:$F$2000,1)/SUMIFS(Raw_M!$E$2:$E$2000,Raw_M!$A$2:$A$2000,Stock_Card!$B$2,Raw_M!$F$2:$F$2000,13)-1)>0,IF(((SUMIFS(Raw_M!$E$2:$E$2000,Raw_M!$A$2:$A$2000,Stock_Card!$B$2,Raw_M!$F$2:$F$2000,1)/SUMIFS(Raw_M!$E$2:$E$2000,Raw_M!$A$2:$A$2000,Stock_Card!$B$2,Raw_M!$F$2:$F$2000,13)-1)-(SUMIFS(Raw_M!$E$2:$E$2000,Raw_M!$A$2:$A$2000,Stock_Card!$B$2,Raw_M!$F$2:$F$2000,2)/SUMIFS(Raw_M!$E$2:$E$2000,Raw_M!$A$2:$A$2000,Stock_Card!$B$2,Raw_M!$F$2:$F$2000,14)-1))*100>0,"成長且加速","成長但減速"),IF(((SUMIFS(Raw_M!$E$2:$E$2000,Raw_M!$A$2:$A$2000,Stock_Card!$B$2,Raw_M!$F$2:$F$2000,1)/SUMIFS(Raw_M!$E$2:$E$2000,Raw_M!$A$2:$A$2000,Stock_Card!$B$2,Raw_M!$F$2:$F$2000,13)-1)-(SUMIFS(Raw_M!$E$2:$E$2000,Raw_M!$A$2:$A$2000,Stock_Card!$B$2,Raw_M!$F$2:$F$2000,2)/SUMIFS(Raw_M!$E$2:$E$2000,Raw_M!$A$2:$A$2000,Stock_Card!$B$2,Raw_M!$F$2:$F$2000,14)-1))*100>0,"衰退但收斂","衰退且惡化")))),"")) -> 成長且加速 | J5: =IF(Stock_Card!$B$2="","",IFERROR(SUMIFS(Raw_M!$E$2:$E$2000,Raw_M!$A$2:$A$2000,Stock_Card!$B$2,Raw_M!$C$2:$C$2000,">="&((INT(SUMIFS(Raw_M!$C$2:$C$2000,Raw_M!$A$2:$A$2000,Stock_Card!$B$2,Raw_M!$F$2:$F$2000,1)/100)-0)*100+1),Raw_M!$C$2:$C$2000,"<="&((INT(SUMIFS(Raw_M!$C$2:$C$2000,Raw_M!$A$2:$A$2000,Stock_Card!$B$2,Raw_M!$F$2:$F$2000,1)/100)-0)*100+MOD(SUMIFS(Raw_M!$C$2:$C$2000,Raw_M!$A$2:$A$2000,Stock_Card!$B$2,Raw_M!$F$2:$F$2000,1),100))),"")) -> 4233730.5 | K5: =IF(Stock_Card!$B$2="","",IFERROR(IF(OR(COUNTIFS(Raw_M!$A$2:$A$2000,Stock_Card!$B$2,Raw_M!$C$2:$C$2000,">="&((INT(SUMIFS(Raw_M!$C$2:$C$2000,Raw_M!$A$2:$A$2000,Stock_Card!$B$2,Raw_M!$F$2:$F$2000,1)/100)-0)*100+1),Raw_M!$C$2:$C$2000,"<="&((INT(SUMIFS(Raw_M!$C$2:$C$2000,Raw_M!$A$2:$A$2000,Stock_Card!$B$2,Raw_M!$F$2:$F$2000,1)/100)-0)*100+MOD(SUMIFS(Raw_M!$C$2:$C$2000,Raw_M!$A$2:$A$2000,Stock_Card!$B$2,Raw_M!$F$2:$F$2000,1),100)))<>MOD(SUMIFS(Raw_M!$C$2:$C$2000,Raw_M!$A$2:$A$2000,Stock_Card!$B$2,Raw_M!$F$2:$F$2000,1),100),COUNTIFS(Raw_M!$A$2:$A$2000,Stock_Card!$B$2,Raw_M!$C$2:$C$2000,">="&((INT(SUMIFS(Raw_M!$C$2:$C$2000,Raw_M!$A$2:$A$2000,Stock_Card!$B$2,Raw_M!$F$2:$F$2000,1)/100)-1)*100+1),Raw_M!$C$2:$C$2000,"<="&((INT(SUMIFS(Raw_M!$C$2:$C$2000,Raw_M!$A$2:$A$2000,Stock_Card!$B$2,Raw_M!$F$2:$F$2000,1)/100)-1)*100+MOD(SUMIFS(Raw_M!$C$2:$C$2000,Raw_M!$A$2:$A$2000,Stock_Card!$B$2,Raw_M!$F$2:$F$2000,1),100)))<>MOD(SUMIFS(Raw_M!$C$2:$C$2000,Raw_M!$A$2:$A$2000,Stock_Card!$B$2,Raw_M!$F$2:$F$2000,1),100)),"N/M",SUMIFS(Raw_M!$E$2:$E$2000,Raw_M!$A$2:$A$2000,Stock_Card!$B$2,Raw_M!$C$2:$C$2000,">="&((INT(SUMIFS(Raw_M!$C$2:$C$2000,Raw_M!$A$2:$A$2000,Stock_Card!$B$2,Raw_M!$F$2:$F$2000,1)/100)-0)*100+1),Raw_M!$C$2:$C$2000,"<="&((INT(SUMIFS(Raw_M!$C$2:$C$2000,Raw_M!$A$2:$A$2000,Stock_Card!$B$2,Raw_M!$F$2:$F$2000,1)/100)-0)*100+MOD(SUMIFS(Raw_M!$C$2:$C$2000,Raw_M!$A$2:$A$2000,Stock_Card!$B$2,Raw_M!$F$2:$F$2000,1),100)))/SUMIFS(Raw_M!$E$2:$E$2000,Raw_M!$A$2:$A$2000,Stock_Card!$B$2,Raw_M!$C$2:$C$2000,">="&((INT(SUMIFS(Raw_M!$C$2:$C$2000,Raw_M!$A$2:$A$2000,Stock_Card!$B$2,Raw_M!$F$2:$F$2000,1)/100)-1)*100+1),Raw_M!$C$2:$C$2000,"<="&((INT(SUMIFS(Raw_M!$C$2:$C$2000,Raw_M!$A$2:$A$2000,Stock_Card!$B$2,Raw_M!$F$2:$F$2000,1)/100)-1)*100+MOD(SUMIFS(Raw_M!$C$2:$C$2000,Raw_M!$A$2:$A$2000,Stock_Card!$B$2,Raw_M!$F$2:$F$2000,1),100)))-1),"N/M")) -> 0.39215843
A6: =IF(Stock_Card!$B$2="","",IFERROR(INDEX(Raw_M!$B$2:$B$2000,MATCH(Stock_Card!$B$2&"|2",Raw_M!$G$2:$G$2000,0)),"")) -> 2026-09 | B6: =IF(Stock_Card!$B$2="","",IFERROR(SUMIFS(Raw_M!$E$2:$E$2000,Raw_M!$A$2:$A$2000,Stock_Card!$B$2,Raw_M!$F$2:$F$2000,2),"")) -> 514805.34 | C6: =IF(Stock_Card!$B$2="","",IFERROR((SUMIFS(Raw_M!$E$2:$E$2000,Raw_M!$A$2:$A$2000,Stock_Card!$B$2,Raw_M!$F$2:$F$2000,2)/SUMIFS(Raw_M!$E$2:$E$2000,Raw_M!$A$2:$A$2000,Stock_Card!$B$2,Raw_M!$F$2:$F$2000,3)-1),"")) -> 0.10099819 | D6: =IF(Stock_Card!$B$2="","",IFERROR(((SUMIFS(Raw_M!$E$2:$E$2000,Raw_M!$A$2:$A$2000,Stock_Card!$B$2,Raw_M!$F$2:$F$2000,2)/SUMIFS(Raw_M!$E$2:$E$2000,Raw_M!$A$2:$A$2000,Stock_Card!$B$2,Raw_M!$F$2:$F$2000,3)-1)-(SUMIFS(Raw_M!$E$2:$E$2000,Raw_M!$A$2:$A$2000,Stock_Card!$B$2,Raw_M!$F$2:$F$2000,3)/SUMIFS(Raw_M!$E$2:$E$2000,Raw_M!$A$2:$A$2000,Stock_Card!$B$2,Raw_M!$F$2:$F$2000,4)-1))*100,"")) -> 4.4748572 | E6: =IF(Stock_Card!$B$2="","",IFERROR(IF(OR(NOT(ISNUMBER((SUMIFS(Raw_M!$E$2:$E$2000,Raw_M!$A$2:$A$2000,Stock_Card!$B$2,Raw_M!$F$2:$F$2000,3)/SUMIFS(Raw_M!$E$2:$E$2000,Raw_M!$A$2:$A$2000,Stock_Card!$B$2,Raw_M!$F$2:$F$2000,4)-1))),(SUMIFS(Raw_M!$E$2:$E$2000,Raw_M!$A$2:$A$2000,Stock_Card!$B$2,Raw_M!$F$2:$F$2000,3)/SUMIFS(Raw_M!$E$2:$E$2000,Raw_M!$A$2:$A$2000,Stock_Card!$B$2,Raw_M!$F$2:$F$2000,4)-1)<=0,ABS((SUMIFS(Raw_M!$E$2:$E$2000,Raw_M!$A$2:$A$2000,Stock_Card!$B$2,Raw_M!$F$2:$F$2000,3)/SUMIFS(Raw_M!$E$2:$E$2000,Raw_M!$A$2:$A$2000,Stock_Card!$B$2,Raw_M!$F$2:$F$2000,4)-1))<Config!$B$9),"N/M",((SUMIFS(Raw_M!$E$2:$E$2000,Raw_M!$A$2:$A$2000,Stock_Card!$B$2,Raw_M!$F$2:$F$2000,2)/SUMIFS(Raw_M!$E$2:$E$2000,Raw_M!$A$2:$A$2000,Stock_Card!$B$2,Raw_M!$F$2:$F$2000,3)-1)-(SUMIFS(Raw_M!$E$2:$E$2000,Raw_M!$A$2:$A$2000,Stock_Card!$B$2,Raw_M!$F$2:$F$2000,3)/SUMIFS(Raw_M!$E$2:$E$2000,Raw_M!$A$2:$A$2000,Stock_Card!$B$2,Raw_M!$F$2:$F$2000,4)-1))/ABS((SUMIFS(Raw_M!$E$2:$E$2000,Raw_M!$A$2:$A$2000,Stock_Card!$B$2,Raw_M!$F$2:$F$2000,3)/SUMIFS(Raw_M!$E$2:$E$2000,Raw_M!$A$2:$A$2000,Stock_Card!$B$2,Raw_M!$F$2:$F$2000,4)-1))),"N/M")) -> 0.79553558 | F6: =IF(Stock_Card!$B$2="","",IFERROR((SUMIFS(Raw_M!$E$2:$E$2000,Raw_M!$A$2:$A$2000,Stock_Card!$B$2,Raw_M!$F$2:$F$2000,2)/SUMIFS(Raw_M!$E$2:$E$2000,Raw_M!$A$2:$A$2000,Stock_Card!$B$2,Raw_M!$F$2:$F$2000,14)-1),"")) -> 0.53320054 | G6: =IF(Stock_Card!$B$2="","",IFERROR(((SUMIFS(Raw_M!$E$2:$E$2000,Raw_M!$A$2:$A$2000,Stock_Card!$B$2,Raw_M!$F$2:$F$2000,2)/SUMIFS(Raw_M!$E$2:$E$2000,Raw_M!$A$2:$A$2000,Stock_Card!$B$2,Raw_M!$F$2:$F$2000,14)-1)-(SUMIFS(Raw_M!$E$2:$E$2000,Raw_M!$A$2:$A$2000,Stock_Card!$B$2,Raw_M!$F$2:$F$2000,3)/SUMIFS(Raw_M!$E$2:$E$2000,Raw_M!$A$2:$A$2000,Stock_Card!$B$2,Raw_M!$F$2:$F$2000,15)-1))*100,"")) -> 8.6325024 | H6: =IF(Stock_Card!$B$2="","",IFERROR(IF(OR(NOT(ISNUMBER((SUMIFS(Raw_M!$E$2:$E$2000,Raw_M!$A$2:$A$2000,Stock_Card!$B$2,Raw_M!$F$2:$F$2000,3)/SUMIFS(Raw_M!$E$2:$E$2000,Raw_M!$A$2:$A$2000,Stock_Card!$B$2,Raw_M!$F$2:$F$2000,15)-1))),(SUMIFS(Raw_M!$E$2:$E$2000,Raw_M!$A$2:$A$2000,Stock_Card!$B$2,Raw_M!$F$2:$F$2000,3)/SUMIFS(Raw_M!$E$2:$E$2000,Raw_M!$A$2:$A$2000,Stock_Card!$B$2,Raw_M!$F$2:$F$2000,15)-1)<=0,ABS((SUMIFS(Raw_M!$E$2:$E$2000,Raw_M!$A$2:$A$2000,Stock_Card!$B$2,Raw_M!$F$2:$F$2000,3)/SUMIFS(Raw_M!$E$2:$E$2000,Raw_M!$A$2:$A$2000,Stock_Card!$B$2,Raw_M!$F$2:$F$2000,15)-1))<Config!$B$9),"N/M",((SUMIFS(Raw_M!$E$2:$E$2000,Raw_M!$A$2:$A$2000,Stock_Card!$B$2,Raw_M!$F$2:$F$2000,2)/SUMIFS(Raw_M!$E$2:$E$2000,Raw_M!$A$2:$A$2000,Stock_Card!$B$2,Raw_M!$F$2:$F$2000,14)-1)-(SUMIFS(Raw_M!$E$2:$E$2000,Raw_M!$A$2:$A$2000,Stock_Card!$B$2,Raw_M!$F$2:$F$2000,3)/SUMIFS(Raw_M!$E$2:$E$2000,Raw_M!$A$2:$A$2000,Stock_Card!$B$2,Raw_M!$F$2:$F$2000,15)-1))/ABS((SUMIFS(Raw_M!$E$2:$E$2000,Raw_M!$A$2:$A$2000,Stock_Card!$B$2,Raw_M!$F$2:$F$2000,3)/SUMIFS(Raw_M!$E$2:$E$2000,Raw_M!$A$2:$A$2000,Stock_Card!$B$2,Raw_M!$F$2:$F$2000,15)-1))),"N/M")) -> 0.19317466 | I6: =IF(Stock_Card!$B$2="","",IFERROR(IF(AND((SUMIFS(Raw_M!$E$2:$E$2000,Raw_M!$A$2:$A$2000,Stock_Card!$B$2,Raw_M!$F$2:$F$2000,3)/SUMIFS(Raw_M!$E$2:$E$2000,Raw_M!$A$2:$A$2000,Stock_Card!$B$2,Raw_M!$F$2:$F$2000,15)-1)>0,(SUMIFS(Raw_M!$E$2:$E$2000,Raw_M!$A$2:$A$2000,Stock_Card!$B$2,Raw_M!$F$2:$F$2000,2)/SUMIFS(Raw_M!$E$2:$E$2000,Raw_M!$A$2:$A$2000,Stock_Card!$B$2,Raw_M!$F$2:$F$2000,14)-1)<=0),"由正轉負",IF(AND((SUMIFS(Raw_M!$E$2:$E$2000,Raw_M!$A$2:$A$2000,Stock_Card!$B$2,Raw_M!$F$2:$F$2000,3)/SUMIFS(Raw_M!$E$2:$E$2000,Raw_M!$A$2:$A$2000,Stock_Card!$B$2,Raw_M!$F$2:$F$2000,15)-1)<=0,(SUMIFS(Raw_M!$E$2:$E$2000,Raw_M!$A$2:$A$2000,Stock_Card!$B$2,Raw_M!$F$2:$F$2000,2)/SUMIFS(Raw_M!$E$2:$E$2000,Raw_M!$A$2:$A$2000,Stock_Card!$B$2,Raw_M!$F$2:$F$2000,14)-1)>0),"由負轉正",IF((SUMIFS(Raw_M!$E$2:$E$2000,Raw_M!$A$2:$A$2000,Stock_Card!$B$2,Raw_M!$F$2:$F$2000,2)/SUMIFS(Raw_M!$E$2:$E$2000,Raw_M!$A$2:$A$2000,Stock_Card!$B$2,Raw_M!$F$2:$F$2000,14)-1)>0,IF(((SUMIFS(Raw_M!$E$2:$E$2000,Raw_M!$A$2:$A$2000,Stock_Card!$B$2,Raw_M!$F$2:$F$2000,2)/SUMIFS(Raw_M!$E$2:$E$2000,Raw_M!$A$2:$A$2000,Stock_Card!$B$2,Raw_M!$F$2:$F$2000,14)-1)-(SUMIFS(Raw_M!$E$2:$E$2000,Raw_M!$A$2:$A$2000,Stock_Card!$B$2,Raw_M!$F$2:$F$2000,3)/SUMIFS(Raw_M!$E$2:$E$2000,Raw_M!$A$2:$A$2000,Stock_Card!$B$2,Raw_M!$F$2:$F$2000,15)-1))*100>0,"成長且加速","成長但減速"),IF(((SUMIFS(Raw_M!$E$2:$E$2000,Raw_M!$A$2:$A$2000,Stock_Card!$B$2,Raw_M!$F$2:$F$2000,2)/SUMIFS(Raw_M!$E$2:$E$2000,Raw_M!$A$2:$A$2000,Stock_Card!$B$2,Raw_M!$F$2:$F$2000,14)-1)-(SUMIFS(Raw_M!$E$2:$E$2000,Raw_M!$A$2:$A$2000,Stock_Card!$B$2,Raw_M!$F$2:$F$2000,3)/SUMIFS(Raw_M!$E$2:$E$2000,Raw_M!$A$2:$A$2000,Stock_Card!$B$2,Raw_M!$F$2:$F$2000,15)-1))*100>0,"衰退但收斂","衰退且惡化")))),"")) -> 成長且加速 | J6: =IF(Stock_Card!$B$2="","",IFERROR(SUMIFS(Raw_M!$E$2:$E$2000,Raw_M!$A$2:$A$2000,Stock_Card!$B$2,Raw_M!$C$2:$C$2000,">="&((INT(SUMIFS(Raw_M!$C$2:$C$2000,Raw_M!$A$2:$A$2000,Stock_Card!$B$2,Raw_M!$F$2:$F$2000,2)/100)-0)*100+1),Raw_M!$C$2:$C$2000,"<="&((INT(SUMIFS(Raw_M!$C$2:$C$2000,Raw_M!$A$2:$A$2000,Stock_Card!$B$2,Raw_M!$F$2:$F$2000,2)/100)-0)*100+MOD(SUMIFS(Raw_M!$C$2:$C$2000,Raw_M!$A$2:$A$2000,Stock_Card!$B$2,Raw_M!$F$2:$F$2000,2),100))),"")) -> 3721873.1 | K6: =IF(Stock_Card!$B$2="","",IFERROR(IF(OR(COUNTIFS(Raw_M!$A$2:$A$2000,Stock_Card!$B$2,Raw_M!$C$2:$C$2000,">="&((INT(SUMIFS(Raw_M!$C$2:$C$2000,Raw_M!$A$2:$A$2000,Stock_Card!$B$2,Raw_M!$F$2:$F$2000,2)/100)-0)*100+1),Raw_M!$C$2:$C$2000,"<="&((INT(SUMIFS(Raw_M!$C$2:$C$2000,Raw_M!$A$2:$A$2000,Stock_Card!$B$2,Raw_M!$F$2:$F$2000,2)/100)-0)*100+MOD(SUMIFS(Raw_M!$C$2:$C$2000,Raw_M!$A$2:$A$2000,Stock_Card!$B$2,Raw_M!$F$2:$F$2000,2),100)))<>MOD(SUMIFS(Raw_M!$C$2:$C$2000,Raw_M!$A$2:$A$2000,Stock_Card!$B$2,Raw_M!$F$2:$F$2000,2),100),COUNTIFS(Raw_M!$A$2:$A$2000,Stock_Card!$B$2,Raw_M!$C$2:$C$2000,">="&((INT(SUMIFS(Raw_M!$C$2:$C$2000,Raw_M!$A$2:$A$2000,Stock_Card!$B$2,Raw_M!$F$2:$F$2000,2)/100)-1)*100+1),Raw_M!$C$2:$C$2000,"<="&((INT(SUMIFS(Raw_M!$C$2:$C$2000,Raw_M!$A$2:$A$2000,Stock_Card!$B$2,Raw_M!$F$2:$F$2000,2)/100)-1)*100+MOD(SUMIFS(Raw_M!$C$2:$C$2000,Raw_M!$A$2:$A$2000,Stock_Card!$B$2,Raw_M!$F$2:$F$2000,2),100)))<>MOD(SUMIFS(Raw_M!$C$2:$C$2000,Raw_M!$A$2:$A$2000,Stock_Card!$B$2,Raw_M!$F$2:$F$2000,2),100)),"N/M",SUMIFS(Raw_M!$E$2:$E$2000,Raw_M!$A$2:$A$2000,Stock_Card!$B$2,Raw_M!$C$2:$C$2000,">="&((INT(SUMIFS(Raw_M!$C$2:$C$2000,Raw_M!$A$2:$A$2000,Stock_Card!$B$2,Raw_M!$F$2:$F$2000,2)/100)-0)*100+1),Raw_M!$C$2:$C$2000,"<="&((INT(SUMIFS(Raw_M!$C$2:$C$2000,Raw_M!$A$2:$A$2000,Stock_Card!$B$2,Raw_M!$F$2:$F$2000,2)/100)-0)*100+MOD(SUMIFS(Raw_M!$C$2:$C$2000,Raw_M!$A$2:$A$2000,Stock_Card!$B$2,Raw_M!$F$2:$F$2000,2),100)))/SUMIFS(Raw_M!$E$2:$E$2000,Raw_M!$A$2:$A$2000,Stock_Card!$B$2,Raw_M!$C$2:$C$2000,">="&((INT(SUMIFS(Raw_M!$C$2:$C$2000,Raw_M!$A$2:$A$2000,Stock_Card!$B$2,Raw_M!$F$2:$F$2000,2)/100)-1)*100+1),Raw_M!$C$2:$C$2000,"<="&((INT(SUMIFS(Raw_M!$C$2:$C$2000,Raw_M!$A$2:$A$2000,Stock_Card!$B$2,Raw_M!$F$2:$F$2000,2)/100)-1)*100+MOD(SUMIFS(Raw_M!$C$2:$C$2000,Raw_M!$A$2:$A$2000,Stock_Card!$B$2,Raw_M!$F$2:$F$2000,2),100)))-1),"N/M")) -> 0.37331092
A7: =IF(Stock_Card!$B$2="","",IFERROR(INDEX(Raw_M!$B$2:$B$2000,MATCH(Stock_Card!$B$2&"|3",Raw_M!$G$2:$G$2000,0)),"")) -> 2026-08 | B7: =IF(Stock_Card!$B$2="","",IFERROR(SUMIFS(Raw_M!$E$2:$E$2000,Raw_M!$A$2:$A$2000,Stock_Card!$B$2,Raw_M!$F$2:$F$2000,3),"")) -> 467580.55 | C7: =IF(Stock_Card!$B$2="","",IFERROR((SUMIFS(Raw_M!$E$2:$E$2000,Raw_M!$A$2:$A$2000,Stock_Card!$B$2,Raw_M!$F$2:$F$2000,3)/SUMIFS(Raw_M!$E$2:$E$2000,Raw_M!$A$2:$A$2000,Stock_Card!$B$2,Raw_M!$F$2:$F$2000,4)-1),"")) -> 0.056249618 | D7: =IF(Stock_Card!$B$2="","",IFERROR(((SUMIFS(Raw_M!$E$2:$E$2000,Raw_M!$A$2:$A$2000,Stock_Card!$B$2,Raw_M!$F$2:$F$2000,3)/SUMIFS(Raw_M!$E$2:$E$2000,Raw_M!$A$2:$A$2000,Stock_Card!$B$2,Raw_M!$F$2:$F$2000,4)-1)-(SUMIFS(Raw_M!$E$2:$E$2000,Raw_M!$A$2:$A$2000,Stock_Card!$B$2,Raw_M!$F$2:$F$2000,4)/SUMIFS(Raw_M!$E$2:$E$2000,Raw_M!$A$2:$A$2000,Stock_Card!$B$2,Raw_M!$F$2:$F$2000,5)-1))*100,"")) -> -0.53962747 | E7: =IF(Stock_Card!$B$2="","",IFERROR(IF(OR(NOT(ISNUMBER((SUMIFS(Raw_M!$E$2:$E$2000,Raw_M!$A$2:$A$2000,Stock_Card!$B$2,Raw_M!$F$2:$F$2000,4)/SUMIFS(Raw_M!$E$2:$E$2000,Raw_M!$A$2:$A$2000,Stock_Card!$B$2,Raw_M!$F$2:$F$2000,5)-1))),(SUMIFS(Raw_M!$E$2:$E$2000,Raw_M!$A$2:$A$2000,Stock_Card!$B$2,Raw_M!$F$2:$F$2000,4)/SUMIFS(Raw_M!$E$2:$E$2000,Raw_M!$A$2:$A$2000,Stock_Card!$B$2,Raw_M!$F$2:$F$2000,5)-1)<=0,ABS((SUMIFS(Raw_M!$E$2:$E$2000,Raw_M!$A$2:$A$2000,Stock_Card!$B$2,Raw_M!$F$2:$F$2000,4)/SUMIFS(Raw_M!$E$2:$E$2000,Raw_M!$A$2:$A$2000,Stock_Card!$B$2,Raw_M!$F$2:$F$2000,5)-1))<Config!$B$9),"N/M",((SUMIFS(Raw_M!$E$2:$E$2000,Raw_M!$A$2:$A$2000,Stock_Card!$B$2,Raw_M!$F$2:$F$2000,3)/SUMIFS(Raw_M!$E$2:$E$2000,Raw_M!$A$2:$A$2000,Stock_Card!$B$2,Raw_M!$F$2:$F$2000,4)-1)-(SUMIFS(Raw_M!$E$2:$E$2000,Raw_M!$A$2:$A$2000,Stock_Card!$B$2,Raw_M!$F$2:$F$2000,4)/SUMIFS(Raw_M!$E$2:$E$2000,Raw_M!$A$2:$A$2000,Stock_Card!$B$2,Raw_M!$F$2:$F$2000,5)-1))/ABS((SUMIFS(Raw_M!$E$2:$E$2000,Raw_M!$A$2:$A$2000,Stock_Card!$B$2,Raw_M!$F$2:$F$2000,4)/SUMIFS(Raw_M!$E$2:$E$2000,Raw_M!$A$2:$A$2000,Stock_Card!$B$2,Raw_M!$F$2:$F$2000,5)-1))),"N/M")) -> -0.087536646 | F7: =IF(Stock_Card!$B$2="","",IFERROR((SUMIFS(Raw_M!$E$2:$E$2000,Raw_M!$A$2:$A$2000,Stock_Card!$B$2,Raw_M!$F$2:$F$2000,3)/SUMIFS(Raw_M!$E$2:$E$2000,Raw_M!$A$2:$A$2000,Stock_Card!$B$2,Raw_M!$F$2:$F$2000,15)-1),"")) -> 0.44687551 | G7: =IF(Stock_Card!$B$2="","",IFERROR(((SUMIFS(Raw_M!$E$2:$E$2000,Raw_M!$A$2:$A$2000,Stock_Card!$B$2,Raw_M!$F$2:$F$2000,3)/SUMIFS(Raw_M!$E$2:$E$2000,Raw_M!$A$2:$A$2000,Stock_Card!$B$2,Raw_M!$F$2:$F$2000,15)-1)-(SUMIFS(Raw_M!$E$2:$E$2000,Raw_M!$A$2:$A$2000,Stock_Card!$B$2,Raw_M!$F$2:$F$2000,4)/SUMIFS(Raw_M!$E$2:$E$2000,Raw_M!$A$2:$A$2000,Stock_Card!$B$2,Raw_M!$F$2:$F$2000,16)-1))*100,"")) -> -23.179304 | H7: =IF(Stock_Card!$B$2="","",IFERROR(IF(OR(NOT(ISNUMBER((SUMIFS(Raw_M!$E$2:$E$2000,Raw_M!$A$2:$A$2000,Stock_Card!$B$2,Raw_M!$F$2:$F$2000,4)/SUMIFS(Raw_M!$E$2:$E$2000,Raw_M!$A$2:$A$2000,Stock_Card!$B$2,Raw_M!$F$2:$F$2000,16)-1))),(SUMIFS(Raw_M!$E$2:$E$2000,Raw_M!$A$2:$A$2000,Stock_Card!$B$2,Raw_M!$F$2:$F$2000,4)/SUMIFS(Raw_M!$E$2:$E$2000,Raw_M!$A$2:$A$2000,Stock_Card!$B$2,Raw_M!$F$2:$F$2000,16)-1)<=0,ABS((SUMIFS(Raw_M!$E$2:$E$2000,Raw_M!$A$2:$A$2000,Stock_Card!$B$2,Raw_M!$F$2:$F$2000,4)/SUMIFS(Raw_M!$E$2:$E$2000,Raw_M!$A$2:$A$2000,Stock_Card!$B$2,Raw_M!$F$2:$F$2000,16)-1))<Config!$B$9),"N/M",((SUMIFS(Raw_M!$E$2:$E$2000,Raw_M!$A$2:$A$2000,Stock_Card!$B$2,Raw_M!$F$2:$F$2000,3)/SUMIFS(Raw_M!$E$2:$E$2000,Raw_M!$A$2:$A$2000,Stock_Card!$B$2,Raw_M!$F$2:$F$2000,15)-1)-(SUMIFS(Raw_M!$E$2:$E$2000,Raw_M!$A$2:$A$2000,Stock_Card!$B$2,Raw_M!$F$2:$F$2000,4)/SUMIFS(Raw_M!$E$2:$E$2000,Raw_M!$A$2:$A$2000,Stock_Card!$B$2,Raw_M!$F$2:$F$2000,16)-1))/ABS((SUMIFS(Raw_M!$E$2:$E$2000,Raw_M!$A$2:$A$2000,Stock_Card!$B$2,Raw_M!$F$2:$F$2000,4)/SUMIFS(Raw_M!$E$2:$E$2000,Raw_M!$A$2:$A$2000,Stock_Card!$B$2,Raw_M!$F$2:$F$2000,16)-1))),"N/M")) -> -0.34154086 | I7: =IF(Stock_Card!$B$2="","",IFERROR(IF(AND((SUMIFS(Raw_M!$E$2:$E$2000,Raw_M!$A$2:$A$2000,Stock_Card!$B$2,Raw_M!$F$2:$F$2000,4)/SUMIFS(Raw_M!$E$2:$E$2000,Raw_M!$A$2:$A$2000,Stock_Card!$B$2,Raw_M!$F$2:$F$2000,16)-1)>0,(SUMIFS(Raw_M!$E$2:$E$2000,Raw_M!$A$2:$A$2000,Stock_Card!$B$2,Raw_M!$F$2:$F$2000,3)/SUMIFS(Raw_M!$E$2:$E$2000,Raw_M!$A$2:$A$2000,Stock_Card!$B$2,Raw_M!$F$2:$F$2000,15)-1)<=0),"由正轉負",IF(AND((SUMIFS(Raw_M!$E$2:$E$2000,Raw_M!$A$2:$A$2000,Stock_Card!$B$2,Raw_M!$F$2:$F$2000,4)/SUMIFS(Raw_M!$E$2:$E$2000,Raw_M!$A$2:$A$2000,Stock_Card!$B$2,Raw_M!$F$2:$F$2000,16)-1)<=0,(SUMIFS(Raw_M!$E$2:$E$2000,Raw_M!$A$2:$A$2000,Stock_Card!$B$2,Raw_M!$F$2:$F$2000,3)/SUMIFS(Raw_M!$E$2:$E$2000,Raw_M!$A$2:$A$2000,Stock_Card!$B$2,Raw_M!$F$2:$F$2000,15)-1)>0),"由負轉正",IF((SUMIFS(Raw_M!$E$2:$E$2000,Raw_M!$A$2:$A$2000,Stock_Card!$B$2,Raw_M!$F$2:$F$2000,3)/SUMIFS(Raw_M!$E$2:$E$2000,Raw_M!$A$2:$A$2000,Stock_Card!$B$2,Raw_M!$F$2:$F$2000,15)-1)>0,IF(((SUMIFS(Raw_M!$E$2:$E$2000,Raw_M!$A$2:$A$2000,Stock_Card!$B$2,Raw_M!$F$2:$F$2000,3)/SUMIFS(Raw_M!$E$2:$E$2000,Raw_M!$A$2:$A$2000,Stock_Card!$B$2,Raw_M!$F$2:$F$2000,15)-1)-(SUMIFS(Raw_M!$E$2:$E$2000,Raw_M!$A$2:$A$2000,Stock_Card!$B$2,Raw_M!$F$2:$F$2000,4)/SUMIFS(Raw_M!$E$2:$E$2000,Raw_M!$A$2:$A$2000,Stock_Card!$B$2,Raw_M!$F$2:$F$2000,16)-1))*100>0,"成長且加速","成長但減速"),IF(((SUMIFS(Raw_M!$E$2:$E$2000,Raw_M!$A$2:$A$2000,Stock_Card!$B$2,Raw_M!$F$2:$F$2000,3)/SUMIFS(Raw_M!$E$2:$E$2000,Raw_M!$A$2:$A$2000,Stock_Card!$B$2,Raw_M!$F$2:$F$2000,15)-1)-(SUMIFS(Raw_M!$E$2:$E$2000,Raw_M!$A$2:$A$2000,Stock_Card!$B$2,Raw_M!$F$2:$F$2000,4)/SUMIFS(Raw_M!$E$2:$E$2000,Raw_M!$A$2:$A$2000,Stock_Card!$B$2,Raw_M!$F$2:$F$2000,16)-1))*100>0,"衰退但收斂","衰退且惡化")))),"")) -> 成長但減速 | J7: =IF(Stock_Card!$B$2="","",IFERROR(SUMIFS(Raw_M!$E$2:$E$2000,Raw_M!$A$2:$A$2000,Stock_Card!$B$2,Raw_M!$C$2:$C$2000,">="&((INT(SUMIFS(Raw_M!$C$2:$C$2000,Raw_M!$A$2:$A$2000,Stock_Card!$B$2,Raw_M!$F$2:$F$2000,3)/100)-0)*100+1),Raw_M!$C$2:$C$2000,"<="&((INT(SUMIFS(Raw_M!$C$2:$C$2000,Raw_M!$A$2:$A$2000,Stock_Card!$B$2,Raw_M!$F$2:$F$2000,3)/100)-0)*100+MOD(SUMIFS(Raw_M!$C$2:$C$2000,Raw_M!$A$2:$A$2000,Stock_Card!$B$2,Raw_M!$F$2:$F$2000,3),100))),"")) -> 3207067.8 | K7: =IF(Stock_Card!$B$2="","",IFERROR(IF(OR(COUNTIFS(Raw_M!$A$2:$A$2000,Stock_Card!$B$2,Raw_M!$C$2:$C$2000,">="&((INT(SUMIFS(Raw_M!$C$2:$C$2000,Raw_M!$A$2:$A$2000,Stock_Card!$B$2,Raw_M!$F$2:$F$2000,3)/100)-0)*100+1),Raw_M!$C$2:$C$2000,"<="&((INT(SUMIFS(Raw_M!$C$2:$C$2000,Raw_M!$A$2:$A$2000,Stock_Card!$B$2,Raw_M!$F$2:$F$2000,3)/100)-0)*100+MOD(SUMIFS(Raw_M!$C$2:$C$2000,Raw_M!$A$2:$A$2000,Stock_Card!$B$2,Raw_M!$F$2:$F$2000,3),100)))<>MOD(SUMIFS(Raw_M!$C$2:$C$2000,Raw_M!$A$2:$A$2000,Stock_Card!$B$2,Raw_M!$F$2:$F$2000,3),100),COUNTIFS(Raw_M!$A$2:$A$2000,Stock_Card!$B$2,Raw_M!$C$2:$C$2000,">="&((INT(SUMIFS(Raw_M!$C$2:$C$2000,Raw_M!$A$2:$A$2000,Stock_Card!$B$2,Raw_M!$F$2:$F$2000,3)/100)-1)*100+1),Raw_M!$C$2:$C$2000,"<="&((INT(SUMIFS(Raw_M!$C$2:$C$2000,Raw_M!$A$2:$A$2000,Stock_Card!$B$2,Raw_M!$F$2:$F$2000,3)/100)-1)*100+MOD(SUMIFS(Raw_M!$C$2:$C$2000,Raw_M!$A$2:$A$2000,Stock_Card!$B$2,Raw_M!$F$2:$F$2000,3),100)))<>MOD(SUMIFS(Raw_M!$C$2:$C$2000,Raw_M!$A$2:$A$2000,Stock_Card!$B$2,Raw_M!$F$2:$F$2000,3),100)),"N/M",SUMIFS(Raw_M!$E$2:$E$2000,Raw_M!$A$2:$A$2000,Stock_Card!$B$2,Raw_M!$C$2:$C$2000,">="&((INT(SUMIFS(Raw_M!$C$2:$C$2000,Raw_M!$A$2:$A$2000,Stock_Card!$B$2,Raw_M!$F$2:$F$2000,3)/100)-0)*100+1),Raw_M!$C$2:$C$2000,"<="&((INT(SUMIFS(Raw_M!$C$2:$C$2000,Raw_M!$A$2:$A$2000,Stock_Card!$B$2,Raw_M!$F$2:$F$2000,3)/100)-0)*100+MOD(SUMIFS(Raw_M!$C$2:$C$2000,Raw_M!$A$2:$A$2000,Stock_Card!$B$2,Raw_M!$F$2:$F$2000,3),100)))/SUMIFS(Raw_M!$E$2:$E$2000,Raw_M!$A$2:$A$2000,Stock_Card!$B$2,Raw_M!$C$2:$C$2000,">="&((INT(SUMIFS(Raw_M!$C$2:$C$2000,Raw_M!$A$2:$A$2000,Stock_Card!$B$2,Raw_M!$F$2:$F$2000,3)/100)-1)*100+1),Raw_M!$C$2:$C$2000,"<="&((INT(SUMIFS(Raw_M!$C$2:$C$2000,Raw_M!$A$2:$A$2000,Stock_Card!$B$2,Raw_M!$F$2:$F$2000,3)/100)-1)*100+MOD(SUMIFS(Raw_M!$C$2:$C$2000,Raw_M!$A$2:$A$2000,Stock_Card!$B$2,Raw_M!$F$2:$F$2000,3),100)))-1),"N/M")) -> 0.35070016
A8: =IF(Stock_Card!$B$2="","",IFERROR(INDEX(Raw_M!$B$2:$B$2000,MATCH(Stock_Card!$B$2&"|4",Raw_M!$G$2:$G$2000,0)),"")) -> 2026-07 | B8: =IF(Stock_Card!$B$2="","",IFERROR(SUMIFS(Raw_M!$E$2:$E$2000,Raw_M!$A$2:$A$2000,Stock_Card!$B$2,Raw_M!$F$2:$F$2000,4),"")) -> 442679.97 | C8: =IF(Stock_Card!$B$2="","",IFERROR((SUMIFS(Raw_M!$E$2:$E$2000,Raw_M!$A$2:$A$2000,Stock_Card!$B$2,Raw_M!$F$2:$F$2000,4)/SUMIFS(Raw_M!$E$2:$E$2000,Raw_M!$A$2:$A$2000,Stock_Card!$B$2,Raw_M!$F$2:$F$2000,5)-1),"")) -> 0.061645892 | D8: =IF(Stock_Card!$B$2="","",IFERROR(((SUMIFS(Raw_M!$E$2:$E$2000,Raw_M!$A$2:$A$2000,Stock_Card!$B$2,Raw_M!$F$2:$F$2000,4)/SUMIFS(Raw_M!$E$2:$E$2000,Raw_M!$A$2:$A$2000,Stock_Card!$B$2,Raw_M!$F$2:$F$2000,5)-1)-(SUMIFS(Raw_M!$E$2:$E$2000,Raw_M!$A$2:$A$2000,Stock_Card!$B$2,Raw_M!$F$2:$F$2000,5)/SUMIFS(Raw_M!$E$2:$E$2000,Raw_M!$A$2:$A$2000,Stock_Card!$B$2,Raw_M!$F$2:$F$2000,6)-1))*100,"")) -> 4.6428793 | E8: =IF(Stock_Card!$B$2="","",IFERROR(IF(OR(NOT(ISNUMBER((SUMIFS(Raw_M!$E$2:$E$2000,Raw_M!$A$2:$A$2000,Stock_Card!$B$2,Raw_M!$F$2:$F$2000,5)/SUMIFS(Raw_M!$E$2:$E$2000,Raw_M!$A$2:$A$2000,Stock_Card!$B$2,Raw_M!$F$2:$F$2000,6)-1))),(SUMIFS(Raw_M!$E$2:$E$2000,Raw_M!$A$2:$A$2000,Stock_Card!$B$2,Raw_M!$F$2:$F$2000,5)/SUMIFS(Raw_M!$E$2:$E$2000,Raw_M!$A$2:$A$2000,Stock_Card!$B$2,Raw_M!$F$2:$F$2000,6)-1)<=0,ABS((SUMIFS(Raw_M!$E$2:$E$2000,Raw_M!$A$2:$A$2000,Stock_Card!$B$2,Raw_M!$F$2:$F$2000,5)/SUMIFS(Raw_M!$E$2:$E$2000,Raw_M!$A$2:$A$2000,Stock_Card!$B$2,Raw_M!$F$2:$F$2000,6)-1))<Config!$B$9),"N/M",((SUMIFS(Raw_M!$E$2:$E$2000,Raw_M!$A$2:$A$2000,Stock_Card!$B$2,Raw_M!$F$2:$F$2000,4)/SUMIFS(Raw_M!$E$2:$E$2000,Raw_M!$A$2:$A$2000,Stock_Card!$B$2,Raw_M!$F$2:$F$2000,5)-1)-(SUMIFS(Raw_M!$E$2:$E$2000,Raw_M!$A$2:$A$2000,Stock_Card!$B$2,Raw_M!$F$2:$F$2000,5)/SUMIFS(Raw_M!$E$2:$E$2000,Raw_M!$A$2:$A$2000,Stock_Card!$B$2,Raw_M!$F$2:$F$2000,6)-1))/ABS((SUMIFS(Raw_M!$E$2:$E$2000,Raw_M!$A$2:$A$2000,Stock_Card!$B$2,Raw_M!$F$2:$F$2000,5)/SUMIFS(Raw_M!$E$2:$E$2000,Raw_M!$A$2:$A$2000,Stock_Card!$B$2,Raw_M!$F$2:$F$2000,6)-1))),"N/M")) -> N/M | F8: =IF(Stock_Card!$B$2="","",IFERROR((SUMIFS(Raw_M!$E$2:$E$2000,Raw_M!$A$2:$A$2000,Stock_Card!$B$2,Raw_M!$F$2:$F$2000,4)/SUMIFS(Raw_M!$E$2:$E$2000,Raw_M!$A$2:$A$2000,Stock_Card!$B$2,Raw_M!$F$2:$F$2000,16)-1),"")) -> 0.67866855 | G8: =IF(Stock_Card!$B$2="","",IFERROR(((SUMIFS(Raw_M!$E$2:$E$2000,Raw_M!$A$2:$A$2000,Stock_Card!$B$2,Raw_M!$F$2:$F$2000,4)/SUMIFS(Raw_M!$E$2:$E$2000,Raw_M!$A$2:$A$2000,Stock_Card!$B$2,Raw_M!$F$2:$F$2000,16)-1)-(SUMIFS(Raw_M!$E$2:$E$2000,Raw_M!$A$2:$A$2000,Stock_Card!$B$2,Raw_M!$F$2:$F$2000,5)/SUMIFS(Raw_M!$E$2:$E$2000,Raw_M!$A$2:$A$2000,Stock_Card!$B$2,Raw_M!$F$2:$F$2000,17)-1))*100,"")) -> 37.771875 | H8: =IF(Stock_Card!$B$2="","",IFERROR(IF(OR(NOT(ISNUMBER((SUMIFS(Raw_M!$E$2:$E$2000,Raw_M!$A$2:$A$2000,Stock_Card!$B$2,Raw_M!$F$2:$F$2000,5)/SUMIFS(Raw_M!$E$2:$E$2000,Raw_M!$A$2:$A$2000,Stock_Card!$B$2,Raw_M!$F$2:$F$2000,17)-1))),(SUMIFS(Raw_M!$E$2:$E$2000,Raw_M!$A$2:$A$2000,Stock_Card!$B$2,Raw_M!$F$2:$F$2000,5)/SUMIFS(Raw_M!$E$2:$E$2000,Raw_M!$A$2:$A$2000,Stock_Card!$B$2,Raw_M!$F$2:$F$2000,17)-1)<=0,ABS((SUMIFS(Raw_M!$E$2:$E$2000,Raw_M!$A$2:$A$2000,Stock_Card!$B$2,Raw_M!$F$2:$F$2000,5)/SUMIFS(Raw_M!$E$2:$E$2000,Raw_M!$A$2:$A$2000,Stock_Card!$B$2,Raw_M!$F$2:$F$2000,17)-1))<Config!$B$9),"N/M",((SUMIFS(Raw_M!$E$2:$E$2000,Raw_M!$A$2:$A$2000,Stock_Card!$B$2,Raw_M!$F$2:$F$2000,4)/SUMIFS(Raw_M!$E$2:$E$2000,Raw_M!$A$2:$A$2000,Stock_Card!$B$2,Raw_M!$F$2:$F$2000,16)-1)-(SUMIFS(Raw_M!$E$2:$E$2000,Raw_M!$A$2:$A$2000,Stock_Card!$B$2,Raw_M!$F$2:$F$2000,5)/SUMIFS(Raw_M!$E$2:$E$2000,Raw_M!$A$2:$A$2000,Stock_Card!$B$2,Raw_M!$F$2:$F$2000,17)-1))/ABS((SUMIFS(Raw_M!$E$2:$E$2000,Raw_M!$A$2:$A$2000,Stock_Card!$B$2,Raw_M!$F$2:$F$2000,5)/SUMIFS(Raw_M!$E$2:$E$2000,Raw_M!$A$2:$A$2000,Stock_Card!$B$2,Raw_M!$F$2:$F$2000,17)-1))),"N/M")) -> 1.2550889 | I8: =IF(Stock_Card!$B$2="","",IFERROR(IF(AND((SUMIFS(Raw_M!$E$2:$E$2000,Raw_M!$A$2:$A$2000,Stock_Card!$B$2,Raw_M!$F$2:$F$2000,5)/SUMIFS(Raw_M!$E$2:$E$2000,Raw_M!$A$2:$A$2000,Stock_Card!$B$2,Raw_M!$F$2:$F$2000,17)-1)>0,(SUMIFS(Raw_M!$E$2:$E$2000,Raw_M!$A$2:$A$2000,Stock_Card!$B$2,Raw_M!$F$2:$F$2000,4)/SUMIFS(Raw_M!$E$2:$E$2000,Raw_M!$A$2:$A$2000,Stock_Card!$B$2,Raw_M!$F$2:$F$2000,16)-1)<=0),"由正轉負",IF(AND((SUMIFS(Raw_M!$E$2:$E$2000,Raw_M!$A$2:$A$2000,Stock_Card!$B$2,Raw_M!$F$2:$F$2000,5)/SUMIFS(Raw_M!$E$2:$E$2000,Raw_M!$A$2:$A$2000,Stock_Card!$B$2,Raw_M!$F$2:$F$2000,17)-1)<=0,(SUMIFS(Raw_M!$E$2:$E$2000,Raw_M!$A$2:$A$2000,Stock_Card!$B$2,Raw_M!$F$2:$F$2000,4)/SUMIFS(Raw_M!$E$2:$E$2000,Raw_M!$A$2:$A$2000,Stock_Card!$B$2,Raw_M!$F$2:$F$2000,16)-1)>0),"由負轉正",IF((SUMIFS(Raw_M!$E$2:$E$2000,Raw_M!$A$2:$A$2000,Stock_Card!$B$2,Raw_M!$F$2:$F$2000,4)/SUMIFS(Raw_M!$E$2:$E$2000,Raw_M!$A$2:$A$2000,Stock_Card!$B$2,Raw_M!$F$2:$F$2000,16)-1)>0,IF(((SUMIFS(Raw_M!$E$2:$E$2000,Raw_M!$A$2:$A$2000,Stock_Card!$B$2,Raw_M!$F$2:$F$2000,4)/SUMIFS(Raw_M!$E$2:$E$2000,Raw_M!$A$2:$A$2000,Stock_Card!$B$2,Raw_M!$F$2:$F$2000,16)-1)-(SUMIFS(Raw_M!$E$2:$E$2000,Raw_M!$A$2:$A$2000,Stock_Card!$B$2,Raw_M!$F$2:$F$2000,5)/SUMIFS(Raw_M!$E$2:$E$2000,Raw_M!$A$2:$A$2000,Stock_Card!$B$2,Raw_M!$F$2:$F$2000,17)-1))*100>0,"成長且加速","成長但減速"),IF(((SUMIFS(Raw_M!$E$2:$E$2000,Raw_M!$A$2:$A$2000,Stock_Card!$B$2,Raw_M!$F$2:$F$2000,4)/SUMIFS(Raw_M!$E$2:$E$2000,Raw_M!$A$2:$A$2000,Stock_Card!$B$2,Raw_M!$F$2:$F$2000,16)-1)-(SUMIFS(Raw_M!$E$2:$E$2000,Raw_M!$A$2:$A$2000,Stock_Card!$B$2,Raw_M!$F$2:$F$2000,5)/SUMIFS(Raw_M!$E$2:$E$2000,Raw_M!$A$2:$A$2000,Stock_Card!$B$2,Raw_M!$F$2:$F$2000,17)-1))*100>0,"衰退但收斂","衰退且惡化")))),"")) -> 成長且加速 | J8: =IF(Stock_Card!$B$2="","",IFERROR(SUMIFS(Raw_M!$E$2:$E$2000,Raw_M!$A$2:$A$2000,Stock_Card!$B$2,Raw_M!$C$2:$C$2000,">="&((INT(SUMIFS(Raw_M!$C$2:$C$2000,Raw_M!$A$2:$A$2000,Stock_Card!$B$2,Raw_M!$F$2:$F$2000,4)/100)-0)*100+1),Raw_M!$C$2:$C$2000,"<="&((INT(SUMIFS(Raw_M!$C$2:$C$2000,Raw_M!$A$2:$A$2000,Stock_Card!$B$2,Raw_M!$F$2:$F$2000,4)/100)-0)*100+MOD(SUMIFS(Raw_M!$C$2:$C$2000,Raw_M!$A$2:$A$2000,Stock_Card!$B$2,Raw_M!$F$2:$F$2000,4),100))),"")) -> 2739487.3 | K8: =IF(Stock_Card!$B$2="","",IFERROR(IF(OR(COUNTIFS(Raw_M!$A$2:$A$2000,Stock_Card!$B$2,Raw_M!$C$2:$C$2000,">="&((INT(SUMIFS(Raw_M!$C$2:$C$2000,Raw_M!$A$2:$A$2000,Stock_Card!$B$2,Raw_M!$F$2:$F$2000,4)/100)-0)*100+1),Raw_M!$C$2:$C$2000,"<="&((INT(SUMIFS(Raw_M!$C$2:$C$2000,Raw_M!$A$2:$A$2000,Stock_Card!$B$2,Raw_M!$F$2:$F$2000,4)/100)-0)*100+MOD(SUMIFS(Raw_M!$C$2:$C$2000,Raw_M!$A$2:$A$2000,Stock_Card!$B$2,Raw_M!$F$2:$F$2000,4),100)))<>MOD(SUMIFS(Raw_M!$C$2:$C$2000,Raw_M!$A$2:$A$2000,Stock_Card!$B$2,Raw_M!$F$2:$F$2000,4),100),COUNTIFS(Raw_M!$A$2:$A$2000,Stock_Card!$B$2,Raw_M!$C$2:$C$2000,">="&((INT(SUMIFS(Raw_M!$C$2:$C$2000,Raw_M!$A$2:$A$2000,Stock_Card!$B$2,Raw_M!$F$2:$F$2000,4)/100)-1)*100+1),Raw_M!$C$2:$C$2000,"<="&((INT(SUMIFS(Raw_M!$C$2:$C$2000,Raw_M!$A$2:$A$2000,Stock_Card!$B$2,Raw_M!$F$2:$F$2000,4)/100)-1)*100+MOD(SUMIFS(Raw_M!$C$2:$C$2000,Raw_M!$A$2:$A$2000,Stock_Card!$B$2,Raw_M!$F$2:$F$2000,4),100)))<>MOD(SUMIFS(Raw_M!$C$2:$C$2000,Raw_M!$A$2:$A$2000,Stock_Card!$B$2,Raw_M!$F$2:$F$2000,4),100)),"N/M",SUMIFS(Raw_M!$E$2:$E$2000,Raw_M!$A$2:$A$2000,Stock_Card!$B$2,Raw_M!$C$2:$C$2000,">="&((INT(SUMIFS(Raw_M!$C$2:$C$2000,Raw_M!$A$2:$A$2000,Stock_Card!$B$2,Raw_M!$F$2:$F$2000,4)/100)-0)*100+1),Raw_M!$C$2:$C$2000,"<="&((INT(SUMIFS(Raw_M!$C$2:$C$2000,Raw_M!$A$2:$A$2000,Stock_Card!$B$2,Raw_M!$F$2:$F$2000,4)/100)-0)*100+MOD(SUMIFS(Raw_M!$C$2:$C$2000,Raw_M!$A$2:$A$2000,Stock_Card!$B$2,Raw_M!$F$2:$F$2000,4),100)))/SUMIFS(Raw_M!$E$2:$E$2000,Raw_M!$A$2:$A$2000,Stock_Card!$B$2,Raw_M!$C$2:$C$2000,">="&((INT(SUMIFS(Raw_M!$C$2:$C$2000,Raw_M!$A$2:$A$2000,Stock_Card!$B$2,Raw_M!$F$2:$F$2000,4)/100)-1)*100+1),Raw_M!$C$2:$C$2000,"<="&((INT(SUMIFS(Raw_M!$C$2:$C$2000,Raw_M!$A$2:$A$2000,Stock_Card!$B$2,Raw_M!$F$2:$F$2000,4)/100)-1)*100+MOD(SUMIFS(Raw_M!$C$2:$C$2000,Raw_M!$A$2:$A$2000,Stock_Card!$B$2,Raw_M!$F$2:$F$2000,4),100)))-1),"N/M")) -> 0.33554783
A9: =IF(Stock_Card!$B$2="","",IFERROR(INDEX(Raw_M!$B$2:$B$2000,MATCH(Stock_Card!$B$2&"|5",Raw_M!$G$2:$G$2000,0)),"")) -> 2026-06 | B9: =IF(Stock_Card!$B$2="","",IFERROR(SUMIFS(Raw_M!$E$2:$E$2000,Raw_M!$A$2:$A$2000,Stock_Card!$B$2,Raw_M!$F$2:$F$2000,5),"")) -> 416975.16 | C9: =IF(Stock_Card!$B$2="","",IFERROR((SUMIFS(Raw_M!$E$2:$E$2000,Raw_M!$A$2:$A$2000,Stock_Card!$B$2,Raw_M!$F$2:$F$2000,5)/SUMIFS(Raw_M!$E$2:$E$2000,Raw_M!$A$2:$A$2000,Stock_Card!$B$2,Raw_M!$F$2:$F$2000,6)-1),"")) -> 0.0152171 | D9: =IF(Stock_Card!$B$2="","",IFERROR(((SUMIFS(Raw_M!$E$2:$E$2000,Raw_M!$A$2:$A$2000,Stock_Card!$B$2,Raw_M!$F$2:$F$2000,5)/SUMIFS(Raw_M!$E$2:$E$2000,Raw_M!$A$2:$A$2000,Stock_Card!$B$2,Raw_M!$F$2:$F$2000,6)-1)-(SUMIFS(Raw_M!$E$2:$E$2000,Raw_M!$A$2:$A$2000,Stock_Card!$B$2,Raw_M!$F$2:$F$2000,6)/SUMIFS(Raw_M!$E$2:$E$2000,Raw_M!$A$2:$A$2000,Stock_Card!$B$2,Raw_M!$F$2:$F$2000,7)-1))*100,"")) -> 2.5974976 | E9: =IF(Stock_Card!$B$2="","",IFERROR(IF(OR(NOT(ISNUMBER((SUMIFS(Raw_M!$E$2:$E$2000,Raw_M!$A$2:$A$2000,Stock_Card!$B$2,Raw_M!$F$2:$F$2000,6)/SUMIFS(Raw_M!$E$2:$E$2000,Raw_M!$A$2:$A$2000,Stock_Card!$B$2,Raw_M!$F$2:$F$2000,7)-1))),(SUMIFS(Raw_M!$E$2:$E$2000,Raw_M!$A$2:$A$2000,Stock_Card!$B$2,Raw_M!$F$2:$F$2000,6)/SUMIFS(Raw_M!$E$2:$E$2000,Raw_M!$A$2:$A$2000,Stock_Card!$B$2,Raw_M!$F$2:$F$2000,7)-1)<=0,ABS((SUMIFS(Raw_M!$E$2:$E$2000,Raw_M!$A$2:$A$2000,Stock_Card!$B$2,Raw_M!$F$2:$F$2000,6)/SUMIFS(Raw_M!$E$2:$E$2000,Raw_M!$A$2:$A$2000,Stock_Card!$B$2,Raw_M!$F$2:$F$2000,7)-1))<Config!$B$9),"N/M",((SUMIFS(Raw_M!$E$2:$E$2000,Raw_M!$A$2:$A$2000,Stock_Card!$B$2,Raw_M!$F$2:$F$2000,5)/SUMIFS(Raw_M!$E$2:$E$2000,Raw_M!$A$2:$A$2000,Stock_Card!$B$2,Raw_M!$F$2:$F$2000,6)-1)-(SUMIFS(Raw_M!$E$2:$E$2000,Raw_M!$A$2:$A$2000,Stock_Card!$B$2,Raw_M!$F$2:$F$2000,6)/SUMIFS(Raw_M!$E$2:$E$2000,Raw_M!$A$2:$A$2000,Stock_Card!$B$2,Raw_M!$F$2:$F$2000,7)-1))/ABS((SUMIFS(Raw_M!$E$2:$E$2000,Raw_M!$A$2:$A$2000,Stock_Card!$B$2,Raw_M!$F$2:$F$2000,6)/SUMIFS(Raw_M!$E$2:$E$2000,Raw_M!$A$2:$A$2000,Stock_Card!$B$2,Raw_M!$F$2:$F$2000,7)-1))),"N/M")) -> N/M | F9: =IF(Stock_Card!$B$2="","",IFERROR((SUMIFS(Raw_M!$E$2:$E$2000,Raw_M!$A$2:$A$2000,Stock_Card!$B$2,Raw_M!$F$2:$F$2000,5)/SUMIFS(Raw_M!$E$2:$E$2000,Raw_M!$A$2:$A$2000,Stock_Card!$B$2,Raw_M!$F$2:$F$2000,17)-1),"")) -> 0.3009498 | G9: =IF(Stock_Card!$B$2="","",IFERROR(((SUMIFS(Raw_M!$E$2:$E$2000,Raw_M!$A$2:$A$2000,Stock_Card!$B$2,Raw_M!$F$2:$F$2000,5)/SUMIFS(Raw_M!$E$2:$E$2000,Raw_M!$A$2:$A$2000,Stock_Card!$B$2,Raw_M!$F$2:$F$2000,17)-1)-(SUMIFS(Raw_M!$E$2:$E$2000,Raw_M!$A$2:$A$2000,Stock_Card!$B$2,Raw_M!$F$2:$F$2000,6)/SUMIFS(Raw_M!$E$2:$E$2000,Raw_M!$A$2:$A$2000,Stock_Card!$B$2,Raw_M!$F$2:$F$2000,18)-1))*100,"")) -> 12.599568 | H9: =IF(Stock_Card!$B$2="","",IFERROR(IF(OR(NOT(ISNUMBER((SUMIFS(Raw_M!$E$2:$E$2000,Raw_M!$A$2:$A$2000,Stock_Card!$B$2,Raw_M!$F$2:$F$2000,6)/SUMIFS(Raw_M!$E$2:$E$2000,Raw_M!$A$2:$A$2000,Stock_Card!$B$2,Raw_M!$F$2:$F$2000,18)-1))),(SUMIFS(Raw_M!$E$2:$E$2000,Raw_M!$A$2:$A$2000,Stock_Card!$B$2,Raw_M!$F$2:$F$2000,6)/SUMIFS(Raw_M!$E$2:$E$2000,Raw_M!$A$2:$A$2000,Stock_Card!$B$2,Raw_M!$F$2:$F$2000,18)-1)<=0,ABS((SUMIFS(Raw_M!$E$2:$E$2000,Raw_M!$A$2:$A$2000,Stock_Card!$B$2,Raw_M!$F$2:$F$2000,6)/SUMIFS(Raw_M!$E$2:$E$2000,Raw_M!$A$2:$A$2000,Stock_Card!$B$2,Raw_M!$F$2:$F$2000,18)-1))<Config!$B$9),"N/M",((SUMIFS(Raw_M!$E$2:$E$2000,Raw_M!$A$2:$A$2000,Stock_Card!$B$2,Raw_M!$F$2:$F$2000,5)/SUMIFS(Raw_M!$E$2:$E$2000,Raw_M!$A$2:$A$2000,Stock_Card!$B$2,Raw_M!$F$2:$F$2000,17)-1)-(SUMIFS(Raw_M!$E$2:$E$2000,Raw_M!$A$2:$A$2000,Stock_Card!$B$2,Raw_M!$F$2:$F$2000,6)/SUMIFS(Raw_M!$E$2:$E$2000,Raw_M!$A$2:$A$2000,Stock_Card!$B$2,Raw_M!$F$2:$F$2000,18)-1))/ABS((SUMIFS(Raw_M!$E$2:$E$2000,Raw_M!$A$2:$A$2000,Stock_Card!$B$2,Raw_M!$F$2:$F$2000,6)/SUMIFS(Raw_M!$E$2:$E$2000,Raw_M!$A$2:$A$2000,Stock_Card!$B$2,Raw_M!$F$2:$F$2000,18)-1))),"N/M")) -> 0.72016409 | I9: =IF(Stock_Card!$B$2="","",IFERROR(IF(AND((SUMIFS(Raw_M!$E$2:$E$2000,Raw_M!$A$2:$A$2000,Stock_Card!$B$2,Raw_M!$F$2:$F$2000,6)/SUMIFS(Raw_M!$E$2:$E$2000,Raw_M!$A$2:$A$2000,Stock_Card!$B$2,Raw_M!$F$2:$F$2000,18)-1)>0,(SUMIFS(Raw_M!$E$2:$E$2000,Raw_M!$A$2:$A$2000,Stock_Card!$B$2,Raw_M!$F$2:$F$2000,5)/SUMIFS(Raw_M!$E$2:$E$2000,Raw_M!$A$2:$A$2000,Stock_Card!$B$2,Raw_M!$F$2:$F$2000,17)-1)<=0),"由正轉負",IF(AND((SUMIFS(Raw_M!$E$2:$E$2000,Raw_M!$A$2:$A$2000,Stock_Card!$B$2,Raw_M!$F$2:$F$2000,6)/SUMIFS(Raw_M!$E$2:$E$2000,Raw_M!$A$2:$A$2000,Stock_Card!$B$2,Raw_M!$F$2:$F$2000,18)-1)<=0,(SUMIFS(Raw_M!$E$2:$E$2000,Raw_M!$A$2:$A$2000,Stock_Card!$B$2,Raw_M!$F$2:$F$2000,5)/SUMIFS(Raw_M!$E$2:$E$2000,Raw_M!$A$2:$A$2000,Stock_Card!$B$2,Raw_M!$F$2:$F$2000,17)-1)>0),"由負轉正",IF((SUMIFS(Raw_M!$E$2:$E$2000,Raw_M!$A$2:$A$2000,Stock_Card!$B$2,Raw_M!$F$2:$F$2000,5)/SUMIFS(Raw_M!$E$2:$E$2000,Raw_M!$A$2:$A$2000,Stock_Card!$B$2,Raw_M!$F$2:$F$2000,17)-1)>0,IF(((SUMIFS(Raw_M!$E$2:$E$2000,Raw_M!$A$2:$A$2000,Stock_Card!$B$2,Raw_M!$F$2:$F$2000,5)/SUMIFS(Raw_M!$E$2:$E$2000,Raw_M!$A$2:$A$2000,Stock_Card!$B$2,Raw_M!$F$2:$F$2000,17)-1)-(SUMIFS(Raw_M!$E$2:$E$2000,Raw_M!$A$2:$A$2000,Stock_Card!$B$2,Raw_M!$F$2:$F$2000,6)/SUMIFS(Raw_M!$E$2:$E$2000,Raw_M!$A$2:$A$2000,Stock_Card!$B$2,Raw_M!$F$2:$F$2000,18)-1))*100>0,"成長且加速","成長但減速"),IF(((SUMIFS(Raw_M!$E$2:$E$2000,Raw_M!$A$2:$A$2000,Stock_Card!$B$2,Raw_M!$F$2:$F$2000,5)/SUMIFS(Raw_M!$E$2:$E$2000,Raw_M!$A$2:$A$2000,Stock_Card!$B$2,Raw_M!$F$2:$F$2000,17)-1)-(SUMIFS(Raw_M!$E$2:$E$2000,Raw_M!$A$2:$A$2000,Stock_Card!$B$2,Raw_M!$F$2:$F$2000,6)/SUMIFS(Raw_M!$E$2:$E$2000,Raw_M!$A$2:$A$2000,Stock_Card!$B$2,Raw_M!$F$2:$F$2000,18)-1))*100>0,"衰退但收斂","衰退且惡化")))),"")) -> 成長且加速 | J9: =IF(Stock_Card!$B$2="","",IFERROR(SUMIFS(Raw_M!$E$2:$E$2000,Raw_M!$A$2:$A$2000,Stock_Card!$B$2,Raw_M!$C$2:$C$2000,">="&((INT(SUMIFS(Raw_M!$C$2:$C$2000,Raw_M!$A$2:$A$2000,Stock_Card!$B$2,Raw_M!$F$2:$F$2000,5)/100)-0)*100+1),Raw_M!$C$2:$C$2000,"<="&((INT(SUMIFS(Raw_M!$C$2:$C$2000,Raw_M!$A$2:$A$2000,Stock_Card!$B$2,Raw_M!$F$2:$F$2000,5)/100)-0)*100+MOD(SUMIFS(Raw_M!$C$2:$C$2000,Raw_M!$A$2:$A$2000,Stock_Card!$B$2,Raw_M!$F$2:$F$2000,5),100))),"")) -> 2296807.3 | K9: =IF(Stock_Card!$B$2="","",IFERROR(IF(OR(COUNTIFS(Raw_M!$A$2:$A$2000,Stock_Card!$B$2,Raw_M!$C$2:$C$2000,">="&((INT(SUMIFS(Raw_M!$C$2:$C$2000,Raw_M!$A$2:$A$2000,Stock_Card!$B$2,Raw_M!$F$2:$F$2000,5)/100)-0)*100+1),Raw_M!$C$2:$C$2000,"<="&((INT(SUMIFS(Raw_M!$C$2:$C$2000,Raw_M!$A$2:$A$2000,Stock_Card!$B$2,Raw_M!$F$2:$F$2000,5)/100)-0)*100+MOD(SUMIFS(Raw_M!$C$2:$C$2000,Raw_M!$A$2:$A$2000,Stock_Card!$B$2,Raw_M!$F$2:$F$2000,5),100)))<>MOD(SUMIFS(Raw_M!$C$2:$C$2000,Raw_M!$A$2:$A$2000,Stock_Card!$B$2,Raw_M!$F$2:$F$2000,5),100),COUNTIFS(Raw_M!$A$2:$A$2000,Stock_Card!$B$2,Raw_M!$C$2:$C$2000,">="&((INT(SUMIFS(Raw_M!$C$2:$C$2000,Raw_M!$A$2:$A$2000,Stock_Card!$B$2,Raw_M!$F$2:$F$2000,5)/100)-1)*100+1),Raw_M!$C$2:$C$2000,"<="&((INT(SUMIFS(Raw_M!$C$2:$C$2000,Raw_M!$A$2:$A$2000,Stock_Card!$B$2,Raw_M!$F$2:$F$2000,5)/100)-1)*100+MOD(SUMIFS(Raw_M!$C$2:$C$2000,Raw_M!$A$2:$A$2000,Stock_Card!$B$2,Raw_M!$F$2:$F$2000,5),100)))<>MOD(SUMIFS(Raw_M!$C$2:$C$2000,Raw_M!$A$2:$A$2000,Stock_Card!$B$2,Raw_M!$F$2:$F$2000,5),100)),"N/M",SUMIFS(Raw_M!$E$2:$E$2000,Raw_M!$A$2:$A$2000,Stock_Card!$B$2,Raw_M!$C$2:$C$2000,">="&((INT(SUMIFS(Raw_M!$C$2:$C$2000,Raw_M!$A$2:$A$2000,Stock_Card!$B$2,Raw_M!$F$2:$F$2000,5)/100)-0)*100+1),Raw_M!$C$2:$C$2000,"<="&((INT(SUMIFS(Raw_M!$C$2:$C$2000,Raw_M!$A$2:$A$2000,Stock_Card!$B$2,Raw_M!$F$2:$F$2000,5)/100)-0)*100+MOD(SUMIFS(Raw_M!$C$2:$C$2000,Raw_M!$A$2:$A$2000,Stock_Card!$B$2,Raw_M!$F$2:$F$2000,5),100)))/SUMIFS(Raw_M!$E$2:$E$2000,Raw_M!$A$2:$A$2000,Stock_Card!$B$2,Raw_M!$C$2:$C$2000,">="&((INT(SUMIFS(Raw_M!$C$2:$C$2000,Raw_M!$A$2:$A$2000,Stock_Card!$B$2,Raw_M!$F$2:$F$2000,5)/100)-1)*100+1),Raw_M!$C$2:$C$2000,"<="&((INT(SUMIFS(Raw_M!$C$2:$C$2000,Raw_M!$A$2:$A$2000,Stock_Card!$B$2,Raw_M!$F$2:$F$2000,5)/100)-1)*100+MOD(SUMIFS(Raw_M!$C$2:$C$2000,Raw_M!$A$2:$A$2000,Stock_Card!$B$2,Raw_M!$F$2:$F$2000,5),100)))-1),"N/M")) -> 0.2849274
A10: =IF(Stock_Card!$B$2="","",IFERROR(INDEX(Raw_M!$B$2:$B$2000,MATCH(Stock_Card!$B$2&"|6",Raw_M!$G$2:$G$2000,0)),"")) -> 2026-05 | B10: =IF(Stock_Card!$B$2="","",IFERROR(SUMIFS(Raw_M!$E$2:$E$2000,Raw_M!$A$2:$A$2000,Stock_Card!$B$2,Raw_M!$F$2:$F$2000,6),"")) -> 410725.12 | C10: =IF(Stock_Card!$B$2="","",IFERROR((SUMIFS(Raw_M!$E$2:$E$2000,Raw_M!$A$2:$A$2000,Stock_Card!$B$2,Raw_M!$F$2:$F$2000,6)/SUMIFS(Raw_M!$E$2:$E$2000,Raw_M!$A$2:$A$2000,Stock_Card!$B$2,Raw_M!$F$2:$F$2000,7)-1),"")) -> -0.010757876 | D10: =IF(Stock_Card!$B$2="","",IFERROR(((SUMIFS(Raw_M!$E$2:$E$2000,Raw_M!$A$2:$A$2000,Stock_Card!$B$2,Raw_M!$F$2:$F$2000,6)/SUMIFS(Raw_M!$E$2:$E$2000,Raw_M!$A$2:$A$2000,Stock_Card!$B$2,Raw_M!$F$2:$F$2000,7)-1)-(SUMIFS(Raw_M!$E$2:$E$2000,Raw_M!$A$2:$A$2000,Stock_Card!$B$2,Raw_M!$F$2:$F$2000,7)/SUMIFS(Raw_M!$E$2:$E$2000,Raw_M!$A$2:$A$2000,Stock_Card!$B$2,Raw_M!$F$2:$F$2000,8)-1))*100,"")) -> -31.780354 | E10: =IF(Stock_Card!$B$2="","",IFERROR(IF(OR(NOT(ISNUMBER((SUMIFS(Raw_M!$E$2:$E$2000,Raw_M!$A$2:$A$2000,Stock_Card!$B$2,Raw_M!$F$2:$F$2000,7)/SUMIFS(Raw_M!$E$2:$E$2000,Raw_M!$A$2:$A$2000,Stock_Card!$B$2,Raw_M!$F$2:$F$2000,8)-1))),(SUMIFS(Raw_M!$E$2:$E$2000,Raw_M!$A$2:$A$2000,Stock_Card!$B$2,Raw_M!$F$2:$F$2000,7)/SUMIFS(Raw_M!$E$2:$E$2000,Raw_M!$A$2:$A$2000,Stock_Card!$B$2,Raw_M!$F$2:$F$2000,8)-1)<=0,ABS((SUMIFS(Raw_M!$E$2:$E$2000,Raw_M!$A$2:$A$2000,Stock_Card!$B$2,Raw_M!$F$2:$F$2000,7)/SUMIFS(Raw_M!$E$2:$E$2000,Raw_M!$A$2:$A$2000,Stock_Card!$B$2,Raw_M!$F$2:$F$2000,8)-1))<Config!$B$9),"N/M",((SUMIFS(Raw_M!$E$2:$E$2000,Raw_M!$A$2:$A$2000,Stock_Card!$B$2,Raw_M!$F$2:$F$2000,6)/SUMIFS(Raw_M!$E$2:$E$2000,Raw_M!$A$2:$A$2000,Stock_Card!$B$2,Raw_M!$F$2:$F$2000,7)-1)-(SUMIFS(Raw_M!$E$2:$E$2000,Raw_M!$A$2:$A$2000,Stock_Card!$B$2,Raw_M!$F$2:$F$2000,7)/SUMIFS(Raw_M!$E$2:$E$2000,Raw_M!$A$2:$A$2000,Stock_Card!$B$2,Raw_M!$F$2:$F$2000,8)-1))/ABS((SUMIFS(Raw_M!$E$2:$E$2000,Raw_M!$A$2:$A$2000,Stock_Card!$B$2,Raw_M!$F$2:$F$2000,7)/SUMIFS(Raw_M!$E$2:$E$2000,Raw_M!$A$2:$A$2000,Stock_Card!$B$2,Raw_M!$F$2:$F$2000,8)-1))),"N/M")) -> -1.0350367 | F10: =IF(Stock_Card!$B$2="","",IFERROR((SUMIFS(Raw_M!$E$2:$E$2000,Raw_M!$A$2:$A$2000,Stock_Card!$B$2,Raw_M!$F$2:$F$2000,6)/SUMIFS(Raw_M!$E$2:$E$2000,Raw_M!$A$2:$A$2000,Stock_Card!$B$2,Raw_M!$F$2:$F$2000,18)-1),"")) -> 0.17495412 | G10: =IF(Stock_Card!$B$2="","",IFERROR(((SUMIFS(Raw_M!$E$2:$E$2000,Raw_M!$A$2:$A$2000,Stock_Card!$B$2,Raw_M!$F$2:$F$2000,6)/SUMIFS(Raw_M!$E$2:$E$2000,Raw_M!$A$2:$A$2000,Stock_Card!$B$2,Raw_M!$F$2:$F$2000,18)-1)-(SUMIFS(Raw_M!$E$2:$E$2000,Raw_M!$A$2:$A$2000,Stock_Card!$B$2,Raw_M!$F$2:$F$2000,7)/SUMIFS(Raw_M!$E$2:$E$2000,Raw_M!$A$2:$A$2000,Stock_Card!$B$2,Raw_M!$F$2:$F$2000,19)-1))*100,"")) -> -27.698426 | H10: =IF(Stock_Card!$B$2="","",IFERROR(IF(OR(NOT(ISNUMBER((SUMIFS(Raw_M!$E$2:$E$2000,Raw_M!$A$2:$A$2000,Stock_Card!$B$2,Raw_M!$F$2:$F$2000,7)/SUMIFS(Raw_M!$E$2:$E$2000,Raw_M!$A$2:$A$2000,Stock_Card!$B$2,Raw_M!$F$2:$F$2000,19)-1))),(SUMIFS(Raw_M!$E$2:$E$2000,Raw_M!$A$2:$A$2000,Stock_Card!$B$2,Raw_M!$F$2:$F$2000,7)/SUMIFS(Raw_M!$E$2:$E$2000,Raw_M!$A$2:$A$2000,Stock_Card!$B$2,Raw_M!$F$2:$F$2000,19)-1)<=0,ABS((SUMIFS(Raw_M!$E$2:$E$2000,Raw_M!$A$2:$A$2000,Stock_Card!$B$2,Raw_M!$F$2:$F$2000,7)/SUMIFS(Raw_M!$E$2:$E$2000,Raw_M!$A$2:$A$2000,Stock_Card!$B$2,Raw_M!$F$2:$F$2000,19)-1))<Config!$B$9),"N/M",((SUMIFS(Raw_M!$E$2:$E$2000,Raw_M!$A$2:$A$2000,Stock_Card!$B$2,Raw_M!$F$2:$F$2000,6)/SUMIFS(Raw_M!$E$2:$E$2000,Raw_M!$A$2:$A$2000,Stock_Card!$B$2,Raw_M!$F$2:$F$2000,18)-1)-(SUMIFS(Raw_M!$E$2:$E$2000,Raw_M!$A$2:$A$2000,Stock_Card!$B$2,Raw_M!$F$2:$F$2000,7)/SUMIFS(Raw_M!$E$2:$E$2000,Raw_M!$A$2:$A$2000,Stock_Card!$B$2,Raw_M!$F$2:$F$2000,19)-1))/ABS((SUMIFS(Raw_M!$E$2:$E$2000,Raw_M!$A$2:$A$2000,Stock_Card!$B$2,Raw_M!$F$2:$F$2000,7)/SUMIFS(Raw_M!$E$2:$E$2000,Raw_M!$A$2:$A$2000,Stock_Card!$B$2,Raw_M!$F$2:$F$2000,19)-1))),"N/M")) -> -0.61288058 | I10: =IF(Stock_Card!$B$2="","",IFERROR(IF(AND((SUMIFS(Raw_M!$E$2:$E$2000,Raw_M!$A$2:$A$2000,Stock_Card!$B$2,Raw_M!$F$2:$F$2000,7)/SUMIFS(Raw_M!$E$2:$E$2000,Raw_M!$A$2:$A$2000,Stock_Card!$B$2,Raw_M!$F$2:$F$2000,19)-1)>0,(SUMIFS(Raw_M!$E$2:$E$2000,Raw_M!$A$2:$A$2000,Stock_Card!$B$2,Raw_M!$F$2:$F$2000,6)/SUMIFS(Raw_M!$E$2:$E$2000,Raw_M!$A$2:$A$2000,Stock_Card!$B$2,Raw_M!$F$2:$F$2000,18)-1)<=0),"由正轉負",IF(AND((SUMIFS(Raw_M!$E$2:$E$2000,Raw_M!$A$2:$A$2000,Stock_Card!$B$2,Raw_M!$F$2:$F$2000,7)/SUMIFS(Raw_M!$E$2:$E$2000,Raw_M!$A$2:$A$2000,Stock_Card!$B$2,Raw_M!$F$2:$F$2000,19)-1)<=0,(SUMIFS(Raw_M!$E$2:$E$2000,Raw_M!$A$2:$A$2000,Stock_Card!$B$2,Raw_M!$F$2:$F$2000,6)/SUMIFS(Raw_M!$E$2:$E$2000,Raw_M!$A$2:$A$2000,Stock_Card!$B$2,Raw_M!$F$2:$F$2000,18)-1)>0),"由負轉正",IF((SUMIFS(Raw_M!$E$2:$E$2000,Raw_M!$A$2:$A$2000,Stock_Card!$B$2,Raw_M!$F$2:$F$2000,6)/SUMIFS(Raw_M!$E$2:$E$2000,Raw_M!$A$2:$A$2000,Stock_Card!$B$2,Raw_M!$F$2:$F$2000,18)-1)>0,IF(((SUMIFS(Raw_M!$E$2:$E$2000,Raw_M!$A$2:$A$2000,Stock_Card!$B$2,Raw_M!$F$2:$F$2000,6)/SUMIFS(Raw_M!$E$2:$E$2000,Raw_M!$A$2:$A$2000,Stock_Card!$B$2,Raw_M!$F$2:$F$2000,18)-1)-(SUMIFS(Raw_M!$E$2:$E$2000,Raw_M!$A$2:$A$2000,Stock_Card!$B$2,Raw_M!$F$2:$F$2000,7)/SUMIFS(Raw_M!$E$2:$E$2000,Raw_M!$A$2:$A$2000,Stock_Card!$B$2,Raw_M!$F$2:$F$2000,19)-1))*100>0,"成長且加速","成長但減速"),IF(((SUMIFS(Raw_M!$E$2:$E$2000,Raw_M!$A$2:$A$2000,Stock_Card!$B$2,Raw_M!$F$2:$F$2000,6)/SUMIFS(Raw_M!$E$2:$E$2000,Raw_M!$A$2:$A$2000,Stock_Card!$B$2,Raw_M!$F$2:$F$2000,18)-1)-(SUMIFS(Raw_M!$E$2:$E$2000,Raw_M!$A$2:$A$2000,Stock_Card!$B$2,Raw_M!$F$2:$F$2000,7)/SUMIFS(Raw_M!$E$2:$E$2000,Raw_M!$A$2:$A$2000,Stock_Card!$B$2,Raw_M!$F$2:$F$2000,19)-1))*100>0,"衰退但收斂","衰退且惡化")))),"")) -> 成長但減速 | J10: =IF(Stock_Card!$B$2="","",IFERROR(SUMIFS(Raw_M!$E$2:$E$2000,Raw_M!$A$2:$A$2000,Stock_Card!$B$2,Raw_M!$C$2:$C$2000,">="&((INT(SUMIFS(Raw_M!$C$2:$C$2000,Raw_M!$A$2:$A$2000,Stock_Card!$B$2,Raw_M!$F$2:$F$2000,6)/100)-0)*100+1),Raw_M!$C$2:$C$2000,"<="&((INT(SUMIFS(Raw_M!$C$2:$C$2000,Raw_M!$A$2:$A$2000,Stock_Card!$B$2,Raw_M!$F$2:$F$2000,6)/100)-0)*100+MOD(SUMIFS(Raw_M!$C$2:$C$2000,Raw_M!$A$2:$A$2000,Stock_Card!$B$2,Raw_M!$F$2:$F$2000,6),100))),"")) -> 1879832.1 | K10: =IF(Stock_Card!$B$2="","",IFERROR(IF(OR(COUNTIFS(Raw_M!$A$2:$A$2000,Stock_Card!$B$2,Raw_M!$C$2:$C$2000,">="&((INT(SUMIFS(Raw_M!$C$2:$C$2000,Raw_M!$A$2:$A$2000,Stock_Card!$B$2,Raw_M!$F$2:$F$2000,6)/100)-0)*100+1),Raw_M!$C$2:$C$2000,"<="&((INT(SUMIFS(Raw_M!$C$2:$C$2000,Raw_M!$A$2:$A$2000,Stock_Card!$B$2,Raw_M!$F$2:$F$2000,6)/100)-0)*100+MOD(SUMIFS(Raw_M!$C$2:$C$2000,Raw_M!$A$2:$A$2000,Stock_Card!$B$2,Raw_M!$F$2:$F$2000,6),100)))<>MOD(SUMIFS(Raw_M!$C$2:$C$2000,Raw_M!$A$2:$A$2000,Stock_Card!$B$2,Raw_M!$F$2:$F$2000,6),100),COUNTIFS(Raw_M!$A$2:$A$2000,Stock_Card!$B$2,Raw_M!$C$2:$C$2000,">="&((INT(SUMIFS(Raw_M!$C$2:$C$2000,Raw_M!$A$2:$A$2000,Stock_Card!$B$2,Raw_M!$F$2:$F$2000,6)/100)-1)*100+1),Raw_M!$C$2:$C$2000,"<="&((INT(SUMIFS(Raw_M!$C$2:$C$2000,Raw_M!$A$2:$A$2000,Stock_Card!$B$2,Raw_M!$F$2:$F$2000,6)/100)-1)*100+MOD(SUMIFS(Raw_M!$C$2:$C$2000,Raw_M!$A$2:$A$2000,Stock_Card!$B$2,Raw_M!$F$2:$F$2000,6),100)))<>MOD(SUMIFS(Raw_M!$C$2:$C$2000,Raw_M!$A$2:$A$2000,Stock_Card!$B$2,Raw_M!$F$2:$F$2000,6),100)),"N/M",SUMIFS(Raw_M!$E$2:$E$2000,Raw_M!$A$2:$A$2000,Stock_Card!$B$2,Raw_M!$C$2:$C$2000,">="&((INT(SUMIFS(Raw_M!$C$2:$C$2000,Raw_M!$A$2:$A$2000,Stock_Card!$B$2,Raw_M!$F$2:$F$2000,6)/100)-0)*100+1),Raw_M!$C$2:$C$2000,"<="&((INT(SUMIFS(Raw_M!$C$2:$C$2000,Raw_M!$A$2:$A$2000,Stock_Card!$B$2,Raw_M!$F$2:$F$2000,6)/100)-0)*100+MOD(SUMIFS(Raw_M!$C$2:$C$2000,Raw_M!$A$2:$A$2000,Stock_Card!$B$2,Raw_M!$F$2:$F$2000,6),100)))/SUMIFS(Raw_M!$E$2:$E$2000,Raw_M!$A$2:$A$2000,Stock_Card!$B$2,Raw_M!$C$2:$C$2000,">="&((INT(SUMIFS(Raw_M!$C$2:$C$2000,Raw_M!$A$2:$A$2000,Stock_Card!$B$2,Raw_M!$F$2:$F$2000,6)/100)-1)*100+1),Raw_M!$C$2:$C$2000,"<="&((INT(SUMIFS(Raw_M!$C$2:$C$2000,Raw_M!$A$2:$A$2000,Stock_Card!$B$2,Raw_M!$F$2:$F$2000,6)/100)-1)*100+MOD(SUMIFS(Raw_M!$C$2:$C$2000,Raw_M!$A$2:$A$2000,Stock_Card!$B$2,Raw_M!$F$2:$F$2000,6),100)))-1),"N/M")) -> 0.28142672
A11: =IF(Stock_Card!$B$2="","",IFERROR(INDEX(Raw_M!$B$2:$B$2000,MATCH(Stock_Card!$B$2&"|7",Raw_M!$G$2:$G$2000,0)),"")) -> 2026-04 | B11: =IF(Stock_Card!$B$2="","",IFERROR(SUMIFS(Raw_M!$E$2:$E$2000,Raw_M!$A$2:$A$2000,Stock_Card!$B$2,Raw_M!$F$2:$F$2000,7),"")) -> 415191.7 | C11: =IF(Stock_Card!$B$2="","",IFERROR((SUMIFS(Raw_M!$E$2:$E$2000,Raw_M!$A$2:$A$2000,Stock_Card!$B$2,Raw_M!$F$2:$F$2000,7)/SUMIFS(Raw_M!$E$2:$E$2000,Raw_M!$A$2:$A$2000,Stock_Card!$B$2,Raw_M!$F$2:$F$2000,8)-1),"")) -> 0.30704567 | D11: =IF(Stock_Card!$B$2="","",IFERROR(((SUMIFS(Raw_M!$E$2:$E$2000,Raw_M!$A$2:$A$2000,Stock_Card!$B$2,Raw_M!$F$2:$F$2000,7)/SUMIFS(Raw_M!$E$2:$E$2000,Raw_M!$A$2:$A$2000,Stock_Card!$B$2,Raw_M!$F$2:$F$2000,8)-1)-(SUMIFS(Raw_M!$E$2:$E$2000,Raw_M!$A$2:$A$2000,Stock_Card!$B$2,Raw_M!$F$2:$F$2000,8)/SUMIFS(Raw_M!$E$2:$E$2000,Raw_M!$A$2:$A$2000,Stock_Card!$B$2,Raw_M!$F$2:$F$2000,9)-1))*100,"")) -> 51.538821 | E11: =IF(Stock_Card!$B$2="","",IFERROR(IF(OR(NOT(ISNUMBER((SUMIFS(Raw_M!$E$2:$E$2000,Raw_M!$A$2:$A$2000,Stock_Card!$B$2,Raw_M!$F$2:$F$2000,8)/SUMIFS(Raw_M!$E$2:$E$2000,Raw_M!$A$2:$A$2000,Stock_Card!$B$2,Raw_M!$F$2:$F$2000,9)-1))),(SUMIFS(Raw_M!$E$2:$E$2000,Raw_M!$A$2:$A$2000,Stock_Card!$B$2,Raw_M!$F$2:$F$2000,8)/SUMIFS(Raw_M!$E$2:$E$2000,Raw_M!$A$2:$A$2000,Stock_Card!$B$2,Raw_M!$F$2:$F$2000,9)-1)<=0,ABS((SUMIFS(Raw_M!$E$2:$E$2000,Raw_M!$A$2:$A$2000,Stock_Card!$B$2,Raw_M!$F$2:$F$2000,8)/SUMIFS(Raw_M!$E$2:$E$2000,Raw_M!$A$2:$A$2000,Stock_Card!$B$2,Raw_M!$F$2:$F$2000,9)-1))<Config!$B$9),"N/M",((SUMIFS(Raw_M!$E$2:$E$2000,Raw_M!$A$2:$A$2000,Stock_Card!$B$2,Raw_M!$F$2:$F$2000,7)/SUMIFS(Raw_M!$E$2:$E$2000,Raw_M!$A$2:$A$2000,Stock_Card!$B$2,Raw_M!$F$2:$F$2000,8)-1)-(SUMIFS(Raw_M!$E$2:$E$2000,Raw_M!$A$2:$A$2000,Stock_Card!$B$2,Raw_M!$F$2:$F$2000,8)/SUMIFS(Raw_M!$E$2:$E$2000,Raw_M!$A$2:$A$2000,Stock_Card!$B$2,Raw_M!$F$2:$F$2000,9)-1))/ABS((SUMIFS(Raw_M!$E$2:$E$2000,Raw_M!$A$2:$A$2000,Stock_Card!$B$2,Raw_M!$F$2:$F$2000,8)/SUMIFS(Raw_M!$E$2:$E$2000,Raw_M!$A$2:$A$2000,Stock_Card!$B$2,Raw_M!$F$2:$F$2000,9)-1))),"N/M")) -> N/M | F11: =IF(Stock_Card!$B$2="","",IFERROR((SUMIFS(Raw_M!$E$2:$E$2000,Raw_M!$A$2:$A$2000,Stock_Card!$B$2,Raw_M!$F$2:$F$2000,7)/SUMIFS(Raw_M!$E$2:$E$2000,Raw_M!$A$2:$A$2000,Stock_Card!$B$2,Raw_M!$F$2:$F$2000,19)-1),"")) -> 0.45193839 | G11: =IF(Stock_Card!$B$2="","",IFERROR(((SUMIFS(Raw_M!$E$2:$E$2000,Raw_M!$A$2:$A$2000,Stock_Card!$B$2,Raw_M!$F$2:$F$2000,7)/SUMIFS(Raw_M!$E$2:$E$2000,Raw_M!$A$2:$A$2000,Stock_Card!$B$2,Raw_M!$F$2:$F$2000,19)-1)-(SUMIFS(Raw_M!$E$2:$E$2000,Raw_M!$A$2:$A$2000,Stock_Card!$B$2,Raw_M!$F$2:$F$2000,8)/SUMIFS(Raw_M!$E$2:$E$2000,Raw_M!$A$2:$A$2000,Stock_Card!$B$2,Raw_M!$F$2:$F$2000,20)-1))*100,"")) -> 23.022352 | H11: =IF(Stock_Card!$B$2="","",IFERROR(IF(OR(NOT(ISNUMBER((SUMIFS(Raw_M!$E$2:$E$2000,Raw_M!$A$2:$A$2000,Stock_Card!$B$2,Raw_M!$F$2:$F$2000,8)/SUMIFS(Raw_M!$E$2:$E$2000,Raw_M!$A$2:$A$2000,Stock_Card!$B$2,Raw_M!$F$2:$F$2000,20)-1))),(SUMIFS(Raw_M!$E$2:$E$2000,Raw_M!$A$2:$A$2000,Stock_Card!$B$2,Raw_M!$F$2:$F$2000,8)/SUMIFS(Raw_M!$E$2:$E$2000,Raw_M!$A$2:$A$2000,Stock_Card!$B$2,Raw_M!$F$2:$F$2000,20)-1)<=0,ABS((SUMIFS(Raw_M!$E$2:$E$2000,Raw_M!$A$2:$A$2000,Stock_Card!$B$2,Raw_M!$F$2:$F$2000,8)/SUMIFS(Raw_M!$E$2:$E$2000,Raw_M!$A$2:$A$2000,Stock_Card!$B$2,Raw_M!$F$2:$F$2000,20)-1))<Config!$B$9),"N/M",((SUMIFS(Raw_M!$E$2:$E$2000,Raw_M!$A$2:$A$2000,Stock_Card!$B$2,Raw_M!$F$2:$F$2000,7)/SUMIFS(Raw_M!$E$2:$E$2000,Raw_M!$A$2:$A$2000,Stock_Card!$B$2,Raw_M!$F$2:$F$2000,19)-1)-(SUMIFS(Raw_M!$E$2:$E$2000,Raw_M!$A$2:$A$2000,Stock_Card!$B$2,Raw_M!$F$2:$F$2000,8)/SUMIFS(Raw_M!$E$2:$E$2000,Raw_M!$A$2:$A$2000,Stock_Card!$B$2,Raw_M!$F$2:$F$2000,20)-1))/ABS((SUMIFS(Raw_M!$E$2:$E$2000,Raw_M!$A$2:$A$2000,Stock_Card!$B$2,Raw_M!$F$2:$F$2000,8)/SUMIFS(Raw_M!$E$2:$E$2000,Raw_M!$A$2:$A$2000,Stock_Card!$B$2,Raw_M!$F$2:$F$2000,20)-1))),"N/M")) -> 1.0383765 | I11: =IF(Stock_Card!$B$2="","",IFERROR(IF(AND((SUMIFS(Raw_M!$E$2:$E$2000,Raw_M!$A$2:$A$2000,Stock_Card!$B$2,Raw_M!$F$2:$F$2000,8)/SUMIFS(Raw_M!$E$2:$E$2000,Raw_M!$A$2:$A$2000,Stock_Card!$B$2,Raw_M!$F$2:$F$2000,20)-1)>0,(SUMIFS(Raw_M!$E$2:$E$2000,Raw_M!$A$2:$A$2000,Stock_Card!$B$2,Raw_M!$F$2:$F$2000,7)/SUMIFS(Raw_M!$E$2:$E$2000,Raw_M!$A$2:$A$2000,Stock_Card!$B$2,Raw_M!$F$2:$F$2000,19)-1)<=0),"由正轉負",IF(AND((SUMIFS(Raw_M!$E$2:$E$2000,Raw_M!$A$2:$A$2000,Stock_Card!$B$2,Raw_M!$F$2:$F$2000,8)/SUMIFS(Raw_M!$E$2:$E$2000,Raw_M!$A$2:$A$2000,Stock_Card!$B$2,Raw_M!$F$2:$F$2000,20)-1)<=0,(SUMIFS(Raw_M!$E$2:$E$2000,Raw_M!$A$2:$A$2000,Stock_Card!$B$2,Raw_M!$F$2:$F$2000,7)/SUMIFS(Raw_M!$E$2:$E$2000,Raw_M!$A$2:$A$2000,Stock_Card!$B$2,Raw_M!$F$2:$F$2000,19)-1)>0),"由負轉正",IF((SUMIFS(Raw_M!$E$2:$E$2000,Raw_M!$A$2:$A$2000,Stock_Card!$B$2,Raw_M!$F$2:$F$2000,7)/SUMIFS(Raw_M!$E$2:$E$2000,Raw_M!$A$2:$A$2000,Stock_Card!$B$2,Raw_M!$F$2:$F$2000,19)-1)>0,IF(((SUMIFS(Raw_M!$E$2:$E$2000,Raw_M!$A$2:$A$2000,Stock_Card!$B$2,Raw_M!$F$2:$F$2000,7)/SUMIFS(Raw_M!$E$2:$E$2000,Raw_M!$A$2:$A$2000,Stock_Card!$B$2,Raw_M!$F$2:$F$2000,19)-1)-(SUMIFS(Raw_M!$E$2:$E$2000,Raw_M!$A$2:$A$2000,Stock_Card!$B$2,Raw_M!$F$2:$F$2000,8)/SUMIFS(Raw_M!$E$2:$E$2000,Raw_M!$A$2:$A$2000,Stock_Card!$B$2,Raw_M!$F$2:$F$2000,20)-1))*100>0,"成長且加速","成長但減速"),IF(((SUMIFS(Raw_M!$E$2:$E$2000,Raw_M!$A$2:$A$2000,Stock_Card!$B$2,Raw_M!$F$2:$F$2000,7)/SUMIFS(Raw_M!$E$2:$E$2000,Raw_M!$A$2:$A$2000,Stock_Card!$B$2,Raw_M!$F$2:$F$2000,19)-1)-(SUMIFS(Raw_M!$E$2:$E$2000,Raw_M!$A$2:$A$2000,Stock_Card!$B$2,Raw_M!$F$2:$F$2000,8)/SUMIFS(Raw_M!$E$2:$E$2000,Raw_M!$A$2:$A$2000,Stock_Card!$B$2,Raw_M!$F$2:$F$2000,20)-1))*100>0,"衰退但收斂","衰退且惡化")))),"")) -> 成長且加速 | J11: =IF(Stock_Card!$B$2="","",IFERROR(SUMIFS(Raw_M!$E$2:$E$2000,Raw_M!$A$2:$A$2000,Stock_Card!$B$2,Raw_M!$C$2:$C$2000,">="&((INT(SUMIFS(Raw_M!$C$2:$C$2000,Raw_M!$A$2:$A$2000,Stock_Card!$B$2,Raw_M!$F$2:$F$2000,7)/100)-0)*100+1),Raw_M!$C$2:$C$2000,"<="&((INT(SUMIFS(Raw_M!$C$2:$C$2000,Raw_M!$A$2:$A$2000,Stock_Card!$B$2,Raw_M!$F$2:$F$2000,7)/100)-0)*100+MOD(SUMIFS(Raw_M!$C$2:$C$2000,Raw_M!$A$2:$A$2000,Stock_Card!$B$2,Raw_M!$F$2:$F$2000,7),100))),"")) -> 1469107 | K11: =IF(Stock_Card!$B$2="","",IFERROR(IF(OR(COUNTIFS(Raw_M!$A$2:$A$2000,Stock_Card!$B$2,Raw_M!$C$2:$C$2000,">="&((INT(SUMIFS(Raw_M!$C$2:$C$2000,Raw_M!$A$2:$A$2000,Stock_Card!$B$2,Raw_M!$F$2:$F$2000,7)/100)-0)*100+1),Raw_M!$C$2:$C$2000,"<="&((INT(SUMIFS(Raw_M!$C$2:$C$2000,Raw_M!$A$2:$A$2000,Stock_Card!$B$2,Raw_M!$F$2:$F$2000,7)/100)-0)*100+MOD(SUMIFS(Raw_M!$C$2:$C$2000,Raw_M!$A$2:$A$2000,Stock_Card!$B$2,Raw_M!$F$2:$F$2000,7),100)))<>MOD(SUMIFS(Raw_M!$C$2:$C$2000,Raw_M!$A$2:$A$2000,Stock_Card!$B$2,Raw_M!$F$2:$F$2000,7),100),COUNTIFS(Raw_M!$A$2:$A$2000,Stock_Card!$B$2,Raw_M!$C$2:$C$2000,">="&((INT(SUMIFS(Raw_M!$C$2:$C$2000,Raw_M!$A$2:$A$2000,Stock_Card!$B$2,Raw_M!$F$2:$F$2000,7)/100)-1)*100+1),Raw_M!$C$2:$C$2000,"<="&((INT(SUMIFS(Raw_M!$C$2:$C$2000,Raw_M!$A$2:$A$2000,Stock_Card!$B$2,Raw_M!$F$2:$F$2000,7)/100)-1)*100+MOD(SUMIFS(Raw_M!$C$2:$C$2000,Raw_M!$A$2:$A$2000,Stock_Card!$B$2,Raw_M!$F$2:$F$2000,7),100)))<>MOD(SUMIFS(Raw_M!$C$2:$C$2000,Raw_M!$A$2:$A$2000,Stock_Card!$B$2,Raw_M!$F$2:$F$2000,7),100)),"N/M",SUMIFS(Raw_M!$E$2:$E$2000,Raw_M!$A$2:$A$2000,Stock_Card!$B$2,Raw_M!$C$2:$C$2000,">="&((INT(SUMIFS(Raw_M!$C$2:$C$2000,Raw_M!$A$2:$A$2000,Stock_Card!$B$2,Raw_M!$F$2:$F$2000,7)/100)-0)*100+1),Raw_M!$C$2:$C$2000,"<="&((INT(SUMIFS(Raw_M!$C$2:$C$2000,Raw_M!$A$2:$A$2000,Stock_Card!$B$2,Raw_M!$F$2:$F$2000,7)/100)-0)*100+MOD(SUMIFS(Raw_M!$C$2:$C$2000,Raw_M!$A$2:$A$2000,Stock_Card!$B$2,Raw_M!$F$2:$F$2000,7),100)))/SUMIFS(Raw_M!$E$2:$E$2000,Raw_M!$A$2:$A$2000,Stock_Card!$B$2,Raw_M!$C$2:$C$2000,">="&((INT(SUMIFS(Raw_M!$C$2:$C$2000,Raw_M!$A$2:$A$2000,Stock_Card!$B$2,Raw_M!$F$2:$F$2000,7)/100)-1)*100+1),Raw_M!$C$2:$C$2000,"<="&((INT(SUMIFS(Raw_M!$C$2:$C$2000,Raw_M!$A$2:$A$2000,Stock_Card!$B$2,Raw_M!$F$2:$F$2000,7)/100)-1)*100+MOD(SUMIFS(Raw_M!$C$2:$C$2000,Raw_M!$A$2:$A$2000,Stock_Card!$B$2,Raw_M!$F$2:$F$2000,7),100)))-1),"N/M")) -> 0.31473506
A12: =IF(Stock_Card!$B$2="","",IFERROR(INDEX(Raw_M!$B$2:$B$2000,MATCH(Stock_Card!$B$2&"|8",Raw_M!$G$2:$G$2000,0)),"")) -> 2026-03 | B12: =IF(Stock_Card!$B$2="","",IFERROR(SUMIFS(Raw_M!$E$2:$E$2000,Raw_M!$A$2:$A$2000,Stock_Card!$B$2,Raw_M!$F$2:$F$2000,8),"")) -> 317656.61 | C12: =IF(Stock_Card!$B$2="","",IFERROR((SUMIFS(Raw_M!$E$2:$E$2000,Raw_M!$A$2:$A$2000,Stock_Card!$B$2,Raw_M!$F$2:$F$2000,8)/SUMIFS(Raw_M!$E$2:$E$2000,Raw_M!$A$2:$A$2000,Stock_Card!$B$2,Raw_M!$F$2:$F$2000,9)-1),"")) -> -0.20834255 | D12: =IF(Stock_Card!$B$2="","",IFERROR(((SUMIFS(Raw_M!$E$2:$E$2000,Raw_M!$A$2:$A$2000,Stock_Card!$B$2,Raw_M!$F$2:$F$2000,8)/SUMIFS(Raw_M!$E$2:$E$2000,Raw_M!$A$2:$A$2000,Stock_Card!$B$2,Raw_M!$F$2:$F$2000,9)-1)-(SUMIFS(Raw_M!$E$2:$E$2000,Raw_M!$A$2:$A$2000,Stock_Card!$B$2,Raw_M!$F$2:$F$2000,9)/SUMIFS(Raw_M!$E$2:$E$2000,Raw_M!$A$2:$A$2000,Stock_Card!$B$2,Raw_M!$F$2:$F$2000,10)-1))*100,"")) -> -40.610629 | E12: =IF(Stock_Card!$B$2="","",IFERROR(IF(OR(NOT(ISNUMBER((SUMIFS(Raw_M!$E$2:$E$2000,Raw_M!$A$2:$A$2000,Stock_Card!$B$2,Raw_M!$F$2:$F$2000,9)/SUMIFS(Raw_M!$E$2:$E$2000,Raw_M!$A$2:$A$2000,Stock_Card!$B$2,Raw_M!$F$2:$F$2000,10)-1))),(SUMIFS(Raw_M!$E$2:$E$2000,Raw_M!$A$2:$A$2000,Stock_Card!$B$2,Raw_M!$F$2:$F$2000,9)/SUMIFS(Raw_M!$E$2:$E$2000,Raw_M!$A$2:$A$2000,Stock_Card!$B$2,Raw_M!$F$2:$F$2000,10)-1)<=0,ABS((SUMIFS(Raw_M!$E$2:$E$2000,Raw_M!$A$2:$A$2000,Stock_Card!$B$2,Raw_M!$F$2:$F$2000,9)/SUMIFS(Raw_M!$E$2:$E$2000,Raw_M!$A$2:$A$2000,Stock_Card!$B$2,Raw_M!$F$2:$F$2000,10)-1))<Config!$B$9),"N/M",((SUMIFS(Raw_M!$E$2:$E$2000,Raw_M!$A$2:$A$2000,Stock_Card!$B$2,Raw_M!$F$2:$F$2000,8)/SUMIFS(Raw_M!$E$2:$E$2000,Raw_M!$A$2:$A$2000,Stock_Card!$B$2,Raw_M!$F$2:$F$2000,9)-1)-(SUMIFS(Raw_M!$E$2:$E$2000,Raw_M!$A$2:$A$2000,Stock_Card!$B$2,Raw_M!$F$2:$F$2000,9)/SUMIFS(Raw_M!$E$2:$E$2000,Raw_M!$A$2:$A$2000,Stock_Card!$B$2,Raw_M!$F$2:$F$2000,10)-1))/ABS((SUMIFS(Raw_M!$E$2:$E$2000,Raw_M!$A$2:$A$2000,Stock_Card!$B$2,Raw_M!$F$2:$F$2000,9)/SUMIFS(Raw_M!$E$2:$E$2000,Raw_M!$A$2:$A$2000,Stock_Card!$B$2,Raw_M!$F$2:$F$2000,10)-1))),"N/M")) -> -2.0534921 | F12: =IF(Stock_Card!$B$2="","",IFERROR((SUMIFS(Raw_M!$E$2:$E$2000,Raw_M!$A$2:$A$2000,Stock_Card!$B$2,Raw_M!$F$2:$F$2000,8)/SUMIFS(Raw_M!$E$2:$E$2000,Raw_M!$A$2:$A$2000,Stock_Card!$B$2,Raw_M!$F$2:$F$2000,20)-1),"")) -> 0.22171487 | G12: =IF(Stock_Card!$B$2="","",IFERROR(((SUMIFS(Raw_M!$E$2:$E$2000,Raw_M!$A$2:$A$2000,Stock_Card!$B$2,Raw_M!$F$2:$F$2000,8)/SUMIFS(Raw_M!$E$2:$E$2000,Raw_M!$A$2:$A$2000,Stock_Card!$B$2,Raw_M!$F$2:$F$2000,20)-1)-(SUMIFS(Raw_M!$E$2:$E$2000,Raw_M!$A$2:$A$2000,Stock_Card!$B$2,Raw_M!$F$2:$F$2000,9)/SUMIFS(Raw_M!$E$2:$E$2000,Raw_M!$A$2:$A$2000,Stock_Card!$B$2,Raw_M!$F$2:$F$2000,21)-1))*100,"")) -> -14.64116 | H12: =IF(Stock_Card!$B$2="","",IFERROR(IF(OR(NOT(ISNUMBER((SUMIFS(Raw_M!$E$2:$E$2000,Raw_M!$A$2:$A$2000,Stock_Card!$B$2,Raw_M!$F$2:$F$2000,9)/SUMIFS(Raw_M!$E$2:$E$2000,Raw_M!$A$2:$A$2000,Stock_Card!$B$2,Raw_M!$F$2:$F$2000,21)-1))),(SUMIFS(Raw_M!$E$2:$E$2000,Raw_M!$A$2:$A$2000,Stock_Card!$B$2,Raw_M!$F$2:$F$2000,9)/SUMIFS(Raw_M!$E$2:$E$2000,Raw_M!$A$2:$A$2000,Stock_Card!$B$2,Raw_M!$F$2:$F$2000,21)-1)<=0,ABS((SUMIFS(Raw_M!$E$2:$E$2000,Raw_M!$A$2:$A$2000,Stock_Card!$B$2,Raw_M!$F$2:$F$2000,9)/SUMIFS(Raw_M!$E$2:$E$2000,Raw_M!$A$2:$A$2000,Stock_Card!$B$2,Raw_M!$F$2:$F$2000,21)-1))<Config!$B$9),"N/M",((SUMIFS(Raw_M!$E$2:$E$2000,Raw_M!$A$2:$A$2000,Stock_Card!$B$2,Raw_M!$F$2:$F$2000,8)/SUMIFS(Raw_M!$E$2:$E$2000,Raw_M!$A$2:$A$2000,Stock_Card!$B$2,Raw_M!$F$2:$F$2000,20)-1)-(SUMIFS(Raw_M!$E$2:$E$2000,Raw_M!$A$2:$A$2000,Stock_Card!$B$2,Raw_M!$F$2:$F$2000,9)/SUMIFS(Raw_M!$E$2:$E$2000,Raw_M!$A$2:$A$2000,Stock_Card!$B$2,Raw_M!$F$2:$F$2000,21)-1))/ABS((SUMIFS(Raw_M!$E$2:$E$2000,Raw_M!$A$2:$A$2000,Stock_Card!$B$2,Raw_M!$F$2:$F$2000,9)/SUMIFS(Raw_M!$E$2:$E$2000,Raw_M!$A$2:$A$2000,Stock_Card!$B$2,Raw_M!$F$2:$F$2000,21)-1))),"N/M")) -> -0.39772092 | I12: =IF(Stock_Card!$B$2="","",IFERROR(IF(AND((SUMIFS(Raw_M!$E$2:$E$2000,Raw_M!$A$2:$A$2000,Stock_Card!$B$2,Raw_M!$F$2:$F$2000,9)/SUMIFS(Raw_M!$E$2:$E$2000,Raw_M!$A$2:$A$2000,Stock_Card!$B$2,Raw_M!$F$2:$F$2000,21)-1)>0,(SUMIFS(Raw_M!$E$2:$E$2000,Raw_M!$A$2:$A$2000,Stock_Card!$B$2,Raw_M!$F$2:$F$2000,8)/SUMIFS(Raw_M!$E$2:$E$2000,Raw_M!$A$2:$A$2000,Stock_Card!$B$2,Raw_M!$F$2:$F$2000,20)-1)<=0),"由正轉負",IF(AND((SUMIFS(Raw_M!$E$2:$E$2000,Raw_M!$A$2:$A$2000,Stock_Card!$B$2,Raw_M!$F$2:$F$2000,9)/SUMIFS(Raw_M!$E$2:$E$2000,Raw_M!$A$2:$A$2000,Stock_Card!$B$2,Raw_M!$F$2:$F$2000,21)-1)<=0,(SUMIFS(Raw_M!$E$2:$E$2000,Raw_M!$A$2:$A$2000,Stock_Card!$B$2,Raw_M!$F$2:$F$2000,8)/SUMIFS(Raw_M!$E$2:$E$2000,Raw_M!$A$2:$A$2000,Stock_Card!$B$2,Raw_M!$F$2:$F$2000,20)-1)>0),"由負轉正",IF((SUMIFS(Raw_M!$E$2:$E$2000,Raw_M!$A$2:$A$2000,Stock_Card!$B$2,Raw_M!$F$2:$F$2000,8)/SUMIFS(Raw_M!$E$2:$E$2000,Raw_M!$A$2:$A$2000,Stock_Card!$B$2,Raw_M!$F$2:$F$2000,20)-1)>0,IF(((SUMIFS(Raw_M!$E$2:$E$2000,Raw_M!$A$2:$A$2000,Stock_Card!$B$2,Raw_M!$F$2:$F$2000,8)/SUMIFS(Raw_M!$E$2:$E$2000,Raw_M!$A$2:$A$2000,Stock_Card!$B$2,Raw_M!$F$2:$F$2000,20)-1)-(SUMIFS(Raw_M!$E$2:$E$2000,Raw_M!$A$2:$A$2000,Stock_Card!$B$2,Raw_M!$F$2:$F$2000,9)/SUMIFS(Raw_M!$E$2:$E$2000,Raw_M!$A$2:$A$2000,Stock_Card!$B$2,Raw_M!$F$2:$F$2000,21)-1))*100>0,"成長且加速","成長但減速"),IF(((SUMIFS(Raw_M!$E$2:$E$2000,Raw_M!$A$2:$A$2000,Stock_Card!$B$2,Raw_M!$F$2:$F$2000,8)/SUMIFS(Raw_M!$E$2:$E$2000,Raw_M!$A$2:$A$2000,Stock_Card!$B$2,Raw_M!$F$2:$F$2000,20)-1)-(SUMIFS(Raw_M!$E$2:$E$2000,Raw_M!$A$2:$A$2000,Stock_Card!$B$2,Raw_M!$F$2:$F$2000,9)/SUMIFS(Raw_M!$E$2:$E$2000,Raw_M!$A$2:$A$2000,Stock_Card!$B$2,Raw_M!$F$2:$F$2000,21)-1))*100>0,"衰退但收斂","衰退且惡化")))),"")) -> 成長但減速 | J12: =IF(Stock_Card!$B$2="","",IFERROR(SUMIFS(Raw_M!$E$2:$E$2000,Raw_M!$A$2:$A$2000,Stock_Card!$B$2,Raw_M!$C$2:$C$2000,">="&((INT(SUMIFS(Raw_M!$C$2:$C$2000,Raw_M!$A$2:$A$2000,Stock_Card!$B$2,Raw_M!$F$2:$F$2000,8)/100)-0)*100+1),Raw_M!$C$2:$C$2000,"<="&((INT(SUMIFS(Raw_M!$C$2:$C$2000,Raw_M!$A$2:$A$2000,Stock_Card!$B$2,Raw_M!$F$2:$F$2000,8)/100)-0)*100+MOD(SUMIFS(Raw_M!$C$2:$C$2000,Raw_M!$A$2:$A$2000,Stock_Card!$B$2,Raw_M!$F$2:$F$2000,8),100))),"")) -> 1053915.3 | K12: =IF(Stock_Card!$B$2="","",IFERROR(IF(OR(COUNTIFS(Raw_M!$A$2:$A$2000,Stock_Card!$B$2,Raw_M!$C$2:$C$2000,">="&((INT(SUMIFS(Raw_M!$C$2:$C$2000,Raw_M!$A$2:$A$2000,Stock_Card!$B$2,Raw_M!$F$2:$F$2000,8)/100)-0)*100+1),Raw_M!$C$2:$C$2000,"<="&((INT(SUMIFS(Raw_M!$C$2:$C$2000,Raw_M!$A$2:$A$2000,Stock_Card!$B$2,Raw_M!$F$2:$F$2000,8)/100)-0)*100+MOD(SUMIFS(Raw_M!$C$2:$C$2000,Raw_M!$A$2:$A$2000,Stock_Card!$B$2,Raw_M!$F$2:$F$2000,8),100)))<>MOD(SUMIFS(Raw_M!$C$2:$C$2000,Raw_M!$A$2:$A$2000,Stock_Card!$B$2,Raw_M!$F$2:$F$2000,8),100),COUNTIFS(Raw_M!$A$2:$A$2000,Stock_Card!$B$2,Raw_M!$C$2:$C$2000,">="&((INT(SUMIFS(Raw_M!$C$2:$C$2000,Raw_M!$A$2:$A$2000,Stock_Card!$B$2,Raw_M!$F$2:$F$2000,8)/100)-1)*100+1),Raw_M!$C$2:$C$2000,"<="&((INT(SUMIFS(Raw_M!$C$2:$C$2000,Raw_M!$A$2:$A$2000,Stock_Card!$B$2,Raw_M!$F$2:$F$2000,8)/100)-1)*100+MOD(SUMIFS(Raw_M!$C$2:$C$2000,Raw_M!$A$2:$A$2000,Stock_Card!$B$2,Raw_M!$F$2:$F$2000,8),100)))<>MOD(SUMIFS(Raw_M!$C$2:$C$2000,Raw_M!$A$2:$A$2000,Stock_Card!$B$2,Raw_M!$F$2:$F$2000,8),100)),"N/M",SUMIFS(Raw_M!$E$2:$E$2000,Raw_M!$A$2:$A$2000,Stock_Card!$B$2,Raw_M!$C$2:$C$2000,">="&((INT(SUMIFS(Raw_M!$C$2:$C$2000,Raw_M!$A$2:$A$2000,Stock_Card!$B$2,Raw_M!$F$2:$F$2000,8)/100)-0)*100+1),Raw_M!$C$2:$C$2000,"<="&((INT(SUMIFS(Raw_M!$C$2:$C$2000,Raw_M!$A$2:$A$2000,Stock_Card!$B$2,Raw_M!$F$2:$F$2000,8)/100)-0)*100+MOD(SUMIFS(Raw_M!$C$2:$C$2000,Raw_M!$A$2:$A$2000,Stock_Card!$B$2,Raw_M!$F$2:$F$2000,8),100)))/SUMIFS(Raw_M!$E$2:$E$2000,Raw_M!$A$2:$A$2000,Stock_Card!$B$2,Raw_M!$C$2:$C$2000,">="&((INT(SUMIFS(Raw_M!$C$2:$C$2000,Raw_M!$A$2:$A$2000,Stock_Card!$B$2,Raw_M!$F$2:$F$2000,8)/100)-1)*100+1),Raw_M!$C$2:$C$2000,"<="&((INT(SUMIFS(Raw_M!$C$2:$C$2000,Raw_M!$A$2:$A$2000,Stock_Card!$B$2,Raw_M!$F$2:$F$2000,8)/100)-1)*100+MOD(SUMIFS(Raw_M!$C$2:$C$2000,Raw_M!$A$2:$A$2000,Stock_Card!$B$2,Raw_M!$F$2:$F$2000,8),100)))-1),"N/M")) -> 0.26754791
A13: =IF(Stock_Card!$B$2="","",IFERROR(INDEX(Raw_M!$B$2:$B$2000,MATCH(Stock_Card!$B$2&"|9",Raw_M!$G$2:$G$2000,0)),"")) -> 2026-02 | B13: =IF(Stock_Card!$B$2="","",IFERROR(SUMIFS(Raw_M!$E$2:$E$2000,Raw_M!$A$2:$A$2000,Stock_Card!$B$2,Raw_M!$F$2:$F$2000,9),"")) -> 401255.13 | C13: =IF(Stock_Card!$B$2="","",IFERROR((SUMIFS(Raw_M!$E$2:$E$2000,Raw_M!$A$2:$A$2000,Stock_Card!$B$2,Raw_M!$F$2:$F$2000,9)/SUMIFS(Raw_M!$E$2:$E$2000,Raw_M!$A$2:$A$2000,Stock_Card!$B$2,Raw_M!$F$2:$F$2000,10)-1),"")) -> 0.19776374 | D13: =IF(Stock_Card!$B$2="","",IFERROR(((SUMIFS(Raw_M!$E$2:$E$2000,Raw_M!$A$2:$A$2000,Stock_Card!$B$2,Raw_M!$F$2:$F$2000,9)/SUMIFS(Raw_M!$E$2:$E$2000,Raw_M!$A$2:$A$2000,Stock_Card!$B$2,Raw_M!$F$2:$F$2000,10)-1)-(SUMIFS(Raw_M!$E$2:$E$2000,Raw_M!$A$2:$A$2000,Stock_Card!$B$2,Raw_M!$F$2:$F$2000,10)/SUMIFS(Raw_M!$E$2:$E$2000,Raw_M!$A$2:$A$2000,Stock_Card!$B$2,Raw_M!$F$2:$F$2000,11)-1))*100,"")) -> 22.282163 | E13: =IF(Stock_Card!$B$2="","",IFERROR(IF(OR(NOT(ISNUMBER((SUMIFS(Raw_M!$E$2:$E$2000,Raw_M!$A$2:$A$2000,Stock_Card!$B$2,Raw_M!$F$2:$F$2000,10)/SUMIFS(Raw_M!$E$2:$E$2000,Raw_M!$A$2:$A$2000,Stock_Card!$B$2,Raw_M!$F$2:$F$2000,11)-1))),(SUMIFS(Raw_M!$E$2:$E$2000,Raw_M!$A$2:$A$2000,Stock_Card!$B$2,Raw_M!$F$2:$F$2000,10)/SUMIFS(Raw_M!$E$2:$E$2000,Raw_M!$A$2:$A$2000,Stock_Card!$B$2,Raw_M!$F$2:$F$2000,11)-1)<=0,ABS((SUMIFS(Raw_M!$E$2:$E$2000,Raw_M!$A$2:$A$2000,Stock_Card!$B$2,Raw_M!$F$2:$F$2000,10)/SUMIFS(Raw_M!$E$2:$E$2000,Raw_M!$A$2:$A$2000,Stock_Card!$B$2,Raw_M!$F$2:$F$2000,11)-1))<Config!$B$9),"N/M",((SUMIFS(Raw_M!$E$2:$E$2000,Raw_M!$A$2:$A$2000,Stock_Card!$B$2,Raw_M!$F$2:$F$2000,9)/SUMIFS(Raw_M!$E$2:$E$2000,Raw_M!$A$2:$A$2000,Stock_Card!$B$2,Raw_M!$F$2:$F$2000,10)-1)-(SUMIFS(Raw_M!$E$2:$E$2000,Raw_M!$A$2:$A$2000,Stock_Card!$B$2,Raw_M!$F$2:$F$2000,10)/SUMIFS(Raw_M!$E$2:$E$2000,Raw_M!$A$2:$A$2000,Stock_Card!$B$2,Raw_M!$F$2:$F$2000,11)-1))/ABS((SUMIFS(Raw_M!$E$2:$E$2000,Raw_M!$A$2:$A$2000,Stock_Card!$B$2,Raw_M!$F$2:$F$2000,10)/SUMIFS(Raw_M!$E$2:$E$2000,Raw_M!$A$2:$A$2000,Stock_Card!$B$2,Raw_M!$F$2:$F$2000,11)-1))),"N/M")) -> N/M | F13: =IF(Stock_Card!$B$2="","",IFERROR((SUMIFS(Raw_M!$E$2:$E$2000,Raw_M!$A$2:$A$2000,Stock_Card!$B$2,Raw_M!$F$2:$F$2000,9)/SUMIFS(Raw_M!$E$2:$E$2000,Raw_M!$A$2:$A$2000,Stock_Card!$B$2,Raw_M!$F$2:$F$2000,21)-1),"")) -> 0.36812647 | G13: =IF(Stock_Card!$B$2="","",IFERROR(((SUMIFS(Raw_M!$E$2:$E$2000,Raw_M!$A$2:$A$2000,Stock_Card!$B$2,Raw_M!$F$2:$F$2000,9)/SUMIFS(Raw_M!$E$2:$E$2000,Raw_M!$A$2:$A$2000,Stock_Card!$B$2,Raw_M!$F$2:$F$2000,21)-1)-(SUMIFS(Raw_M!$E$2:$E$2000,Raw_M!$A$2:$A$2000,Stock_Card!$B$2,Raw_M!$F$2:$F$2000,10)/SUMIFS(Raw_M!$E$2:$E$2000,Raw_M!$A$2:$A$2000,Stock_Card!$B$2,Raw_M!$F$2:$F$2000,22)-1))*100,"")) -> 16.378427 | H13: =IF(Stock_Card!$B$2="","",IFERROR(IF(OR(NOT(ISNUMBER((SUMIFS(Raw_M!$E$2:$E$2000,Raw_M!$A$2:$A$2000,Stock_Card!$B$2,Raw_M!$F$2:$F$2000,10)/SUMIFS(Raw_M!$E$2:$E$2000,Raw_M!$A$2:$A$2000,Stock_Card!$B$2,Raw_M!$F$2:$F$2000,22)-1))),(SUMIFS(Raw_M!$E$2:$E$2000,Raw_M!$A$2:$A$2000,Stock_Card!$B$2,Raw_M!$F$2:$F$2000,10)/SUMIFS(Raw_M!$E$2:$E$2000,Raw_M!$A$2:$A$2000,Stock_Card!$B$2,Raw_M!$F$2:$F$2000,22)-1)<=0,ABS((SUMIFS(Raw_M!$E$2:$E$2000,Raw_M!$A$2:$A$2000,Stock_Card!$B$2,Raw_M!$F$2:$F$2000,10)/SUMIFS(Raw_M!$E$2:$E$2000,Raw_M!$A$2:$A$2000,Stock_Card!$B$2,Raw_M!$F$2:$F$2000,22)-1))<Config!$B$9),"N/M",((SUMIFS(Raw_M!$E$2:$E$2000,Raw_M!$A$2:$A$2000,Stock_Card!$B$2,Raw_M!$F$2:$F$2000,9)/SUMIFS(Raw_M!$E$2:$E$2000,Raw_M!$A$2:$A$2000,Stock_Card!$B$2,Raw_M!$F$2:$F$2000,21)-1)-(SUMIFS(Raw_M!$E$2:$E$2000,Raw_M!$A$2:$A$2000,Stock_Card!$B$2,Raw_M!$F$2:$F$2000,10)/SUMIFS(Raw_M!$E$2:$E$2000,Raw_M!$A$2:$A$2000,Stock_Card!$B$2,Raw_M!$F$2:$F$2000,22)-1))/ABS((SUMIFS(Raw_M!$E$2:$E$2000,Raw_M!$A$2:$A$2000,Stock_Card!$B$2,Raw_M!$F$2:$F$2000,10)/SUMIFS(Raw_M!$E$2:$E$2000,Raw_M!$A$2:$A$2000,Stock_Card!$B$2,Raw_M!$F$2:$F$2000,22)-1))),"N/M")) -> 0.80151956 | I13: =IF(Stock_Card!$B$2="","",IFERROR(IF(AND((SUMIFS(Raw_M!$E$2:$E$2000,Raw_M!$A$2:$A$2000,Stock_Card!$B$2,Raw_M!$F$2:$F$2000,10)/SUMIFS(Raw_M!$E$2:$E$2000,Raw_M!$A$2:$A$2000,Stock_Card!$B$2,Raw_M!$F$2:$F$2000,22)-1)>0,(SUMIFS(Raw_M!$E$2:$E$2000,Raw_M!$A$2:$A$2000,Stock_Card!$B$2,Raw_M!$F$2:$F$2000,9)/SUMIFS(Raw_M!$E$2:$E$2000,Raw_M!$A$2:$A$2000,Stock_Card!$B$2,Raw_M!$F$2:$F$2000,21)-1)<=0),"由正轉負",IF(AND((SUMIFS(Raw_M!$E$2:$E$2000,Raw_M!$A$2:$A$2000,Stock_Card!$B$2,Raw_M!$F$2:$F$2000,10)/SUMIFS(Raw_M!$E$2:$E$2000,Raw_M!$A$2:$A$2000,Stock_Card!$B$2,Raw_M!$F$2:$F$2000,22)-1)<=0,(SUMIFS(Raw_M!$E$2:$E$2000,Raw_M!$A$2:$A$2000,Stock_Card!$B$2,Raw_M!$F$2:$F$2000,9)/SUMIFS(Raw_M!$E$2:$E$2000,Raw_M!$A$2:$A$2000,Stock_Card!$B$2,Raw_M!$F$2:$F$2000,21)-1)>0),"由負轉正",IF((SUMIFS(Raw_M!$E$2:$E$2000,Raw_M!$A$2:$A$2000,Stock_Card!$B$2,Raw_M!$F$2:$F$2000,9)/SUMIFS(Raw_M!$E$2:$E$2000,Raw_M!$A$2:$A$2000,Stock_Card!$B$2,Raw_M!$F$2:$F$2000,21)-1)>0,IF(((SUMIFS(Raw_M!$E$2:$E$2000,Raw_M!$A$2:$A$2000,Stock_Card!$B$2,Raw_M!$F$2:$F$2000,9)/SUMIFS(Raw_M!$E$2:$E$2000,Raw_M!$A$2:$A$2000,Stock_Card!$B$2,Raw_M!$F$2:$F$2000,21)-1)-(SUMIFS(Raw_M!$E$2:$E$2000,Raw_M!$A$2:$A$2000,Stock_Card!$B$2,Raw_M!$F$2:$F$2000,10)/SUMIFS(Raw_M!$E$2:$E$2000,Raw_M!$A$2:$A$2000,Stock_Card!$B$2,Raw_M!$F$2:$F$2000,22)-1))*100>0,"成長且加速","成長但減速"),IF(((SUMIFS(Raw_M!$E$2:$E$2000,Raw_M!$A$2:$A$2000,Stock_Card!$B$2,Raw_M!$F$2:$F$2000,9)/SUMIFS(Raw_M!$E$2:$E$2000,Raw_M!$A$2:$A$2000,Stock_Card!$B$2,Raw_M!$F$2:$F$2000,21)-1)-(SUMIFS(Raw_M!$E$2:$E$2000,Raw_M!$A$2:$A$2000,Stock_Card!$B$2,Raw_M!$F$2:$F$2000,10)/SUMIFS(Raw_M!$E$2:$E$2000,Raw_M!$A$2:$A$2000,Stock_Card!$B$2,Raw_M!$F$2:$F$2000,22)-1))*100>0,"衰退但收斂","衰退且惡化")))),"")) -> 成長且加速 | J13: =IF(Stock_Card!$B$2="","",IFERROR(SUMIFS(Raw_M!$E$2:$E$2000,Raw_M!$A$2:$A$2000,Stock_Card!$B$2,Raw_M!$C$2:$C$2000,">="&((INT(SUMIFS(Raw_M!$C$2:$C$2000,Raw_M!$A$2:$A$2000,Stock_Card!$B$2,Raw_M!$F$2:$F$2000,9)/100)-0)*100+1),Raw_M!$C$2:$C$2000,"<="&((INT(SUMIFS(Raw_M!$C$2:$C$2000,Raw_M!$A$2:$A$2000,Stock_Card!$B$2,Raw_M!$F$2:$F$2000,9)/100)-0)*100+MOD(SUMIFS(Raw_M!$C$2:$C$2000,Raw_M!$A$2:$A$2000,Stock_Card!$B$2,Raw_M!$F$2:$F$2000,9),100))),"")) -> 736258.7 | K13: =IF(Stock_Card!$B$2="","",IFERROR(IF(OR(COUNTIFS(Raw_M!$A$2:$A$2000,Stock_Card!$B$2,Raw_M!$C$2:$C$2000,">="&((INT(SUMIFS(Raw_M!$C$2:$C$2000,Raw_M!$A$2:$A$2000,Stock_Card!$B$2,Raw_M!$F$2:$F$2000,9)/100)-0)*100+1),Raw_M!$C$2:$C$2000,"<="&((INT(SUMIFS(Raw_M!$C$2:$C$2000,Raw_M!$A$2:$A$2000,Stock_Card!$B$2,Raw_M!$F$2:$F$2000,9)/100)-0)*100+MOD(SUMIFS(Raw_M!$C$2:$C$2000,Raw_M!$A$2:$A$2000,Stock_Card!$B$2,Raw_M!$F$2:$F$2000,9),100)))<>MOD(SUMIFS(Raw_M!$C$2:$C$2000,Raw_M!$A$2:$A$2000,Stock_Card!$B$2,Raw_M!$F$2:$F$2000,9),100),COUNTIFS(Raw_M!$A$2:$A$2000,Stock_Card!$B$2,Raw_M!$C$2:$C$2000,">="&((INT(SUMIFS(Raw_M!$C$2:$C$2000,Raw_M!$A$2:$A$2000,Stock_Card!$B$2,Raw_M!$F$2:$F$2000,9)/100)-1)*100+1),Raw_M!$C$2:$C$2000,"<="&((INT(SUMIFS(Raw_M!$C$2:$C$2000,Raw_M!$A$2:$A$2000,Stock_Card!$B$2,Raw_M!$F$2:$F$2000,9)/100)-1)*100+MOD(SUMIFS(Raw_M!$C$2:$C$2000,Raw_M!$A$2:$A$2000,Stock_Card!$B$2,Raw_M!$F$2:$F$2000,9),100)))<>MOD(SUMIFS(Raw_M!$C$2:$C$2000,Raw_M!$A$2:$A$2000,Stock_Card!$B$2,Raw_M!$F$2:$F$2000,9),100)),"N/M",SUMIFS(Raw_M!$E$2:$E$2000,Raw_M!$A$2:$A$2000,Stock_Card!$B$2,Raw_M!$C$2:$C$2000,">="&((INT(SUMIFS(Raw_M!$C$2:$C$2000,Raw_M!$A$2:$A$2000,Stock_Card!$B$2,Raw_M!$F$2:$F$2000,9)/100)-0)*100+1),Raw_M!$C$2:$C$2000,"<="&((INT(SUMIFS(Raw_M!$C$2:$C$2000,Raw_M!$A$2:$A$2000,Stock_Card!$B$2,Raw_M!$F$2:$F$2000,9)/100)-0)*100+MOD(SUMIFS(Raw_M!$C$2:$C$2000,Raw_M!$A$2:$A$2000,Stock_Card!$B$2,Raw_M!$F$2:$F$2000,9),100)))/SUMIFS(Raw_M!$E$2:$E$2000,Raw_M!$A$2:$A$2000,Stock_Card!$B$2,Raw_M!$C$2:$C$2000,">="&((INT(SUMIFS(Raw_M!$C$2:$C$2000,Raw_M!$A$2:$A$2000,Stock_Card!$B$2,Raw_M!$F$2:$F$2000,9)/100)-1)*100+1),Raw_M!$C$2:$C$2000,"<="&((INT(SUMIFS(Raw_M!$C$2:$C$2000,Raw_M!$A$2:$A$2000,Stock_Card!$B$2,Raw_M!$F$2:$F$2000,9)/100)-1)*100+MOD(SUMIFS(Raw_M!$C$2:$C$2000,Raw_M!$A$2:$A$2000,Stock_Card!$B$2,Raw_M!$F$2:$F$2000,9),100)))-1),"N/M")) -> 0.28840182
A14: =IF(Stock_Card!$B$2="","",IFERROR(INDEX(Raw_M!$B$2:$B$2000,MATCH(Stock_Card!$B$2&"|10",Raw_M!$G$2:$G$2000,0)),"")) -> 2026-01 | B14: =IF(Stock_Card!$B$2="","",IFERROR(SUMIFS(Raw_M!$E$2:$E$2000,Raw_M!$A$2:$A$2000,Stock_Card!$B$2,Raw_M!$F$2:$F$2000,10),"")) -> 335003.57 | C14: =IF(Stock_Card!$B$2="","",IFERROR((SUMIFS(Raw_M!$E$2:$E$2000,Raw_M!$A$2:$A$2000,Stock_Card!$B$2,Raw_M!$F$2:$F$2000,10)/SUMIFS(Raw_M!$E$2:$E$2000,Raw_M!$A$2:$A$2000,Stock_Card!$B$2,Raw_M!$F$2:$F$2000,11)-1),"")) -> -0.025057882 | D14: =IF(Stock_Card!$B$2="","",IFERROR(((SUMIFS(Raw_M!$E$2:$E$2000,Raw_M!$A$2:$A$2000,Stock_Card!$B$2,Raw_M!$F$2:$F$2000,10)/SUMIFS(Raw_M!$E$2:$E$2000,Raw_M!$A$2:$A$2000,Stock_Card!$B$2,Raw_M!$F$2:$F$2000,11)-1)-(SUMIFS(Raw_M!$E$2:$E$2000,Raw_M!$A$2:$A$2000,Stock_Card!$B$2,Raw_M!$F$2:$F$2000,11)/SUMIFS(Raw_M!$E$2:$E$2000,Raw_M!$A$2:$A$2000,Stock_Card!$B$2,Raw_M!$F$2:$F$2000,12)-1))*100,"")) -> 3.9870006 | E14: =IF(Stock_Card!$B$2="","",IFERROR(IF(OR(NOT(ISNUMBER((SUMIFS(Raw_M!$E$2:$E$2000,Raw_M!$A$2:$A$2000,Stock_Card!$B$2,Raw_M!$F$2:$F$2000,11)/SUMIFS(Raw_M!$E$2:$E$2000,Raw_M!$A$2:$A$2000,Stock_Card!$B$2,Raw_M!$F$2:$F$2000,12)-1))),(SUMIFS(Raw_M!$E$2:$E$2000,Raw_M!$A$2:$A$2000,Stock_Card!$B$2,Raw_M!$F$2:$F$2000,11)/SUMIFS(Raw_M!$E$2:$E$2000,Raw_M!$A$2:$A$2000,Stock_Card!$B$2,Raw_M!$F$2:$F$2000,12)-1)<=0,ABS((SUMIFS(Raw_M!$E$2:$E$2000,Raw_M!$A$2:$A$2000,Stock_Card!$B$2,Raw_M!$F$2:$F$2000,11)/SUMIFS(Raw_M!$E$2:$E$2000,Raw_M!$A$2:$A$2000,Stock_Card!$B$2,Raw_M!$F$2:$F$2000,12)-1))<Config!$B$9),"N/M",((SUMIFS(Raw_M!$E$2:$E$2000,Raw_M!$A$2:$A$2000,Stock_Card!$B$2,Raw_M!$F$2:$F$2000,10)/SUMIFS(Raw_M!$E$2:$E$2000,Raw_M!$A$2:$A$2000,Stock_Card!$B$2,Raw_M!$F$2:$F$2000,11)-1)-(SUMIFS(Raw_M!$E$2:$E$2000,Raw_M!$A$2:$A$2000,Stock_Card!$B$2,Raw_M!$F$2:$F$2000,11)/SUMIFS(Raw_M!$E$2:$E$2000,Raw_M!$A$2:$A$2000,Stock_Card!$B$2,Raw_M!$F$2:$F$2000,12)-1))/ABS((SUMIFS(Raw_M!$E$2:$E$2000,Raw_M!$A$2:$A$2000,Stock_Card!$B$2,Raw_M!$F$2:$F$2000,11)/SUMIFS(Raw_M!$E$2:$E$2000,Raw_M!$A$2:$A$2000,Stock_Card!$B$2,Raw_M!$F$2:$F$2000,12)-1))),"N/M")) -> N/M | F14: =IF(Stock_Card!$B$2="","",IFERROR((SUMIFS(Raw_M!$E$2:$E$2000,Raw_M!$A$2:$A$2000,Stock_Card!$B$2,Raw_M!$F$2:$F$2000,10)/SUMIFS(Raw_M!$E$2:$E$2000,Raw_M!$A$2:$A$2000,Stock_Card!$B$2,Raw_M!$F$2:$F$2000,22)-1),"")) -> 0.2043422 | G14: =IF(Stock_Card!$B$2="","",IFERROR(((SUMIFS(Raw_M!$E$2:$E$2000,Raw_M!$A$2:$A$2000,Stock_Card!$B$2,Raw_M!$F$2:$F$2000,10)/SUMIFS(Raw_M!$E$2:$E$2000,Raw_M!$A$2:$A$2000,Stock_Card!$B$2,Raw_M!$F$2:$F$2000,22)-1)-(SUMIFS(Raw_M!$E$2:$E$2000,Raw_M!$A$2:$A$2000,Stock_Card!$B$2,Raw_M!$F$2:$F$2000,11)/SUMIFS(Raw_M!$E$2:$E$2000,Raw_M!$A$2:$A$2000,Stock_Card!$B$2,Raw_M!$F$2:$F$2000,23)-1))*100,"")) -> -4.0372159 | H14: =IF(Stock_Card!$B$2="","",IFERROR(IF(OR(NOT(ISNUMBER((SUMIFS(Raw_M!$E$2:$E$2000,Raw_M!$A$2:$A$2000,Stock_Card!$B$2,Raw_M!$F$2:$F$2000,11)/SUMIFS(Raw_M!$E$2:$E$2000,Raw_M!$A$2:$A$2000,Stock_Card!$B$2,Raw_M!$F$2:$F$2000,23)-1))),(SUMIFS(Raw_M!$E$2:$E$2000,Raw_M!$A$2:$A$2000,Stock_Card!$B$2,Raw_M!$F$2:$F$2000,11)/SUMIFS(Raw_M!$E$2:$E$2000,Raw_M!$A$2:$A$2000,Stock_Card!$B$2,Raw_M!$F$2:$F$2000,23)-1)<=0,ABS((SUMIFS(Raw_M!$E$2:$E$2000,Raw_M!$A$2:$A$2000,Stock_Card!$B$2,Raw_M!$F$2:$F$2000,11)/SUMIFS(Raw_M!$E$2:$E$2000,Raw_M!$A$2:$A$2000,Stock_Card!$B$2,Raw_M!$F$2:$F$2000,23)-1))<Config!$B$9),"N/M",((SUMIFS(Raw_M!$E$2:$E$2000,Raw_M!$A$2:$A$2000,Stock_Card!$B$2,Raw_M!$F$2:$F$2000,10)/SUMIFS(Raw_M!$E$2:$E$2000,Raw_M!$A$2:$A$2000,Stock_Card!$B$2,Raw_M!$F$2:$F$2000,22)-1)-(SUMIFS(Raw_M!$E$2:$E$2000,Raw_M!$A$2:$A$2000,Stock_Card!$B$2,Raw_M!$F$2:$F$2000,11)/SUMIFS(Raw_M!$E$2:$E$2000,Raw_M!$A$2:$A$2000,Stock_Card!$B$2,Raw_M!$F$2:$F$2000,23)-1))/ABS((SUMIFS(Raw_M!$E$2:$E$2000,Raw_M!$A$2:$A$2000,Stock_Card!$B$2,Raw_M!$F$2:$F$2000,11)/SUMIFS(Raw_M!$E$2:$E$2000,Raw_M!$A$2:$A$2000,Stock_Card!$B$2,Raw_M!$F$2:$F$2000,23)-1))),"N/M")) -> -0.16497667 | I14: =IF(Stock_Card!$B$2="","",IFERROR(IF(AND((SUMIFS(Raw_M!$E$2:$E$2000,Raw_M!$A$2:$A$2000,Stock_Card!$B$2,Raw_M!$F$2:$F$2000,11)/SUMIFS(Raw_M!$E$2:$E$2000,Raw_M!$A$2:$A$2000,Stock_Card!$B$2,Raw_M!$F$2:$F$2000,23)-1)>0,(SUMIFS(Raw_M!$E$2:$E$2000,Raw_M!$A$2:$A$2000,Stock_Card!$B$2,Raw_M!$F$2:$F$2000,10)/SUMIFS(Raw_M!$E$2:$E$2000,Raw_M!$A$2:$A$2000,Stock_Card!$B$2,Raw_M!$F$2:$F$2000,22)-1)<=0),"由正轉負",IF(AND((SUMIFS(Raw_M!$E$2:$E$2000,Raw_M!$A$2:$A$2000,Stock_Card!$B$2,Raw_M!$F$2:$F$2000,11)/SUMIFS(Raw_M!$E$2:$E$2000,Raw_M!$A$2:$A$2000,Stock_Card!$B$2,Raw_M!$F$2:$F$2000,23)-1)<=0,(SUMIFS(Raw_M!$E$2:$E$2000,Raw_M!$A$2:$A$2000,Stock_Card!$B$2,Raw_M!$F$2:$F$2000,10)/SUMIFS(Raw_M!$E$2:$E$2000,Raw_M!$A$2:$A$2000,Stock_Card!$B$2,Raw_M!$F$2:$F$2000,22)-1)>0),"由負轉正",IF((SUMIFS(Raw_M!$E$2:$E$2000,Raw_M!$A$2:$A$2000,Stock_Card!$B$2,Raw_M!$F$2:$F$2000,10)/SUMIFS(Raw_M!$E$2:$E$2000,Raw_M!$A$2:$A$2000,Stock_Card!$B$2,Raw_M!$F$2:$F$2000,22)-1)>0,IF(((SUMIFS(Raw_M!$E$2:$E$2000,Raw_M!$A$2:$A$2000,Stock_Card!$B$2,Raw_M!$F$2:$F$2000,10)/SUMIFS(Raw_M!$E$2:$E$2000,Raw_M!$A$2:$A$2000,Stock_Card!$B$2,Raw_M!$F$2:$F$2000,22)-1)-(SUMIFS(Raw_M!$E$2:$E$2000,Raw_M!$A$2:$A$2000,Stock_Card!$B$2,Raw_M!$F$2:$F$2000,11)/SUMIFS(Raw_M!$E$2:$E$2000,Raw_M!$A$2:$A$2000,Stock_Card!$B$2,Raw_M!$F$2:$F$2000,23)-1))*100>0,"成長且加速","成長但減速"),IF(((SUMIFS(Raw_M!$E$2:$E$2000,Raw_M!$A$2:$A$2000,Stock_Card!$B$2,Raw_M!$F$2:$F$2000,10)/SUMIFS(Raw_M!$E$2:$E$2000,Raw_M!$A$2:$A$2000,Stock_Card!$B$2,Raw_M!$F$2:$F$2000,22)-1)-(SUMIFS(Raw_M!$E$2:$E$2000,Raw_M!$A$2:$A$2000,Stock_Card!$B$2,Raw_M!$F$2:$F$2000,11)/SUMIFS(Raw_M!$E$2:$E$2000,Raw_M!$A$2:$A$2000,Stock_Card!$B$2,Raw_M!$F$2:$F$2000,23)-1))*100>0,"衰退但收斂","衰退且惡化")))),"")) -> 成長但減速 | J14: =IF(Stock_Card!$B$2="","",IFERROR(SUMIFS(Raw_M!$E$2:$E$2000,Raw_M!$A$2:$A$2000,Stock_Card!$B$2,Raw_M!$C$2:$C$2000,">="&((INT(SUMIFS(Raw_M!$C$2:$C$2000,Raw_M!$A$2:$A$2000,Stock_Card!$B$2,Raw_M!$F$2:$F$2000,10)/100)-0)*100+1),Raw_M!$C$2:$C$2000,"<="&((INT(SUMIFS(Raw_M!$C$2:$C$2000,Raw_M!$A$2:$A$2000,Stock_Card!$B$2,Raw_M!$F$2:$F$2000,10)/100)-0)*100+MOD(SUMIFS(Raw_M!$C$2:$C$2000,Raw_M!$A$2:$A$2000,Stock_Card!$B$2,Raw_M!$F$2:$F$2000,10),100))),"")) -> 335003.57 | K14: =IF(Stock_Card!$B$2="","",IFERROR(IF(OR(COUNTIFS(Raw_M!$A$2:$A$2000,Stock_Card!$B$2,Raw_M!$C$2:$C$2000,">="&((INT(SUMIFS(Raw_M!$C$2:$C$2000,Raw_M!$A$2:$A$2000,Stock_Card!$B$2,Raw_M!$F$2:$F$2000,10)/100)-0)*100+1),Raw_M!$C$2:$C$2000,"<="&((INT(SUMIFS(Raw_M!$C$2:$C$2000,Raw_M!$A$2:$A$2000,Stock_Card!$B$2,Raw_M!$F$2:$F$2000,10)/100)-0)*100+MOD(SUMIFS(Raw_M!$C$2:$C$2000,Raw_M!$A$2:$A$2000,Stock_Card!$B$2,Raw_M!$F$2:$F$2000,10),100)))<>MOD(SUMIFS(Raw_M!$C$2:$C$2000,Raw_M!$A$2:$A$2000,Stock_Card!$B$2,Raw_M!$F$2:$F$2000,10),100),COUNTIFS(Raw_M!$A$2:$A$2000,Stock_Card!$B$2,Raw_M!$C$2:$C$2000,">="&((INT(SUMIFS(Raw_M!$C$2:$C$2000,Raw_M!$A$2:$A$2000,Stock_Card!$B$2,Raw_M!$F$2:$F$2000,10)/100)-1)*100+1),Raw_M!$C$2:$C$2000,"<="&((INT(SUMIFS(Raw_M!$C$2:$C$2000,Raw_M!$A$2:$A$2000,Stock_Card!$B$2,Raw_M!$F$2:$F$2000,10)/100)-1)*100+MOD(SUMIFS(Raw_M!$C$2:$C$2000,Raw_M!$A$2:$A$2000,Stock_Card!$B$2,Raw_M!$F$2:$F$2000,10),100)))<>MOD(SUMIFS(Raw_M!$C$2:$C$2000,Raw_M!$A$2:$A$2000,Stock_Card!$B$2,Raw_M!$F$2:$F$2000,10),100)),"N/M",SUMIFS(Raw_M!$E$2:$E$2000,Raw_M!$A$2:$A$2000,Stock_Card!$B$2,Raw_M!$C$2:$C$2000,">="&((INT(SUMIFS(Raw_M!$C$2:$C$2000,Raw_M!$A$2:$A$2000,Stock_Card!$B$2,Raw_M!$F$2:$F$2000,10)/100)-0)*100+1),Raw_M!$C$2:$C$2000,"<="&((INT(SUMIFS(Raw_M!$C$2:$C$2000,Raw_M!$A$2:$A$2000,Stock_Card!$B$2,Raw_M!$F$2:$F$2000,10)/100)-0)*100+MOD(SUMIFS(Raw_M!$C$2:$C$2000,Raw_M!$A$2:$A$2000,Stock_Card!$B$2,Raw_M!$F$2:$F$2000,10),100)))/SUMIFS(Raw_M!$E$2:$E$2000,Raw_M!$A$2:$A$2000,Stock_Card!$B$2,Raw_M!$C$2:$C$2000,">="&((INT(SUMIFS(Raw_M!$C$2:$C$2000,Raw_M!$A$2:$A$2000,Stock_Card!$B$2,Raw_M!$F$2:$F$2000,10)/100)-1)*100+1),Raw_M!$C$2:$C$2000,"<="&((INT(SUMIFS(Raw_M!$C$2:$C$2000,Raw_M!$A$2:$A$2000,Stock_Card!$B$2,Raw_M!$F$2:$F$2000,10)/100)-1)*100+MOD(SUMIFS(Raw_M!$C$2:$C$2000,Raw_M!$A$2:$A$2000,Stock_Card!$B$2,Raw_M!$F$2:$F$2000,10),100)))-1),"N/M")) -> 0.2043422
